Workbook

Sheet Read Me
C2: Sheet | D2: Records | E2: What does it cover
C3: Raw Data | D3: 1647 | E3: Export of 1,647 references in Zotero is from IPBES Global Assessment 1, Chapter 2.1. Chapter 2.1 (Status and Trends - Drivers of Change) discusses the indirect and direct drivers of biodiversity loss, as well as associated development pathways.
C4: Enriched Data | D4: 1647 | E4: Manually annotated all 228 references as ‘Y’ when they were found in Chapters 2.1.12 - 2.1.17, i.e., the chapters related to the direct drivers of biodiversity loss. Additionally, if these annotated references were present in Web of Science, they were also marked as ‘Y’.
C5: Curated Data | D5: 156 | E5: From all annotated references, select only those present in Chapters 2.1.12–2.1.17 (156 in total), while excluding references from grey literature (57 in total) and those that do not exist in Web of Science (15 in total).
C6: Query | D6: 119 | E6: Web of Science query to get all records of References Selected in test list

Sheet WOS Search for References
A1: Publication Type | B1: Authors | C1: Article Title | D1: Source Title | E1: Document Type | F1: Abstract | G1: DOI | H1: DOI Link | I1: WoS Categories | J1: Date of Export | K1: UT (Unique WOS ID) | L1: Web of Science Record
A2: J | B2: Lambdon, PW; Pysek, P; Basnou, C; Hejda, M; Arianoutsou, M; Essl, F; Jarosik, V; Pergl, J; Winter, M; Anastasiu, P; Andriopoulos, P; Bazos, I; Brundu, G; Celesti-Grapow, L; Chassot, P; Delipetrou, P; Josefsson, M; Kark, S; Klotz, S; Kokkoris, Y; Kühn, I; Marchante, H; Perglová, I; Pino, J; Vilà, M; Zikos, A; Roy, D; Hulme, PE | C2: Alien flora of Europe:: species diversity, temporal trends, geographical patterns and research needs | D2: PRESLIA | E2: Review | F2: The paper provides the first estimate of the composition and structure of alien plants occurring in the wild in the European continent, based on the results of the DAISIE project (2004-2008), funded by the 6th Framework Programme of the European Union and aimed at creating an inventory of invasive species that threaten European terrestrial, freshwater and marine environments. The plant section of the DAISIE database is based on national checklists from 48 European countries/regions and Israel; for many of them the data were compiled during the project and for some countries DAISIE collected the first comprehensive checklists of alien species, based on primary data (e.g., Cyprus, Greece, R Y. R. O. Macedonia, Slovenia, Ukraine). In total, the database contains records of 5789 alien plant species in Europe (including those native to a part of Europe but alien to another part), of which 2843 are alien to Europe (of extra-European origin). The research focus was on naturalized species; there are in total 3749 naturalized aliens in Europe, of which 1780 are alien to Europe. This represents a marked increase compared to 1568 alien species reported by a previous analysis of data in Flora Europaea (1964-1980). Casual aliens were marginally considered and are represented by 1507 species with European origins and 872 species whose native range falls outside Europe. The highest diversity of alien species is concentrated in industrialized countries with a tradition of good botanical recording or intensive recent research. The highest number of all alien species, regardless of status, is reported from Belgium (1969), the United Kingdom (1779) and Czech Republic (1378). The United Kingdom (857), Germany (450), Belgium (447) and Italy (440) are countries with the most naturalized neophytes. The number of naturalized neophytes in European countries is determined mainly by the interaction of temperature and precipitation; it increases with increasing precipitation but only in climatically warm and moderately warm regions. Of the nowadays naturalized neophytes alien to Europe, 50% arrived after 1899, 25% after 1962 and 10% after 1989. At present, approximately 6.2 new species, that are capable of naturalization, are arriving each year. Most alien species have relatively restricted European distributions; half of all naturalized species occur in four or fewer countries/regions, whereas 70% of non-naturalized species occur in only one region. Alien species are drawn from 213 families, dominated by large global plant families which have a weedy tendency and have undergone major radiations in temperate regions (Asteraceae, Poaceae, Rosaceae, Fabaceae, Brassicaceae). There are 1567 genera, which have alien members in European countries, the commonest being globally-diverse genera comprising mainly urban and agricultural weeds (e.g., Amaranthus, Chenopodium and Solanum) or cultivated for ornamental purposes (Cotoneaster, the genus richest in alien species). Only a few large genera which have successfully invaded (e.g., Oenothera, Oxalis, Panicum, Helianthus) are predominantly of non-European origin. Conyza canadensis, Helianthus tuberosus and Robinia pseudoacacia are most widely distributed alien species. Of all naturalized aliens present in Europe, 64.1% occur in industrial habitats and 58.5% on arable land and in parks and gardens. Grasslands and woodlands are also highly invaded, with 37.4 and 31.5%, respectively, of all naturalized aliens in Europe present in these habitats. Mires, bogs and fens are least invaded; only approximately 10% of aliens in Euope occur there. Intentional introductions to Europe (62.8% of the total number of naturalized aliens) prevail over unintentional (37.2%). Ornamental and horticultural introductions escaped from cultivation account for the highest number of species, 52.2% of the total. Among unintentional introductions, contaminants of seed, mineral materials and other commodities are responsible for 1091 alien species introductions to Europe (76.6% of all species introduced unintentionally) and 363 species are assumed to have arrived as stowaways (directly associated with human transport but arriving independently of commodity). Most aliens in Europe have a native range in the same continent (28.6% of all donor region records are from another part of Europe where the plant is native); in terms of species numbers the contribution of Europe as a region of origin is 53.2%. Considering aliens to Europe separately, 45.8% of species have their native distribution in North and South America, 45.9% in Asia, 20.7% in Africa and 5.3% in Australasia. Based on species composition, European alien flora can be classified into five major groups: (1) north-western, comprising Scandinavia and the UK; (2) west-central, extending from Belgium and the Netherlands to Germany and Switzerland; (3) Baltic, including only the former Soviet Baltic states; (4) east-central, comprizing the remainder of central and eastern Europe; (5) southern, covering the entire Mediterranean region. The clustering patterns cut across some European bioclimatic zones; cultural factors such as regional trade links and traditional local preferences for crop, forestry and ornamental species are also important by influencing the introduced species pool. Finally, the paper evaluates a state of the art in the field of plant invasions in Europe, points to research gaps and outlines avenues of further research towards documenting alien plant invasions in Europe. The data are of varying quality and need to be further assessed with respect to the invasion status and residence time of the species included. This concerns especially the naturalized/casual status; so far, this information is available comprehensively for only 19 countries/regions of the 49 considered. Collating an integrated database on the alien flora of Europe can form a principal contribution to developing a European-wide management strategy of alien species. | I2: Plant Sciences | J2: 45982 | K2: WOS:000258002600001 | L2: View Full Record in Web of Science
A3: J | B3: Seebens, H; Blackburn, TM; Dyer, EE; Genovesi, P; Hulme, PE; Jeschke, JM; Pagad, S; Pysek, P; van Kleunen, M; Winter, M; Ansong, M; Arianoutsou, M; Bacher, S; Blasius, B; Brockerhoff, EG; Brundu, G; Capinha, C; Causton, CE; Celesti-Grapow, L; Dawson, W; Dullinger, S; Economo, EP; Fuentes, N; Guénard, B; Jäger, H; Kartesz, J; Kenis, M; Kühn, I; Lenzner, B; Liebhold, AM; Mosena, A; Moser, D; Nentwig, W; Nishino, M; Pearman, D; Pergl, J; Rabitsch, W; Rojas-Sandoval, J; Roques, A; Rorke, S; Rossinelli, S; Roy, HE; Scalera, R; Schindler, S; Stajerová, K; Tokarska-Guzik, B; Walker, K; Ward, DF; Yamanaka, T; Essl, F | C3: Global rise in emerging alien species results from increased accessibility of new source pools | D3: PROCEEDINGS OF THE NATIONAL ACADEMY OF SCIENCES OF THE UNITED STATES OF AMERICA | E3: Article | F3: Our ability to predict the identity of future invasive alien species is largely based upon knowledge of prior invasion history. Emerging alien species-those never encountered as aliens before-therefore pose a significant challenge to biosecurity interventions worldwide. Understanding their temporal trends, origins, and the drivers of their spread is pivotal to improving prevention and risk assessment tools. Here, we use a database of 45,984 first records of 16,019 established alien species to investigate the temporal dynamics of occurrences of emerging alien species worldwide. Even after many centuries of invasions the rate of emergence of new alien species is still high: Onequarter of first records during 2000-2005 were of species that had not been previously recorded anywhere as alien, though with large variation across taxa. Model results show that the high proportion of emerging alien species cannot be solely explained by increases in well-known drivers such as the amount of imported commodities from historically important source regions. Instead, these dynamics reflect the incorporation of new regions into the pool of potential alien species, likely as a consequence of expanding trade networks and environmental change. This process compensates for the depletion of the historically important source species pool through successive invasions. We estimate that 1-16% of all species on Earth, depending on the taxonomic group, qualify as potential alien species. These results suggest that there remains a high proportion of emerging alien species we have yet to encounter, with future impacts that are difficult to predict. | G3: 10.1073/pnas.1719429115 | H3: http://dx.doi.org/10.1073/pnas.1719429115 | I3: Multidisciplinary Sciences | J3: 45982 | K3: WOS:000426671900017 | L3: View Full Record in Web of Science
A4: J | B4: Newman, M; Wittenberg, AT; Cheng, LY; Compo, GP; Smith, CA | C4: THE EXTREME 2015/16 EL NINO, IN THE CONTEXT OF HISTORICAL CLIMATE VARIABILITY AND CHANGE | D4: BULLETIN OF THE AMERICAN METEOROLOGICAL SOCIETY | E4: Article | G4: 10.1175/BAMS-D-17-0116.1 | H4: http://dx.doi.org/10.1175/BAMS-D-17-0116.1 | I4: Meteorology & Atmospheric Sciences | J4: 45982 | K4: WOS:000429319000004 | L4: View Full Record in Web of Science
A5: J | B5: Risser, MD; Wehner, MF | C5: Attributable Human-Induced Changes in the Likelihood and Magnitude of the Observed Extreme Precipitation during Hurricane Harvey | D5: GEOPHYSICAL RESEARCH LETTERS | E5: Article | F5: Record rainfall amounts were recorded during Hurricane Harvey in the Houston, Texas, area, leading to widespread flooding. We analyze observed precipitation from the Global Historical Climatology Network with a covariate-based extreme value statistical analysis, accounting for both the external influence of global warming and the internal influence of El Nino-Southern Oscillation. We find that human-induced climate change likely increased the chances of the observed precipitation accumulations during Hurricane Harvey in the most affected areas of Houston by a factor of at least 3.5. Further, precipitation accumulations in these areas were likely increased by at least 18.8% (best estimate of 37.7%), which is larger than the 6-7% associated with an attributable warming of 1 degrees C in the Gulf of Mexico and Clausius-Clapeyron scaling. In a Granger causality sense, these statements provide lower bounds on the impact of climate change and motivate further attribution studies using dynamical climate models. | G5: 10.1002/2017GL075888 | H5: http://dx.doi.org/10.1002/2017GL075888 | I5: Geosciences, Multidisciplinary | J5: 45982 | K5: WOS:000422954700032 | L5: View Full Record in Web of Science
A6: J | B6: Johnson, AC; Donnachie, RL; Sumpter, JP; Jurgens, MD; Moeckel, C; Pereira, MG | C6: An alternative approach to risk rank chemicals on the threat they pose to the aquatic environment | D6: SCIENCE OF THE TOTAL ENVIRONMENT | E6: Article | F6: This work presents a new and unbiased method of risk ranking chemicals based on the threat they pose to the aquatic environment. The study ranked 12 metals, 23 pesticides, 11 other persistent organic pollutants (POPs), 13 pharmaceuticals, 10 surfactants and similar compounds and 2 nanoparticles (total of 71) of concern against one another by comparing their median UK river water and median ecotoxicity effect concentrations. To complement this, by giving an assessment on potential wildlife impacts, risk ranking was also carried out by comparing the lowest 10th percentile of the effects data with the highest 90th percentile of the exposure data. In other words, risk was pared down to just toxicity versus exposure. Further modifications included incorporating bioconcentration factors, using only recent water measurements and excluding either lethal or sub-lethal effects. The top ten chemicals, based on the medians, which emerged as having the highest risk to organisms in UK surface waters using all the ecotoxicity data were copper, aluminium, zinc, ethinylestradiol (EE2), linear alkylbenzene sulfonate (LAS), triclosan, manganese, iron, methomyl and chlorpyrifos. By way of contrast, using current UK environmental quality standards as the comparator to median UK river water concentrations would have selected 6 different chemicals in the top ten. This approach revealed big differences in relative risk; for example, zinc presented a million times greater risk then metoprolol and LAS 550 times greater risk than nanosilver. With the exception of EE2, most pharmaceuticals were ranked as having a relatively low risk. (C) 2017 Elsevier B.V. All rights reserved. | G6: 10.1016/j.scitotenv.2017.05.039 | H6: http://dx.doi.org/10.1016/j.scitotenv.2017.05.039 | I6: Environmental Sciences | J6: 45982 | K6: WOS:000405253500033 | L6: View Full Record in Web of Science
A7: J | B7: Emanuel, K | C7: Assessing the present and future probability of Hurricane Harvey's rainfall | D7: PROCEEDINGS OF THE NATIONAL ACADEMY OF SCIENCES OF THE UNITED STATES OF AMERICA | E7: Article | F7: We estimate, for current and future climates, the annual probability of areally averaged hurricane rain of Hurricane Harvey's magnitude by downscaling large numbers of tropical cyclones from three climate reanalyses and six climate models. For the state of Texas, we estimate that the annual probability of 500 mm of area-integrated rainfall was about 1% in the period 1981-2000 and will increase to 18% over the period 2081-2100 under Intergovernmental Panel on Climate Change (IPCC) AR5 representative concentration pathway 8.5. If the frequency of such event is increasingly linearly between these two periods, then in 2017 the annual probability would be 6%, a sixfold increase since the late 20th century. | G7: 10.1073/pnas.1716222114 | H7: http://dx.doi.org/10.1073/pnas.1716222114 | I7: Multidisciplinary Sciences | J7: 45982 | K7: WOS:000416891600045 | L7: View Full Record in Web of Science
A8: J | B8: Dawson, W; Moser, D; van Kleunen, M; Kreft, H; Pergl, J; Pysek, P; Weigelt, P; Winter, M; Lenzner, B; Blackburn, TM; Dyer, EE; Cassey, P; Scrivens, SL; Economo, EP; Guénard, B; Capinha, C; Seebens, H; García-Díaz, P; Nentwig, W; García-Berthou, E; Casal, C; Mandrak, NE; Fuller, P; Meyer, C; Essl, F | C8: Global hotspots and correlates of alien species richness across taxonomic groups | D8: NATURE ECOLOGY & EVOLUTION | E8: Article | F8: Human-mediated transport beyond biogeographic barriers has led to the introduction and establishment of alien species in new regions worldwide. However, we lack a global picture of established alien species richness for multiple taxonomic groups. Here, we assess global patterns and potential drivers of established alien species richness across eight taxonomic groups (amphibians, ants, birds, freshwater fishes, mammals, vascular plants, reptiles and spiders) for 186 islands and 423 mainland regions. Hotspots of established alien species richness are predominantly island and coastal mainland regions. Regions with greater gross domestic product per capita, human population density, and area have higher established alien richness, with strongest effects emerging for islands. Ants and reptiles, birds and mammals, and vascular plants and spiders form pairs of taxonomic groups with the highest spatial congruence in established alien richness, but drivers explaining richness differ between the taxa in each pair. Across all taxonomic groups, our results highlight the need to prioritize prevention of further alien species introductions to island and coastal mainland regions globally. | G8: 10.1038/s41559-017-0186 | H8: http://dx.doi.org/10.1038/s41559-017-0186 | I8: Ecology; Evolutionary Biology | J8: 45982 | K8: WOS:000417179000015 | L8: View Full Record in Web of Science
A9: J | B9: Geyer, R; Jambeck, JR; Law, KL | C9: Production, use, and fate of all plastics ever made | D9: SCIENCE ADVANCES | E9: Article | F9: Plastics have outgrown most man-made materials and have long been under environmental scrutiny. However, robust global information, particularly about their end-of-life fate, is lacking. By identifying and synthesizing dispersed data on production, use, and end-of-life management of polymer resins, synthetic fibers, and additives, we present the first global analysis of all mass-produced plastics ever manufactured. We estimate that 8300 million metric tons (Mt) as of virgin plastics have been produced to date. As of 2015, approximately 6300 Mt of plastic waste had been generated, around 9% of which had been recycled, 12% was incinerated, and 79% was accumulated in landfills or the natural environment. If current production and waste management trends continue, roughly 12,000 Mt of plastic waste will be in landfills or in the natural environment by 2050. | G9: 10.1126/sciadv.1700782 | H9: http://dx.doi.org/10.1126/sciadv.1700782 | I9: Multidisciplinary Sciences | J9: 45982 | K9: WOS:000411588000033 | L9: View Full Record in Web of Science
A10: J | B10: L'Heureux, ML; Takahashi, K; Watkins, AB; Barnston, AG; Becker, EJ; Di Liberto, TE; Gamble, F; Gottschalck, J; Halpert, MS; Huang, BY; Mosquera-Väsquez, K; Wittenberg, AT | C10: OBSERVING AND PREDICTING THE 2015/16 EL NINO | D10: BULLETIN OF THE AMERICAN METEOROLOGICAL SOCIETY | E10: Article | F10: The El Nino of 2015/16 rivaled the major El Nino events of 1982/83 and 1997/98, showcasing advancements in operational observing and prediction systems, while offering challenges for the future. | G10: 10.1175/BAMS-D-16-0009.1 | H10: http://dx.doi.org/10.1175/BAMS-D-16-0009.1 | I10: Meteorology & Atmospheric Sciences | J10: 45982 | K10: WOS:000406502800006 | L10: View Full Record in Web of Science
A11: J | B11: Lebreton, LCM; Van der Zwet, J; Damsteeg, JW; Slat, B; Andrady, A; Reisser, J | C11: River plastic emissions to the world's oceans | D11: NATURE COMMUNICATIONS | E11: Article | F11: Plastics in the marine environment have become a major concern because of their persistence at sea, and adverse consequences to marine life and potentially human health. Implementing mitigation strategies requires an understanding and quantification of marine plastic sources, taking spatial and temporal variability into account. Here we present a global model of plastic inputs from rivers into oceans based on waste management, population density and hydrological information. Our model is calibrated against measurements available in the literature. We estimate that between 1.15 and 2.41 million tonnes of plastic waste currently enters the ocean every year from rivers, with over 74% of emissions occurring between May and October. The top 20 polluting rivers, mostly located in Asia, account for 67% of the global total. The findings of this study provide baseline data for ocean plastic mass balance exercises, and assist in prioritizing future plastic debris monitoring and mitigation strategies. | G11: 10.1038/ncomms15611 | H11: http://dx.doi.org/10.1038/ncomms15611 | I11: Multidisciplinary Sciences | J11: 45982 | K11: WOS:000402803800001 | L11: View Full Record in Web of Science
A12: J | B12: Altieri, AH; Harrison, SB; Seemann, J; Collin, R; Diaz, RJ; Knowlton, N | C12: Tropical dead zones and mass mortalities on coral reefs | D12: PROCEEDINGS OF THE NATIONAL ACADEMY OF SCIENCES OF THE UNITED STATES OF AMERICA | E12: Article | F12: Degradation of coastal water quality in the form of low dissolved oxygen levels (hypoxia) can harm biodiversity, ecosystem function, and human wellbeing. Extreme hypoxic conditions along the coast, leading to what are often referred to as dead zones, are known primarily from temperate regions. However, little is known about the potential threat of hypoxia in the tropics, even though the known risk factors, including eutrophication and elevated temperatures, are common. Here we document an unprecedented hypoxic event on the Caribbean coast of Panama and assess the risk of dead zones to coral reefs worldwide. The event caused coral bleaching and massive mortality of corals and other reef-associated organisms, but observed shifts in community structure combined with laboratory experiments revealed that not all coral species are equally sensitive to hypoxia. Analyses of global databases showed that coral reefs are associated with more than half of the known tropical dead zones worldwide, with >10% of all coral reefs at elevated risk for hypoxia based on local and global risk factors. Hypoxic events in the tropics and associated mortality events have likely been underreported, perhaps by an order of magnitude, because of the lack of local scientific capacity for their detection. Monitoring and management plans for coral reef resilience should incorporate the growing threat of coastal hypoxia and include support for increased detection and research capacity. | G12: 10.1073/pnas.1621517114 | H12: http://dx.doi.org/10.1073/pnas.1621517114 | I12: Multidisciplinary Sciences | J12: 45982 | K12: WOS:000398159000048 | L12: View Full Record in Web of Science
A13: J | B13: Seebens, H; Blackburn, TM; Dyer, EE; Genovesi, P; Hulme, PE; Jeschke, JM; Pagad, S; Pysek, P; Winter, M; Arianoutsou, M; Bacher, S; Blasius, B; Brundu, G; Capinha, C; Celesti-Grapow, L; Dawson, W; Dullinger, S; Fuentes, N; Jäger, H; Kartesz, J; Kenis, M; Kreft, H; Kühn, I; Lenzner, B; Liebhold, A; Mosena, A; Moser, D; Nishino, M; Pearman, D; Pergl, J; Rabitsch, W; Rojas-Sandoval, J; Roques, A; Rorke, S; Rossinelli, S; Roy, HE; Scalera, R; Schindler, S; Stajerová, K; Tokarska-Guzik, B; van Kleunen, M; Walker, K; Weigelt, P; Yamanaka, T; Essl, F | C13: No saturation in the accumulation of alien species worldwide | D13: NATURE COMMUNICATIONS | E13: Article | F13: Although research on human-mediated exchanges of species has substantially intensified during the last centuries, we know surprisingly little about temporal dynamics of alien species accumulations across regions and taxa. Using a novel database of 45,813 first records of 16,926 established alien species, we show that the annual rate of first records worldwide has increased during the last 200 years, with 37% of all first records reported most recently (1970-2014). Inter-continental and inter-taxonomic variation can be largely attributed to the diaspora of European settlers in the nineteenth century and to the acceleration in trade in the twentieth century. For all taxonomic groups, the increase in numbers of alien species does not show any sign of saturation and most taxa even show increases in the rate of first records over time. This highlights that past efforts to mitigate invasions have not been effective enough to keep up with increasing globalization. | G13: 10.1038/ncomms14435 | H13: http://dx.doi.org/10.1038/ncomms14435 | I13: Multidisciplinary Sciences | J13: 45982 | K13: WOS:000394221600001 | L13: View Full Record in Web of Science
A14: J | B14: Arroita, M; Flores, L; Larrañaga, A; Martínez, A; Martínez-Santos, M; Pereda, O; Ruiz-Romera, E; Solagaistua, L; Elosegi, A | C14: Water abstraction impacts stream ecosystem functioning via wetted-channel contraction | D14: FRESHWATER BIOLOGY | E14: Article | F14: Water abstraction is rapidly increasing worldwide in order to respond to escalating demands for water, food and energy. Abstraction can alter the hydrological regime of streams and rivers, reduce in-stream habitats, change water quality and affect fluvial communities. It can also impair ecosystem functioning, although this aspect has been seldom assessed. We experimentally tested the effect of water abstraction on stream functioning in a headwater mountain stream using a before and after control-impact (BACI) design. We quantified changes in water physicochemical properties, biofilm biomass and activity (exo-enzymes and metabolism), and ecosystem processes (nutrient cycling, organic matter retention and breakdown). Water abstraction did not affect water physicochemical properties, but reduced the biomass and the alkaline phosphatase activity of biofilm per surface unit, the areal uptake of nutrients, and the travel distance of organic matter. It did not affect the biofilm metabolism and breakdown of submerged leaf litter, but decreased the total breakdown. The impacts were larger when analysed per unit of channel length. All variables, except benthic chlorophyll-a, were significantly reduced by abstraction, due to the contraction of the wetted channel. The decrease in the biomass and activity of biofilm, as well as in nutrient uptake and total organic matter breakdown observed in this study could increase nutrient concentration in downstream reaches and reduce the energy transfer to higher trophic levels. Ecosystem services of permanent headwater streams are likely to be compromised with the reduction of wetted-channel width. | G14: 10.1111/fwb.12864 | H14: http://dx.doi.org/10.1111/fwb.12864 | I14: Ecology; Marine & Freshwater Biology | J14: 45982 | K14: WOS:000393793100003 | L14: View Full Record in Web of Science
A15: J | B15: Hattich, GSI; Listmann, L; Raab, J; Ozod-Seradj, D; Reusch, TBH; Matthiessen, B | C15: Inter- and intraspecific phenotypic plasticity of three phytoplankton species in response to ocean acidification | D15: BIOLOGY LETTERS | E15: Article | F15: Phenotypic plasticity describes the phenotypic adjustment of the same genotype to different environmental conditions and is best described by a reaction norm. We focus on the effect of ocean acidification on inter-and intraspecific reaction norms of three globally important phytoplankton species (Emiliania huxleyi, Gephyrocapsa oceanica and Chaetoceros affinis). Despite significant differences in growth rates between the species, they all showed a high potential for phenotypic buffering (similar growth rates between ambient and high CO2 conditions). Only three coccolithophore genotypes showed a reduced growth in high CO2. Diverging responses to high CO2 of single coccolithophore genotypes compared with the respective mean species responses, however, raise the question of whether an extrapolation to the population level is possible from single-genotype experiments. We therefore compared the mean response of all tested genotypes with a total species response comprising the same genotypes, which was not significantly different in the coccolithophores. Assessing species reaction norms to different environmental conditions on short time scale in a genotype-mix could thus reduce sampling effort while increasing predictive power. | G15: 10.1098/rsbl.2016.0774 | H15: http://dx.doi.org/10.1098/rsbl.2016.0774 | I15: Biology; Ecology; Evolutionary Biology | J15: 45982 | K15: WOS:000396015400004 | L15: View Full Record in Web of Science
A16: J | B16: Hoegh-Guldberg, O; Poloczanska, ES; Skirving, W; Dove, S | C16: Coral Reef Ecosystems under Climate Change and Ocean Acidification | D16: FRONTIERS IN MARINE SCIENCE | E16: Review | F16: Coral reefs are found in a wide range of environments, where they provide food and habitat to a large range of organisms as well as providing many other ecological goods and services. Warm-water coral reefs, for example, occupy shallow sunlit, warm, and alkaline waters in order to grow and calcify at the high rates necessary to build and maintain their calcium carbonate structures. At deeper locations (40-150 m), mesophotic (low light) coral reefs accumulate calcium carbonate at much lower rates (if at all in some cases) yet remain important as habitat for a wide range of organisms, including those important for fisheries. Finally, even deeper, down to 2,000 m or more, the so-called cold-water coral reefs are found in the dark depths. Despite their importance, coral reefs are facing significant challenges from human activities including pollution, over-harvesting, physical destruction, and climate change. In the latter case, even lower greenhouse gas emission scenarios (such as Representative Concentration Pathway RCP 4.5) are likely drive the elimination of most warm-water coral reefs by 2040-2050. Cold-water corals are also threatened by warming temperatures and ocean acidification although evidence of the direct effect of climate change is less clear. Evidence that coral reefs can adapt at rates which are sufficient for them to keep up with rapid ocean warming and acidification is minimal, especially given that corals are long-lived and hence have slow rates of evolution. Conclusions that coral reefs will migrate to higher latitudes as they warm are equally unfounded, with the observations of tropical species appearing at high latitudes necessary but not sufficient evidence that entire coral reef ecosystems are shifting. On the contrary, coral reefs are likely to degrade rapidly over the next 20 years, presenting fundamental challenges for the 500 million people who derive food, income, coastal protection, and a range of other services from coral reefs. Unless rapid advances to the goals of the Paris Climate Change Agreement occur over the next decade, hundreds of millions of people are likely to face increasing amounts of poverty and social disruption, and, in some cases, regional insecurity. | G16: 10.3389/fmars.2017.00158 | H16: http://dx.doi.org/10.3389/fmars.2017.00158 | I16: Environmental Sciences; Marine & Freshwater Biology | J16: 45982 | K16: WOS:000457690600158 | L16: View Full Record in Web of Science
... A59: J | B59: Nepstad, D; McGrath, D; Stickler, C; Alencar, A; Azevedo, A; Swette, B; Bezerra, T; DiGiano, M; Shimada, J; da Motta, RS; Armijo, E; Castello, L; Brando, P; Hansen, MC; McGrath-Horn, M; Carvalho, O; Hess, L | C59: Slowing Amazon deforestation through public policy and interventions in beef and soy supply chains | D59: SCIENCE | E59: Review | F59: The recent 70% decline in deforestation in the Brazilian Amazon suggests that it is possible to manage the advance of a vast agricultural frontier. Enforcement of laws, interventions in soy and beef supply chains, restrictions on access to credit, and expansion of protected areas appear to have contributed to this decline, as did a decline in the demand for new deforestation. The supply chain interventions that fed into this deceleration are precariously dependent on corporate risk management, and public policies have relied excessively on punitive measures. Systems for delivering positive incentives for farmers to forgo deforestation have been designed but not fully implemented. Territorial approaches to deforestation have been effective and could consolidate progress in slowing deforestation while providing a framework for addressing other important dimensions of sustainable development. | G59: 10.1126/science.1248525 | H59: http://dx.doi.org/10.1126/science.1248525 | I59: Multidisciplinary Sciences | J59: 45982 | K59: WOS:000336791200038 | L59: View Full Record in Web of Science
A60: J | B60: Franzke, CLE | C60: WARMING TRENDS Nonlinear climate change | D60: NATURE CLIMATE CHANGE | E60: Editorial Material | G60: 10.1038/nclimate2245 | H60: http://dx.doi.org/10.1038/nclimate2245 | I60: Environmental Sciences; Environmental Studies; Meteorology & Atmospheric Sciences | J60: 45982 | K60: WOS:000337138700011 | L60: View Full Record in Web of Science
A61: J | B61: Moschet, C; Wittmer, I; Simovic, J; Junghans, M; Piazzoli, A; Singer, H; Stamm, C; Leu, C; Hollender, J | C61: How a Complete Pesticide Screening Changes the Assessment of Surface Water Quality | D61: ENVIRONMENTAL SCIENCE & TECHNOLOGY | E61: Article | F61: A comprehensive assessment of pesticides in surface waters is challenging due to the large number of potential contaminants. Most scientific studies and routine monitoring programs include only 15-40 pesticides, which leads to error-prone interpretations. In the present study, an extensive analytical screening was carried out using liquid chromatography-high-resolution mass spectrometry, covering 86% of all polar organic pesticides sold in Switzerland and applied to agricultural or urban land (in total 249 compounds), plus 134 transformation products; each of which could be quantified in the low ng/L range. Five medium-sized rivers, containing large areas of diverse crops and urban settlements within the respective catchments, were sampled between March and July 2012. More than 100 parent compounds and 40 transformation products were detected in total, between 30 and compounds in each two-week composite sample in concentrations up to 1500 ng/L. The sum of pesticide concentrations was above 1000 ng/L in 78% of samples. The chronic environmental quality standard was exceeded for 19 single substances; using a mixture toxicity approach, exceedances occurred over the whole measurement period in all rivers. With scenario calculations including only 30-40 frequently measured pesticides, the number of detected substances and the mixture toxicity would be underestimated on average by a factor of 2. Thus, selecting a subset of substances to assess the surface water quality may be sufficient, but a comprehensive screening yields substantially more confidence. | G61: 10.1021/es500371t | H61: http://dx.doi.org/10.1021/es500371t | I61: Engineering, Environmental; Environmental Sciences | J61: 45982 | K61: WOS:000336415200011 | L61: View Full Record in Web of Science
A62: J | B62: Haddeland, I; Heinke, J; Biemans, H; Eisner, S; Flörke, M; Hanasaki, N; Konzmann, M; Ludwig, F; Masaki, Y; Schewe, J; Stacke, T; Tessler, ZD; Wada, Y; Wisser, D | C62: Global water resources affected by human interventions and climate change | D62: PROCEEDINGS OF THE NATIONAL ACADEMY OF SCIENCES OF THE UNITED STATES OF AMERICA | E62: Article | F62: Humans directly change the dynamics of the water cycle through dams constructed for water storage, and through water withdrawals for industrial, agricultural, or domestic purposes. Climate change is expected to additionally affect water supply and demand. Here, analyses of climate change and direct human impacts on the terrestrial water cycle are presented and compared using a multimodel approach. Seven global hydrological models have been forced with multiple climate projections, and with and without taking into account impacts of human interventions such as dams and water withdrawals on the hydrological cycle. Model results are analyzed for different levels of global warming, allowing for analyses in line with temperature targets for climate change mitigation. The results indicate that direct human impacts on the water cycle in some regions, e. g., parts of Asia and in the western United States, are of the same order of magnitude, or even exceed impacts to be expected for moderate levels of global warming (+2 K). Despite some spread in model projections, irrigation water consumption is generally projected to increase with higher global mean temperatures. Irrigation water scarcity is particularly large in parts of southern and eastern Asia, and is expected to become even larger in the future. | G62: 10.1073/pnas.1222475110 | H62: http://dx.doi.org/10.1073/pnas.1222475110 | I62: Multidisciplinary Sciences | J62: 45982 | K62: WOS:000332560300026 | L62: View Full Record in Web of Science
A63: J | B63: Cazenave, A; Le Cozannet, G | C63: Sea level rise and its coastal impacts | D63: EARTHS FUTURE | E63: Review | F63: Global warming in response to accumulation of human-induced greenhouse gases inside the atmosphere has already caused several visible consequences, among them increase of the Earth's mean temperature and ocean heat content, melting of glaciers, and loss of ice from the Greenland and Antarctica ice sheets. Ocean warming and land ice melt in turn are causing sea level to rise. Sea level rise and its impacts on coastal zones have become a question of growing interest in the scientific community, as well as in the media and public. In this review paper, we summarize the most up-to-date knowledge about sea level rise and its causes, highlighting the regional variability that superimposes the global mean rise. We also present sea level projections for the 21st century under different warming scenarios. We next address the issue of the sea level rise impacts. We question whether there is already observational evidence of coastal impacts of sea level rise and highlight the fact that results differ from one location to another. This suggests that the response of coastal systems to sea level rise is highly dependent on local natural and human settings. We finally show that in spite of remaining uncertainties about future sea levels and related impacts, it becomes possible to provide preliminary assessment of regional impacts of sea level rise. | G63: 10.1002/2013EF000188 | H63: http://dx.doi.org/10.1002/2013EF000188 | I63: Environmental Sciences; Geosciences, Multidisciplinary; Meteorology & Atmospheric Sciences | J63: 45982 | K63: WOS:000358125500001 | L63: View Full Record in Web of Science
A64: J | B64: Rickson, RJ | C64: Can control of soil erosion mitigate water pollution by sediments? | D64: SCIENCE OF THE TOTAL ENVIRONMENT | E64: Article | F64: The detrimental impact of sediment and associated pollutants on water quality is widely acknowledged, with many watercourses in the UK failing to meet the standard of 'good ecological status'. Catchment sediment budgets show that hill slope erosion processes can be significant sources of waterborne sediment, with rates of erosion likely to increase given predicted future weather patterns. However, linking on-site erosion rates with off-site impacts is complicated because of the limited data on soil erosion rates in the UK and the dynamic nature of the source pathway receptor continuum over space and time. Even so, soil erosion control measures are designed to reduce sediment production (source) and mobilisation/transport (pathway) on hill slopes, with consequent mitigation of pollution incidents in watercourses (receptors). The purpose of this paper is to review the scientific evidence of the effectiveness of erosion control measures used in the UK to reduce sediment loads of hill slope origin in watercourses. Although over 73 soil erosion mitigation measures have been identified from the literature, empirical data on erosion control effectiveness are limited. Baseline comparisons for the 18 measures where data do exist reveal erosion control effectiveness is highly variable over time and between study locations. Given the limitations of the evidence base in terms of geographical coverage and duration of monitoring, performance of the different measures cannot be extrapolated to other areas. This uncertainty in effectiveness has implications for implementing erosion/sediment risk reduction policies, where quantified targets are stipulated, as is the case in the EU Freshwater Fish and draft Soil Framework Directives. Also, demonstrating technical effectiveness of erosion control measures alone will not encourage uptake by land managers: quantifying the costs and benefits of adopting erosion mitigation is equally important, but these are uncertain and difficult to express in monetary terms. (C) 2013 Elsevier B.V. All rights reserved. | G64: 10.1016/j.scitotenv.2013.05.057 | H64: http://dx.doi.org/10.1016/j.scitotenv.2013.05.057 | I64: Environmental Sciences | J64: 45982 | K64: WOS:000331776000125 | L64: View Full Record in Web of Science
A65: J | B65: Gypens, N; Borges, AV | C65: Increase in dimethylsulfide (DMS) emissions due to eutrophication of coastal waters offsets their reduction due to ocean acidification | D65: FRONTIERS IN MARINE SCIENCE | E65: Article | F65: Available information from manipulative experiments suggested that the emission of dimethylsulfide (DMS) would decrease in response to the accumulation of anthropogenic CO2 in the ocean (ocean acidification). However, in coastal environments, the carbonate chemistry of surface waters was also strongly modified by eutrophication and related changes in biological activity (increased primary production and change in phytoplankton dominance) during the last 50 years. Here, we tested the hypothesis that DMS emissions in marine coastal environments also strongly responded to eutrophication in addition to ocean acidification at decadal timescales. We used the R-MIRO-BIOGAS model in the eutrophied Southern Bight of the North Sea characterized by intense blooms of Phaeocystis that are high producers of dimethylsulfoniopropionate (DMSP), the precursor of DMS. We showed that, for the period from 1951 to 2007, eutrophication actually led to an increase of DMS emissions much stronger than the response of DMS emissions to ocean acidification. | G65: 10.3389/fmars.2014.00004 | H65: http://dx.doi.org/10.3389/fmars.2014.00004 | I65: Environmental Sciences; Marine & Freshwater Biology | J65: 45982 | K65: WOS:000485310600004 | L65: View Full Record in Web of Science
A66: J | B66: Kanemoto, K; Moran, D; Lenzen, M; Geschke, A | C66: International trade undermines national emission reduction targets: New evidence from air pollution | D66: GLOBAL ENVIRONMENTAL CHANGE-HUMAN AND POLICY DIMENSIONS | E66: Article | F66: Many developed countries in Annex B of the Kyoto Protocol have been able to report decreasing emissions, and some have officially fulfilled their CO2 reduction commitments. This is in part because current reporting and regulatory regimes allow these countries to displace emissions intensive production offshore. Using a new highly detailed account of emissions embodied in international trade we investigate this phenomenon of emissions leakage. We independently confirm previous findings that adjusting for trade, developed countries emissions have increased, not decreased. We find that the sectors successfully holding or lowering their domestic emissions are often the same as those increasing their imports of embodied CO2. We also find that the fastest growing flow paths of embodied CO2 largely originate outside the Kyoto Annex B signatory nations. Finally, we find that historically the same phenomenon of emissions displacement has already occurred for air pollution, with the result that despite aggressive legislation in major emitters total global air pollution emissions have increased. If regulatory policies do not account for embodied imports, global emissions are likely to rise even if developed countries emitters enforce strong national emissions targets. (C) 2013 Elsevier Ltd. All rights reserved. | G66: 10.1016/j.gloenvcha.2013.09.008 | H66: http://dx.doi.org/10.1016/j.gloenvcha.2013.09.008 | I66: Environmental Sciences; Environmental Studies; Geography | J66: 45982 | K66: WOS:000333506100007 | L66: View Full Record in Web of Science
A67: J | B67: Sato, T; Qadir, M; Yamamoto, S; Endo, T; Zahoor, A | C67: Global, regional, and country level need for data on wastewater generation, treatment, and use | D67: AGRICULTURAL WATER MANAGEMENT | E67: Review | F67: Irrigation with wastewater supports agricultural production and the livelihoods of millions of smallholder farmers in many parts of the world. Considering the importance of better wastewater management at the local and national levels, there is a need for updated national data on wastewater generation, treatment, and use, which would also assist in regional and global wastewater assessments. While searching data and literature in published or electronic forms for 181 countries, we find that only 55 countries have data available on all three aspects of wastewater - generation, treatment, and use. The number of countries with one or two aspects of wastewater generation, treatment, and use is 69, while there is no information available from 57 countries. Of the available information, only 37% of the data could be categorized as recent (reported during 2008-2012). The available data suggest that high-income countries on average treat 70% of the generated wastewater, followed by upper-middle-income countries (38%), lower-middle-income countries (28%), and low-income countries, where only 8% of the wastewater generated is treated. The availability of current information on wastewater generation, treatment, and use is crucially important for policy makers, researchers, and practitioners, as well as public institutions, to develop national and local action plans aiming at safe and productive use of wastewater in agriculture, aquaculture, and agroforestry systems. The country level information aggregated at the regional and global levels would help in identifying the gaps in pertinent data availability and assessing the potential of wastewater in food, feed, and fish production at different scales. (C) 2013 Elsevier B.V. All rights reserved. | G67: 10.1016/j.agwat.2013.08.007 | H67: http://dx.doi.org/10.1016/j.agwat.2013.08.007 | I67: Agronomy; Water Resources | J67: 45982 | K67: WOS:000326559900001 | L67: View Full Record in Web of Science
A68: J | B68: Six, KD; Kloster, S; Ilyina, T; Archer, SD; Zhang, K; Maier-Reimer, E | C68: Global warming amplified by reduced sulphur fluxes as a result of ocean acidification | D68: NATURE CLIMATE CHANGE | E68: Article | F68: Climate change and decreasing seawater pH (ocean acidification)(1) have widely been considered as uncoupled consequences of the anthropogenic CO2 perturbation(2,3). Recently, experiments in seawater enclosures (mesocosms) showed that concentrations of dimethylsulphide (DMS), a biogenic sulphur compound, were markedly lower in a low-pH (e)nvironment4. Marine DMS emissions are the largest natural source of atmospheric sulphur(5) and changes in their strength have the potential to alter the Earth's radiation budget(6). Here we establish observational-based relationships between pH changes and DMS concentrations to estimate changes in future DMS emissions with Earth system model(7) climate simulations. Global DMS emissions decrease by about 18(+/-3)% in 2100 compared with pre-industrial times as a result of the combined effects of ocean acidification and climate change. The reduced DMS emissions induce a significant additional radiative forcing, of which 83% is attributed to the impact of ocean acidification, tantamount to an equilibrium temperature response between 0.23 and 0.48 K. Our results indicate that ocean acidification has the potential to exacerbate anthropogenic warming through a mechanism that is not considered at present in projections of future climate change. | G68: 10.1038/NCLIMATE1981 | H68: http://dx.doi.org/10.1038/NCLIMATE1981 | I68: Environmental Sciences; Environmental Studies; Meteorology & Atmospheric Sciences | J68: 45982 | K68: WOS:000330125100016 | L68: View Full Record in Web of Science
A69: J | B69: Hoornweg, D; Bhada-Tata, P; Kennedy, C | C69: Waste production must peak this century | D69: NATURE | E69: Editorial Material | G69: 10.1038/502615a | H69: http://dx.doi.org/10.1038/502615a | I69: Multidisciplinary Sciences | J69: 45982 | K69: WOS:000326293200021 | L69: View Full Record in Web of Science
A70: J | B70: Meyfroidt, P; Lambin, EF; Erb, KH; Hertel, TW | C70: Globalization of land use: distant drivers of land change and geographic displacement of land use | D70: CURRENT OPINION IN ENVIRONMENTAL SUSTAINABILITY | E70: Review | F70: Several streams of research have recently converged to identify the growing importance of distant drivers of land change, interconnections between social-ecological systems that are separated geographically, and the indirect consequences of land use changes. Local to national-scale interventions to promote sustainable land use may have unintended effects owing to a displacement of land use within and across countries. Such leakage or 'indirect land use change' critically depends on international geographies of trade. Computing various material flows and environmental indicators embodied in international trade highlights the differences between producer and consumer-based biophysical accounting. Causal attribution of the links between material and monetary flows across countries, and actual land changes and environmental impacts at local level requires a combination of economic simulation models, statistical studies, place-based empirical studies, value chain analyses, and biophysical accounting. | G70: 10.1016/j.cosust.2013.04.003 | H70: http://dx.doi.org/10.1016/j.cosust.2013.04.003 | I70: Green & Sustainable Science & Technology; Environmental Sciences | J70: 45982 | K70: WOS:000325843700002 | L70: View Full Record in Web of Science
A71: J | B71: Beketov, MA; Kefford, BJ; Schäfer, RB; Liess, M | C71: Pesticides reduce regional biodiversity of stream invertebrates | D71: PROCEEDINGS OF THE NATIONAL ACADEMY OF SCIENCES OF THE UNITED STATES OF AMERICA | E71: Article | F71: The biodiversity crisis is one of the greatest challenges facing humanity, but our understanding of the drivers remains limited. Thus, after decades of studies and regulation efforts, it remains unknown whether to what degree and at what concentrations modern agricultural pesticides cause regional-scale species losses. We analyzed the effects of pesticides on the regional taxa richness of stream invertebrates in Europe (Germany and France) and Australia (southern Victoria). Pesticides caused statistically significant effects on both the species and family richness in both regions, with losses in taxa up to 42% of the recorded taxonomic pools. Furthermore, the effects in Europe were detected at concentrations that current legislation considers environmentally protective. Thus, the current ecological risk assessment of pesticides falls short of protecting biodiversity, and new approaches linking ecology and ecotoxicology are needed. | G71: 10.1073/pnas.1305618110 | H71: http://dx.doi.org/10.1073/pnas.1305618110 | I71: Multidisciplinary Sciences | J71: 45982 | K71: WOS:000321978000046 | L71: View Full Record in Web of Science
A72: J | B72: Krausmann, F; Erb, KH; Gingrich, S; Haberl, H; Bondeau, A; Gaube, V; Lauk, C; Plutzar, C; Searchinger, TD | C72: Global human appropriation of net primary production doubled in the 20th century | D72: PROCEEDINGS OF THE NATIONAL ACADEMY OF SCIENCES OF THE UNITED STATES OF AMERICA | E72: Article | F72: Global increases in population, consumption, and gross domestic product raise concerns about the sustainability of the current and future use of natural resources. The human appropriation of net primary production (HANPP) provides a useful measure of human intervention into the biosphere. The productive capacity of land is appropriated by harvesting or burning biomass and by converting natural ecosystems to managed lands with lower productivity. This work analyzes trends in HANPP from 1910 to 2005 and finds that although human population has grown fourfold and economic output 17-fold, global HANPP has only doubled. Despite this increase in efficiency, HANPP has still risen from 6.9 Gt of carbon per y in 1910 to 14.8 GtC/y in 2005, i.e., from 13% to 25% of the net primary production of potential vegetation. Biomass harvested per capita and year has slightly declined despite growth in consumption because of a decline in reliance on bioenergy and higher conversion efficiencies of primary biomass to products. The rise in efficiency is overwhelmingly due to increased crop yields, albeit frequently associated with substantial ecological costs, such as fossil energy inputs, soil degradation, and biodiversity loss. If humans can maintain the past trend lines in efficiency gains, we estimate that HANPP might only grow to 27-29% by 2050, but providing large amounts of bioenergy could increase global HANPP to 44%. This result calls for caution in refocusing the energy economy on land-based resources and for strategies that foster the continuation of increases in land-use efficiency without excessively increasing ecological costs of intensification. | G72: 10.1073/pnas.1211349110 | H72: http://dx.doi.org/10.1073/pnas.1211349110 | I72: Multidisciplinary Sciences | J72: 45982 | K72: WOS:000321500200066 | L72: View Full Record in Web of Science
A73: J | B73: Van Dijk, TC; Van Staalduinen, MA; Van der Sluijs, JP | C73: Macro-Invertebrate Decline in Surface Water Polluted with Imidacloprid | D73: PLOS ONE | E73: Article | F73: Imidacloprid is one of the most widely used insecticides in the world. Its concentration in surface water exceeds the water quality norms in many parts of the Netherlands. Several studies have demonstrated harmful effects of this neonicotinoid to a wide range of non-target species. Therefore we expected that surface water pollution with imidacloprid would negatively impact aquatic ecosystems. Availability of extensive monitoring data on the abundance of aquatic macro-invertebrate species, and on imidacloprid concentrations in surface water in the Netherlands enabled us to test this hypothesis. Our regression analysis showed a significant negative relationship (P<0.001) between macro-invertebrate abundance and imidacloprid concentration for all species pooled. A significant negative relationship was also found for the orders Amphipoda, Basommatophora, Diptera, Ephemeroptera and Isopoda, and for several species separately. The order Odonata had a negative relationship very close to the significance threshold of 0.05 (P <0.051). However, in accordance with previous research, a positive relationship was found for the order Actinedida. We used the monitoring field data to test whether the existing three water quality norms for imidacloprid in the Netherlands are protective in real conditions. Our data show that macrofauna abundance drops sharply between 13 and 67 ng l(-1). For aquatic ecosystem protection, two of the norms are not protective at all while the strictest norm of 13 ng l(-1) (MTR) seems somewhat protective. In addition to the existing experimental evidence on the negative effects of imidacloprid on invertebrate life, our study, based on data from large-scale field monitoring during multiple years, shows that serious concern about the far-reaching consequences of the abundant use of imidacloprid for aquatic ecosystems is justified. | G73: 10.1371/journal.pone.0062374 | H73: http://dx.doi.org/10.1371/journal.pone.0062374 | I73: Multidisciplinary Sciences | J73: 45982 | K73: WOS:000319167000043 | L73: View Full Record in Web of Science
A74: J | B74: Chidumayo, EN; Gumbo, DJ | C74: The environmental impacts of charcoal production in tropical ecosystems of the world: A synthesis | D74: ENERGY FOR SUSTAINABLE DEVELOPMENT | E74: Review | F74: Charcoal production in tropical regions of the world is often perceived to have devastating ecological and environmental effects and governments, public forestry institutions and non government organizations have been particularly concerned about these charcoal-related impacts. The most commonly cited impact is deforestation, i.e., the clearance of forest or woodland. At a small spatial scale this may indeed be the case but on a larger landscape scale charcoal production most frequently results only in forest degradation. Much of the charcoal in tropical countries is commonly made in traditional earth and pit kilns with a wood-to-charcoal conversion rate of about 20% and in 2009 the contribution of charcoal production to deforestation in tropical countries with the highest rates of deforestation is estimated at less than 7%. A large proportion of the area utilized for charcoal production has the potential for rapid forest recovery especially with good post-harvest management. There are conflicting reports on the effects of deforestation on catchment hydrology with the majority of small catchment studies indicating increased runoff and low evapotranspiration while studies of large basins have shown no such changes. Emissions of greenhouse gases from charcoal production in tropical ecosystems in 2009 are estimated at 71.2 million t for carbon dioxide and 1.3 million t for methane. The failure of past charcoal policies to address environmental impacts and achieve sustainability can be attributed to erroneous assumptions and predictions by national and international organizations regarding wood-based fuels. Possible ways of enhancing charcoal policies' legitimacy and therefore effective implementation are multi-stakeholder participation and demonstration of coherence with globally recognized principles, goals and relevant international regimes, such as the Millennium Development Goals (MDGs). In this way charcoal production can significantly contribute to poverty reduction and environmental sustainability. (C) 2012 International Energy Initiative. Published by Elsevier Inc. All rights reserved. | G74: 10.1016/j.esd.2012.07.004 | H74: http://dx.doi.org/10.1016/j.esd.2012.07.004 | I74: Green & Sustainable Science & Technology; Energy & Fuels | J74: 45982 | K74: WOS:000317091400003 | L74: View Full Record in Web of Science
A75: J | B75: Ausubel, JH; Wernick, IK; Waggoner, PE | C75: Peak Farmland and the Prospect for Land Sparing | D75: POPULATION AND DEVELOPMENT REVIEW | E75: Article | G75: 10.1111/j.1728-4457.2013.00561.x | H75: http://dx.doi.org/10.1111/j.1728-4457.2013.00561.x | I75: Demography; Sociology | J75: 45982 | K75: WOS:000315224500015 | L75: View Full Record in Web of Science
A76: J | B76: Klimont, Z; Smith, SJ; Cofala, J | C76: The last decade of global anthropogenic sulfur dioxide: 2000-2011 emissions | D76: ENVIRONMENTAL RESEARCH LETTERS | E76: Article | F76: The evolution of global and regional anthropogenic SO2 emissions in the last decade has been estimated through a bottom-up calculation. After increasing until about 2006, we estimate a declining trend continuing until 2011. However, there is strong spatial variability, with North America and Europe continuing to reduce emissions, with an increasing role of Asia and international shipping. China remains a key contributor, but the introduction of stricter emission limits followed by an ambitious program of installing flue gas desulfurization on power plants resulted in a significant decline in emissions from the energy sector and stabilization of total Chinese SO2 emissions. Comparable mitigation strategies are not yet present in several other Asian countries and industrial sectors in general, while emissions from international shipping are expected to start declining soon following an international agreement to reduce the sulfur content of fuel oil. The estimated trends in global SO2 emissions are within the range of representative concentration pathway (RCP) projections and the uncertainty previously estimated for the year 2005. | G76: 10.1088/1748-9326/8/1/014003 | H76: http://dx.doi.org/10.1088/1748-9326/8/1/014003 | I76: Environmental Sciences; Meteorology & Atmospheric Sciences | J76: 45982 | K76: WOS:000316998300011 | L76: View Full Record in Web of Science
A77: J | B77: Simberloff, D; Martin, JL; Genovesi, P; Maris, V; Wardle, DA; Aronson, J; Courchamp, F; Galil, B; García-Berthou, E; Pascal, M; Pysek, P; Sousa, R; Tabacchi, E; Vilà, M | C77: Impacts of biological invasions: what's what and the way forward | D77: TRENDS IN ECOLOGY & EVOLUTION | E77: Review | F77: Study of the impacts of biological invasions, a pervasive component of global change, has generated remarkable understanding of the mechanisms and consequences of the spread of introduced populations. The growing field of invasion science, poised at a crossroads where ecology, social sciences, resource management, and public perception meet, is increasingly exposed to critical scrutiny from several perspectives. Although the rate of biological invasions, elucidation of their consequences, and knowledge about mitigation are growing rapidly, the very need for invasion science is disputed. Here, we highlight recent progress in understanding invasion impacts and management, and discuss the challenges that the discipline faces in its science and interactions with society. | G77: 10.1016/j.tree.2012.07.013 | H77: http://dx.doi.org/10.1016/j.tree.2012.07.013 | I77: Ecology; Evolutionary Biology; Genetics & Heredity | J77: 45982 | K77: WOS:000314142100012 | L77: View Full Record in Web of Science
A78: S | B78: Stammer, D; Cazenave, A; Ponte, RM; Tamisiea, ME | C78: Causes for Contemporary Regional Sea Level Changes | D78: ANNUAL REVIEW OF MARINE SCIENCE, VOL 5 | E78: Review; Book Chapter | F78: Regional sea level changes can deviate substantially from those of the global mean, can vary on a broad range of timescales, and in some regions can even lead to a reversal of long-term global mean sea level trends. The underlying causes are associated with dynamic variations in the ocean circulation as part of climate modes of variability and with an isostatic adjustment of Earth's crust to past and ongoing changes in polar ice masses and continental water storage. Relative to the coastline, sea level is also affected by processes such as earthquakes and anthropogenically induced subsidence. Present-day regional sea level changes appear to be caused primarily by natural climate variability. However, the imprint of anthropogenic effects on regional sea level-whether due to changes in the atmospheric forcing or to mass variations in the system-will grow with time as climate change progresses, and toward the end of the twenty-first century, regional sea level patterns will be a superposition of climate variability modes and natural and anthropogenically induced static sea level patterns. Attribution and predictions of ongoing and future sea level changes require an expanded and sustained climate observing system. | G78: 10.1146/annurev-marine-121211-172406 | H78: http://dx.doi.org/10.1146/annurev-marine-121211-172406 | I78: Geochemistry & Geophysics; Marine & Freshwater Biology; Oceanography | J78: 45982 | K78: WOS:000316390400003 | L78: View Full Record in Web of Science
A79: J | B79: Houghton, RA | C79: Carbon emissions and the drivers of deforestation and forest degradation in the tropics | D79: CURRENT OPINION IN ENVIRONMENTAL SUSTAINABILITY | E79: Review | F79: The net emissions of carbon from deforestation and degradation in the tropics, including the draining and burning of peat swamps in SE Asia, averaged similar to 1.4 (+/- 0.5) PgC yr(-1) over the period 1990-2010. Most (60-90%) of the emissions were from deforestation; degradation (or reductions of biomass density within forests) is more difficult to document but results from harvest of wood and the re-clearing of fallow forests within the shifting cultivation cycle. The main driver of deforestation is agriculture, whether permanent or shifting, and whether for food crops or pasture. The relative contribution of deforestation and degradation to anthropogenic carbon emissions has been declining, but reducing emissions from land, along with reduced emissions from fossil fuels, could help stabilize the CO2 concentration of the atmosphere. | G79: 10.1016/j.cosust.2012.06.006 | H79: http://dx.doi.org/10.1016/j.cosust.2012.06.006 | I79: Green & Sustainable Science & Technology; Environmental Sciences | J79: 45982 | K79: WOS:000312418600003 | L79: View Full Record in Web of Science
A80: J | B80: Sallenger, AH; Doran, KS; Howd, PA | C80: Hotspot of accelerated sea-level rise on the Atlantic coast of North America | D80: NATURE CLIMATE CHANGE | E80: Article | F80: Climate warming does not force sea-level rise (SLR) at the same rate everywhere. Rather, there are spatial variations of SLR superimposed on a global average rise. These variations are forced by dynamic processes(1-4), arising from circulation and variations in temperature and/or salinity, and by static equilibrium processes(5), arising from mass redistributions changing gravity and the Earth's rotation and shape. These sea-level variations form unique spatial patterns, yet there are very few observations verifying predicted patterns or fingerprints(6). Here, we present evidence of recently accelerated SLR in a unique 1,000-km-long hotspot on the highly populated North American Atlantic coast north of Cape Hatteras and show that it is consistent with a modelled fingerprint of dynamic SLR. Between 1950-1979 and 1980-2009, SLR rate increases in this northeast hotspot were similar to 3-4 times higher than the global average. Modelled dynamic plus steric SLR by 2100 at New York City ranges with Intergovernmental Panel on Climate Change scenario from 36 to 51 cm (ref. 3); lower emission scenarios project 24-36 cm (ref. 7). Extrapolations from data herein range from 20 to 29 cm. SLR superimposed on storm surge, wave run-up and set-up will increase the vulnerability of coastal cities to flooding, and beaches and wetlands to deterioration. | G80: 10.1038/NCLIMATE1597 | H80: http://dx.doi.org/10.1038/NCLIMATE1597 | I80: Environmental Sciences; Environmental Studies; Meteorology & Atmospheric Sciences | J80: 45982 | K80: WOS:000312433700023 | L80: View Full Record in Web of Science
A81: J | B81: Miettinen, J; Hooijer, A; Shi, CH; Tollenaar, D; Vernimmen, R; Liew, SC; Malins, C; Page, SE | C81: Extent of industrial plantations on Southeast Asian peatlands in 2010 with analysis of historical expansion and future projections | D81: GLOBAL CHANGE BIOLOGY BIOENERGY | E81: Article | F81: Tropical peatlands cover over 25 Mha in Southeast Asia and are estimated to contain around 70 Gt of carbon. Peat swamp forest ecosystems are an important part of the region's natural resources supporting unique flora and fauna endemic to Southeast Asia. Over recent years, industrial plantation development on peatland, especially for oil palm cultivation, has created intense debate due to its potentially adverse social and environmental effects. The lack of objective up-to-date information on the extent of industrial plantations has complicated quantification of their regional and global environmental consequences, both in terms of loss of forest and biodiversity as well as increases in carbon emissions. Based on visual interpretation of high-resolution (30 m) satellite images, we find that industrial plantations covered over 3.1 Mha (20%) of the peatlands of Peninsular Malaysia, Sumatra and Borneo in 2010, surpassing the area of Belgium and causing an annual carbon emission from peat decomposition of 230310 Mt CO2e. The majority (62%) of the plantations were located on the island of Sumatra, and over two-thirds (69%) of all industrial plantations were developed for oil palm cultivation, with the remainder mostly being Acacia plantations for paper pulp production. Historical analysis shows strong acceleration of plantation development in recent years: 70% of all industrial plantations have been established since 2000 and only 4% of the current plantation area existed in 1990. Business-as-usual projections of future conversion rates, based on historical rates over the past two decades, indicate that 69 Mha of peatland in insular Southeast Asia may be converted to plantations by the year 2020, unless land use planning policies or markets for products change. This would increase the annual carbon emission to somewhere between 380 and 920 Mt CO2e by 2020 depending on water management practices and the extent of plantations. | G81: 10.1111/j.1757-1707.2012.01172.x | H81: http://dx.doi.org/10.1111/j.1757-1707.2012.01172.x | I81: Agronomy; Biotechnology & Applied Microbiology; Energy & Fuels | J81: 45982 | K81: WOS:000309450100028 | L81: View Full Record in Web of Science
A82: J | B82: Hosonuma, N; Herold, M; De Sy, V; De Fries, RS; Brockhaus, M; Verchot, L; Angelsen, A; Romijn, E | C82: An assessment of deforestation and forest degradation drivers in developing countries | D82: ENVIRONMENTAL RESEARCH LETTERS | E82: Article | F82: Countries are encouraged to identify drivers of deforestation and forest degradation in the development of national strategies and action plans for REDD+. In this letter we provide an assessment of proximate drivers of deforestation and forest degradation by synthesizing empirical data reported by countries as part of their REDD+ readiness activities, CIFOR country profiles, UNFCCC national communications and scientific literature. Based on deforestation rate and remaining forest cover 100 (sub) tropical non-Annex I countries were grouped into four forest transition phases. Driver data of 46 countries were summarized for each phase and by continent, and were used as a proxy to estimate drivers for the countries with missing data. The deforestation drivers are similar in Africa and Asia, while degradation drivers are more similar in Latin America and Asia. Commercial agriculture is the most important driver of deforestation, followed by subsistence agriculture. Timber extraction and logging drives most of the degradation, followed by fuelwood collection and charcoal production, uncontrolled fire and livestock grazing. The results reflect the most up to date and comprehensive overview of current national-level data availability on drivers, which is expected to improve over time within the frame of the UNFCCC REDD+ process. | G82: 10.1088/1748-9326/7/4/044009 | H82: http://dx.doi.org/10.1088/1748-9326/7/4/044009 | I82: Environmental Sciences; Meteorology & Atmospheric Sciences | J82: 45982 | K82: WOS:000312696400013 | L82: View Full Record in Web of Science
A83: J | B83: Alcantara, C; Kuemmerle, T; Prishchepov, AV; Radeloff, VC | C83: Mapping abandoned agriculture with multi-temporal MODIS satellite data | D83: REMOTE SENSING OF ENVIRONMENT | E83: Article | F83: Agriculture is expanding and intensifying in many areas of the world, but abandoned agriculture is also becoming more widespread. Unfortunately, data and methods to monitor abandoned agriculture accurately over large areas are lacking. Remote sensing methods may be able to fill this gap though, especially with the frequent observations provided by coarser-resolution sensors and new classification techniques. Past efforts to map abandoned agriculture relied mainly on Landsat data, making it hard to map large regions, and precluding the use of phenology information to identify abandoned agriculture. Our objective here was to test methods to map abandoned agriculture at broad scales with coarse-resolution satellite imagery and phenology data. We classified abandoned agriculture for one Moderate Resolution Imaging Spectroradiometer (MODIS) tile in Eastern Europe (-1,236,000 km(2)) where abandoned agriculture was widespread. Input data included Normalized Difference Vegetation Index (NDVI) and reflectance bands (NASA Global MODIS Terra and Aqua 16-Day Vegetation Indices for the years 2003 through 2008, -250-m resolution), as well as phenology metrics calculated with TIMESAT. The data were classified with Support Vector Machines (SVM). Training data were derived from several Landsat classifications of agricultural abandonment in the study area. A validation was conducted based on independently collected data. Our results showed that it is possible to map abandoned agriculture for large areas from MODIS data with an overall classification accuracy of 65%. Abandoned agriculture was widespread in our study area (15.1% of the total area, compared to 29.6% agriculture). We found strong differences in the MODIS data quality for different years, with data from 2005 resulting in the highest classification accuracy for the abandoned agriculture class (42.8% producer's accuracy). Classifications of MODIS NDVI data were almost as accurate as classifications based on a combination of both red and near-infrared reflectance data. MODIS NDVI data only from the growing-season resulted in similar classification accuracy as data for the full year. Using multiple years of MODIS data did not increase classification accuracy. Six phenology metrics derived with TIMESAT from the NDVI time series (2003-2008) alone were insufficient to detect abandoned agriculture, but phenology metrics improved classification accuracies when used in conjunction with NDVI time series by more than 8% over the use of NDVI data alone. The approach that we identified here is promising and suggests that it is possible to map abandoned agriculture at broad scales, which is relevant to gain a better understanding of this important land use change process. (C) 2012 Elsevier Inc. All rights reserved. | G83: 10.1016/j.rse.2012.05.019 | H83: http://dx.doi.org/10.1016/j.rse.2012.05.019 | I83: Environmental Sciences; Remote Sensing; Imaging Science & Photographic Technology | J83: 45982 | K83: WOS:000311247700029 | L83: View Full Record in Web of Science
A84: J | B84: Alverson, K | C84: VULNERABILITY, IMPACTS, AND ADAPTATION TO SEA LEVEL RISE TAKING AN ECOSYSTEM-BASED APPROACH | D84: OCEANOGRAPHY | E84: Editorial Material | G84: 10.5670/oceanog.2012.101 | H84: http://dx.doi.org/10.5670/oceanog.2012.101 | I84: Oceanography | J84: 45982 | K84: WOS:000308774600037 | L84: View Full Record in Web of Science
A85: J | B85: Greaver, TL; Sullivan, TJ; Herrick, JD; Barber, MC; Baron, JS; Cosby, BJ; Deerhake, ME; Dennis, RL; Dubois, JJB; Goodale, CL; Herlihy, AT; Lawrence, GB; Liu, LL; Lynch, JA; Novak, KJ | C85: Ecological effects of nitrogen and sulfur air pollution in the US: what do we know? | D85: FRONTIERS IN ECOLOGY AND THE ENVIRONMENT | E85: Review | F85: Four decades after the passage of the US Clean Air Act, air-quality standards are set to protect ecosystems from damage caused by gas-phase nitrogen (N) and sulfur (S) compounds, but not from the deposition of these air pollutants to land and water. Here, we synthesize recent scientific literature on the ecological effects of N and S air pollution in the US. Deposition of N and S is the main driver of ecosystem acidification and contributes to nutrient enrichment in many natural systems. Although surface-water acidification has decreased in the US since 1990, it remains a problem in many regions. Perturbations to ecosystems caused by the nutrient effects of N deposition continue to emerge, although gas-phase concentrations are generally not high enough to cause phytotoxicity. In all, there is overwhelming evidence of a broad range of damaging effects to ecosystems in the US under current air-quality conditions. | G85: 10.1890/110049 | H85: http://dx.doi.org/10.1890/110049 | I85: Ecology; Environmental Sciences | J85: 45982 | K85: WOS:000309092700015 | L85: View Full Record in Web of Science
A86: J | B86: Srebotnjak, T; Carr, G; de Sherbinin, A; Rickwood, C | C86: A global Water Quality Index and hot-deck imputation of missing data | D86: ECOLOGICAL INDICATORS | E86: Article | F86: Water is an essential resource for life on Earth and available freshwater resources are emerging as a limiting factor not only in quantity but also in quality for human development and ecological stability in a growing number of locations. Water quality is a significant criterion in matching water demand and supply. Securing adequate freshwater quality for both human and ecological needs is thus an important aspect of integrated environmental management and sustainable development. The 2008 Environmental Performance Index (EPI) published by the Yale Center for Environmental Law and Policy (YCELP) and the Center for International Earth Science Information Network (CIESIN) at Columbia University includes a Water Quality Index (WATQI). The WATQI provides a first global effort at reporting and estimating water quality on the basis of five commonly reported quality parameters: dissolved oxygen, electrical conductivity, pH value, and total nitrogen and phosphorus concentrations. This paper explains the motivation and methodology of the EPI WATQI and demonstrates how hot-deck imputation of missing values can expand its geographical coverage and better inform decision-makers on the types and extents of water quality problems in the context of limited globally comparable water quality monitoring data. (C) 2011 Elsevier Ltd. All rights reserved. | G86: 10.1016/j.ecolind.2011.04.023 | H86: http://dx.doi.org/10.1016/j.ecolind.2011.04.023 | I86: Biodiversity Conservation; Environmental Sciences | J86: 45982 | K86: WOS:000300208400013 | L86: View Full Record in Web of Science
A87: J | B87: van Vliet, N; Mertz, O; Heinimann, A; Langanke, T; Pascual, U; Schmook, B; Adams, C; Schmidt-Vogt, D; Messerli, P; Leisz, S; Castella, JC; Jorgensen, L; Birch-Thomsen, T; Hett, C; Bruun, TB; Ickowitz, A; Vu, KC; Yasuyuki, K; Fox, J; Padoch, C; Dressler, W; Ziegler, AD | C87: Trends, drivers and impacts of changes in swidden cultivation in tropical forest-agriculture frontiers: A global assessment | D87: GLOBAL ENVIRONMENTAL CHANGE-HUMAN AND POLICY DIMENSIONS | E87: Article | F87: This meta-analysis of land-cover transformations of the past 10-15 years in tropical forest-agriculture frontiers world-wide shows that swidden agriculture decreases in landscapes with access to local, national and international markets that encourage cattle production and cash cropping, including biofuels. Conservation policies and practices also accelerate changes in swidden by restricting forest clearing and encouraging commercial agriculture. However, swidden remains important in many frontier areas where farmers have unequal or insecure access to investment and market opportunities, or where multi-functionality of land uses has been preserved as a strategy to adapt to current ecological, economic and political circumstances. In some areas swidden remains important simply because intensification is not a viable choice, for example when population densities and/or food market demands are low. The transformation of swidden landscapes into more intensive land uses has generally increased household incomes, but has also led to negative effects on the social and human capital of local communities to varying degrees. From an environmental perspective, the transition from swidden to other land uses often contributes to permanent deforestation, loss of biodiversity, increased weed pressure, declines in soil fertility, and accelerated soil erosion. Our prognosis is that, despite the global trend towards land use intensification, in many areas swidden will remain part of rural landscapes as the safety component of diversified systems, particularly in response to risks and uncertainties associated with more intensive land use systems. (C) 2011 Elsevier Ltd. All rights reserved. | G87: 10.1016/j.gloenvcha.2011.10.009 | H87: http://dx.doi.org/10.1016/j.gloenvcha.2011.10.009 | I87: Environmental Sciences; Environmental Studies; Geography | J87: 45982 | K87: WOS:000304290100012 | L87: View Full Record in Web of Science
A88: J | B88: Rummukainen, M | C88: Changes in climate and weather extremes in the 21st century | D88: WILEY INTERDISCIPLINARY REVIEWS-CLIMATE CHANGE | E88: Article | F88: Climate and weather extremes are sporadically recurring events that may have major local or regional impacts on the society and the environment. These events are typically related to unusually high or low temperature, prolonged dry or wet conditions, heavy precipitation, or extreme winds. Extreme events are part of the overall climate and weather alongside average conditions and variability, and thus are not unexpected as such. Climate change is expected to affect not only means but also variability and extremes. Some inferences can be based on past and present observations, but analyses of especially rare events are hampered by the availability of long time series. Over time, depending on how far the on-going global warming takes us from the present and the past climate conditions, the weather and climate statistics may well come to shift in ways that are well outside observational data. This may lead to shifts in frequency, intensity and geographical distribution of different extremes. Indeed, projected changes in some extremes over the 21st century are quite robust, such as generally increasing warm and decreasing cold extremes. Possible changes in some other aspects, for example storms, remain much more uncertain. Science-based information both on robust findings and on relevant uncertainties on changing extremes can provide useful information for sectorial planning, disaster risk prevention and overall reduction of societal vulnerability related to climate and weather. WIREs Clim Change 2012, 3:115129. doi: 10.1002/wcc.160 | G88: 10.1002/wcc.160 | H88: http://dx.doi.org/10.1002/wcc.160 | I88: Environmental Studies; Meteorology & Atmospheric Sciences | J88: 45982 | K88: WOS:000301644400001 | L88: View Full Record in Web of Science
A89: J | B89: Macedo, MN; DeFries, RS; Morton, DC; Stickler, CM; Galford, GL; Shimabukuro, YE | C89: Decoupling of deforestation and soy production in the southern Amazon during the late 2000s | D89: PROCEEDINGS OF THE NATIONAL ACADEMY OF SCIENCES OF THE UNITED STATES OF AMERICA | E89: Article | F89: From 2006 to 2010, deforestation in the Amazon frontier state of Mato Grosso decreased to 30% of its historical average (1996-2005) whereas agricultural production reached an all-time high. This study combines satellite data with government deforestation and production statistics to assess land-use transitions and potential market and policy drivers associated with these trends. In the forested region of the state, increased soy production from 2001 to 2005 was entirely due to cropland expansion into previously cleared pasture areas (74%) or forests (26%). From 2006 to 2010, 78% of production increases were due to expansion (22% to yield increases), with 91% on previously cleared land. Cropland expansion fell from 10 to 2% of deforestation between the two periods, with pasture expansion accounting for most remaining deforestation. Declining deforestation coincided with a collapse of commodity markets and implementation of policy measures to reduce deforestation. Soybean profitability has since increased to pre-2006 levels whereas deforestation continued to decline, suggesting that antideforestation measures may have influenced the agricultural sector. We found little evidence of direct leakage of soy expansion into cerrado in Mato Grosso during the late 2000s, although indirect land-use changes and leakage to more distant regions are possible. This study provides evidence that reduced deforestation and increased agricultural production can occur simultaneously in tropical forest frontiers, provided that land is available and policies promote the efficient use of already-cleared lands (intensification) while restricting deforestation. It remains uncertain whether government- and industry-led policies can contain deforestation if future market conditions favor another boom in agricultural expansion. | G89: 10.1073/pnas.1111374109 | H89: http://dx.doi.org/10.1073/pnas.1111374109 | I89: Multidisciplinary Sciences | J89: 45982 | K89: WOS:000299412600068 | L89: View Full Record in Web of Science
A90: J | B90: Hostert, P; Kuemmerle, T; Prishchepov, A; Sieber, A; Lambin, EF; Radeloff, VC | C90: Rapid land use change after socio-economic disturbances: the collapse of the Soviet Union versus Chernobyl | D90: ENVIRONMENTAL RESEARCH LETTERS | E90: Article | F90: Land use change is a principal force and inherent element of global environmental change, threatening biodiversity, natural ecosystems, and their services. However, our ability to anticipate future land use change is severely limited by a lack of understanding of how major socio-economic disturbances (e. g., wars, revolutions, policy changes, and economic crises) affect land use. Here we explored to what extent socio-economic disturbances can shift land use systems onto a different trajectory, and whether this can result in less intensive land use. Our results show that the collapse of the Soviet Union in 1991 caused a major reorganization in land use systems. The effects of this socio-economic disturbance were at least as drastic as those of the nuclear disaster in the Chernobyl region in 1986. While the magnitudes of land abandonment were similar in Ukraine and Belarus in the case of the nuclear disaster (28% and 36% of previously farmed land, respectively), the rates of land abandonment after the collapse of the Soviet Union in Ukraine were twice as high as those in Belarus. This highlights that national policies and institutions play an important role in mediating effects of socio-economic disturbances. The socio-economic disturbance that we studied caused major hardship for local populations, yet also presents opportunities for conservation, as natural ecosystems are recovering on large areas of former farmland. Our results illustrate the potential of socio-economic disturbances to revert land use intensification and the important role institutions and policies play in determining land use systems' resilience against such socio-economic disturbances. | G90: 10.1088/1748-9326/6/4/045201 | H90: http://dx.doi.org/10.1088/1748-9326/6/4/045201 | I90: Environmental Sciences; Meteorology & Atmospheric Sciences | J90: 45982 | K90: WOS:000298674700039 | L90: View Full Record in Web of Science
A91: J | B91: Ongondo, FO; Williams, ID; Cherrett, TJ | C91: How are WEEE doing? A global review of the management of electrical and electronic wastes | D91: WASTE MANAGEMENT | E91: Review | F91: This paper presents and critically analyses the current waste electrical and electronic equipment (WEEE) management practices in various countries and regions. Global trends in (i) the quantities and composition of WEEE; and (ii) the various strategies and practices adopted by selected countries to handle, regulate and prevent WEEE are comprehensively examined. The findings indicate that for (i), the quantities of WEEE generated are high and/or on the increase. IT and telecommunications equipment seem to be the dominant WEEE being generated, at least in terms of numbers, in Africa, in the poorer regions of Asia and in Latin/South America. However, the paper contends that the reported figures on quantities of WEEE generated may be grossly underestimated. For (ii), with the notable exception of Europe, many countries seem to be lacking or are slow in initiating, drafting and adopting WEEE regulations. Handling of WEEE in developing countries is typified by high rate of repair and reuse within a largely informal recycling sector. In both developed and developing nations, the landfilling of WEEE is still a concern. It has been established that stockpiling of unwanted electrical and electronic products is common in both the USA and less developed economies. The paper also identifies and discusses four common priority areas for WEEE across the globe, namely: (i) resource depletion; (ii) ethical concerns; (iii) health and environmental issues; and (iv) WEEE takeback strategies. Further, the paper discusses the future perspectives on WEEE generation, treatment, prevention and regulation. Four key conclusions are drawn from this review: global amounts of WEEE will continue unabated for some time due to emergence of new technologies and affordable electronics; informal recycling in developing nations has the potential of making a valuable contribution if their operations can be changed with strict safety standards as a priority; the pace of initiating and enacting WEEE specific legislation is very slow across the globe and in some cases non-existent; and globally, there is need for more accurate and current data on amounts and types of WEEE generated. (C) 2010 Elsevier Ltd. All rights reserved. | G91: 10.1016/j.wasman.2010.10.023 | H91: http://dx.doi.org/10.1016/j.wasman.2010.10.023 | I91: Engineering, Environmental; Environmental Sciences | J91: 45982 | K91: WOS:000288576800013 | L91: View Full Record in Web of Science
A92: J | B92: Rask, KJ; Rask, N | C92: Economic development and food production-consumption balance: A growing global challenge | D92: FOOD POLICY | E92: Article | F92: Rising affluence in major developing countries (principally China and India) and increasing diversion of agricultural resources for energy production (USA and Brazil) sharply increase agricultural resource demand. Food consumption and production changes during development are analyzed using resource-based cereal-equivalent measures. Diet upgrades to livestock products require fivefold increases in per capita food resource use, reflecting a consistent pattern which is only marginally affected by land base. Food consumption increases exceed production during early development, leading to imports. Consumption eventually stabilizes at high incomes, but production falls short in land-scarce countries. Pork and poultry consumption increase the most; less efficient beef and dairy production command a majority of agricultural resources. (C) 2010 Elsevier Ltd. All rights reserved. | G92: 10.1016/j.foodpol.2010.11.015 | H92: http://dx.doi.org/10.1016/j.foodpol.2010.11.015 | I92: Agricultural Economics & Policy; Economics; Food Science & Technology; Nutrition & Dietetics | J92: 45982 | K92: WOS:000289340500011 | L92: View Full Record in Web of Science
A93: J | B93: Lambin, EF; Meyfroidt, P | C93: Global land use change, economic globalization, and the looming land scarcity | D93: PROCEEDINGS OF THE NATIONAL ACADEMY OF SCIENCES OF THE UNITED STATES OF AMERICA | E93: Article | F93: A central challenge for sustainability is how to preserve forest ecosystems and the services that they provide us while enhancing food production. This challenge for developing countries confronts the force of economic globalization, which seeks cropland that is shrinking in availability and triggers deforestation. Four mechanisms-the displacement, rebound, cascade, and remittance effects-that are amplified by economic globalization accelerate land conversion. A few developing countries have managed a land use transition over the recent decades that simultaneously increased their forest cover and agricultural production. These countries have relied on various mixes of agricultural intensification, land use zoning, forest protection, increased reliance on imported food and wood products, the creation of off-farm jobs, foreign capital investments, and remittances. Sound policies and innovations can therefore reconcile forest preservation with food production. Globalization can be harnessed to increase land use efficiency rather than leading to uncontrolled land use expansion. To do so, land systems should be understood and modeled as open systems with large flows of goods, people, and capital that connect local land use with global-scale factors. | G93: 10.1073/pnas.1100480108 | H93: http://dx.doi.org/10.1073/pnas.1100480108 | I93: Multidisciplinary Sciences | J93: 45982 | K93: WOS:000287844400010 | L93: View Full Record in Web of Science
A94: J | B94: Hegerl, G; Luterbacher, J; González-Rouco, F; Tett, SFB; Crowley, T; Xoplaki, E | C94: Influence of human and natural forcing on European seasonal temperatures | D94: NATURE GEOSCIENCE | E94: Article | F94: It is the regional and seasonal expression of climate change that determines the effect of greenhouse warming on ecosystems and society(1). Whereas anthropogenic influences on European temperatures have been detected over the twentieth century(2,3), it has been suggested that the impact of external influences on European temperatures before 1900 is negligible(4). Here we use reconstructions of seasonal European land temperature(5,6) and simulations with three global climate models(7-9) to show that external influences on climate-such as the concentrations of stratospheric volcanic aerosols or greenhouse gases, other anthropogenic effects and possibly changes in total solar irradiance-have had a discernible influence on European temperatures throughout the past five centuries. In particular, we find that external forcing contributes significantly (p < 5%) to the reconstructed long-term variability of winter and spring temperatures and that it is responsible for a best guess of 75% of the observed winter warming since the late seventeenth century. This warming is largely attributable to greenhouse-gas forcing. Summer temperatures show detectable (p < 5%) interdecadal variations in response to external forcing before 1900 only. Finally, throughout the record we detect highly significant summer cooling and significant winter warming following volcanic eruptions. | G94: 10.1038/NGEO1057 | H94: http://dx.doi.org/10.1038/NGEO1057 | I94: Geosciences, Multidisciplinary | J94: 45982 | K94: WOS:000286723300014 | L94: View Full Record in Web of Science
A95: J | B95: Page, SE; Rieley, JO; Banks, CJ | C95: Global and regional importance of the tropical peatland carbon pool | D95: GLOBAL CHANGE BIOLOGY | E95: Review | F95: Accurate inventory of tropical peatland is important in order to (a) determine the magnitude of the carbon pool; (b) estimate the scale of transfers of peat-derived greenhouse gases to the atmosphere resulting from land use change; and (c) support carbon emissions reduction policies. We review available information on tropical peatland area and thickness and calculate peat volume and carbon content in order to determine their best estimates and ranges of variation. Our best estimate of tropical peatland area is 441 025 km2 (similar to 11% of global peatland area) of which 247 778 km2 (56%) is in Southeast Asia. We estimate the volume of tropical peat to be 1758 Gm3 (similar to 18-25% of global peat volume) with 1359 Gm3 in Southeast Asia (77% of all tropical peat). This new assessment reveals a larger tropical peatland carbon pool than previous estimates, with a best estimate of 88.6 Gt (range 81.7-91.9 Gt) equal to 15-19% of the global peat carbon pool. Of this, 68.5 Gt (77%) is in Southeast Asia, equal to 11-14% of global peat carbon. A single country, Indonesia, has the largest share of tropical peat carbon (57.4 Gt, 65%), followed by Malaysia (9.1 Gt, 10%). These data are used to provide revised estimates for Indonesian and Malaysian forest soil carbon pools of 77 and 15 Gt, respectively, and total forest carbon pools (biomass plus soil) of 97 and 19 Gt. Peat carbon contributes 60% to the total forest soil carbon pool in Malaysia and 74% in Indonesia. These results emphasize the prominent global and regional roles played by the tropical peat carbon pool and the importance of including this pool in national and regional assessments of terrestrial carbon stocks and the prediction of peat-derived greenhouse gas emissions. | G95: 10.1111/j.1365-2486.2010.02279.x | H95: http://dx.doi.org/10.1111/j.1365-2486.2010.02279.x | I95: Biodiversity Conservation; Ecology; Environmental Sciences | J95: 45982 | K95: WOS:000285878000013 | L95: View Full Record in Web of Science
A96: S | B96: Carpenter, SR; Stanley, EH; Vander Zanden, MJ | C96: State of the World's Freshwater Ecosystems: Physical, Chemical, and Biological Changes | D96: ANNUAL REVIEW OF ENVIRONMENT AND RESOURCES, VOL 36 | E96: Review; Book Chapter | F96: Surface freshwaters-lakes, reservoirs, and rivers are among the most extensively altered ecosystems on Earth. Transformations include changes in the morphology of rivers and lakes, hydrology, biogeochemistry of nutrients and toxic substances, ecosystem metabolism and the storage of carbon (C), loss of native species, expansion of invasive species, and disease emergence. Drivers are climate change, hydrologic flow modification, land-use change, chemical inputs, aquatic invasive species, and harvest. Drivers and responses interact, and their relationships must be disentangled to understand the causes and consequences of change as well as the correctives for adverse change in any given watershed. Beyond its importance in terms of drinking water, freshwater supports human well-being in many ways related to food and fiber production, hydration of other ecosystems used by humans, dilution and degradation of pollutants, and cultural values. A natural capital framework can be used to assess freshwater ecosystem services, competing uses for freshwaters, and the processes that underpin the long-term maintenance of freshwaters. Upper limits for human consumption of freshwaters have been proposed, and consumptive use may approach these limits by the mid-century. | G96: 10.1146/annurev-environ-021810-094524 | H96: http://dx.doi.org/10.1146/annurev-environ-021810-094524 | I96: Environmental Sciences; Environmental Studies | J96: 45982 | K96: WOS:000299610900004 | L96: View Full Record in Web of Science
... A150: J | B150: Lucht, W; Prentice, IC; Myneni, RB; Sitch, S; Friedlingstein, P; Cramer, W; Bousquet, P; Buermann, W; Smith, B | C150: Climatic control of the high-latitude vegetation greening trend and Pinatubo effect | D150: SCIENCE | E150: Article | F150: A biogeochemical model of vegetation using observed climate data predicts the high northern latitude greening trend over the past two decades observed by satellites and a marked setback in this trend after the Mount Pinatubo, volcano eruption in 1991. The observed trend toward earlier spring budburst and increased maximum leaf area is produced by the model as a consequence of biogeochemical vegetation responses mainly to changes in temperature. The post-Pinatubo decline in vegetation in 1992-1993 is apparent as the effect of temporary cooling caused by the eruption. High-latitude CO2 uptake during these years is predicted as a consequence of the differential response of heterotrophic respiration and net primary production. | G150: 10.1126/science.1071828 | H150: http://dx.doi.org/10.1126/science.1071828 | I150: Multidisciplinary Sciences | J150: 45982 | K150: WOS:000175976200058 | L150: View Full Record in Web of Science
A151: J | B151: Barnes, DKA | C151: Biodiversity - Invasions by marine life on plastic debris | D151: NATURE | E151: Article | G151: 10.1038/416808a | H151: http://dx.doi.org/10.1038/416808a | I151: Multidisciplinary Sciences | J151: 45982 | K151: WOS:000175163800039 | L151: View Full Record in Web of Science
A152: J | B152: Geist, HJ; Lambin, EF | C152: Proximate causes and underlying driving forces of tropical deforestation | D152: BIOSCIENCE | E152: Article | G152: 10.1641/0006-3568(2002)052[0143:PCAUDF]2.0.CO;2 | H152: http://dx.doi.org/10.1641/0006-3568(2002)052[0143:PCAUDF]2.0.CO;2 | I152: Biology | J152: 45982 | K152: WOS:000173839600005 | L152: View Full Record in Web of Science
A153: J | B153: Skjelkvåle, BL; Stoddard, JL; Andersen, T | C153: Trends in surface water acidification in Europe and North America (1989-1998) | D153: WATER AIR AND SOIL POLLUTION | E153: Article; Proceedings Paper | F153: During the last 20 years, emission reductions in Europe and North America have resulted in decreased atmospheric S-deposition of up to 50%, while N-deposition has stayed almost constant. Data from 98 ICP Waters sites were tested for trends in concentrations of major chemical components for the 10-year period 1989-1998 using the nonparametric seasonal Kendall test. The sites were grouped into regions and types for meta-analysis. All of the regions had highly significant downward trends in SO42-* concentrations. Nitrate concentrations, on the other hand: show no regional patterns of change. Concentrations of base cations declined in most regions. All regions showed tendencies of increasing DOC. The low ANC sites showed the largest rates of recovery. Neither the high NO3- or low NO3- groups of sites exhibited significant trends in NO3- concentrations. Alpine (non-forested) sites show clear and consistent signals of recovery in ANC and pH, and appropriate (relative to SO42-* trends) rates of base cation decline. | G153: 10.1023/A:1013806223310 | H153: http://dx.doi.org/10.1023/A:1013806223310 | I153: Environmental Sciences; Meteorology & Atmospheric Sciences; Water Resources | J153: 45982 | K153: WOS:000172011900102 | L153: View Full Record in Web of Science
A154: J | B154: Driscoll, CT; Lawrence, GB; Bulger, AJ; Butler, TJ; Cronan, CS; Eagar, C; Lambert, KF; Likens, GE; Stoddard, JL; Weathers, KC | C154: Acidic deposition in the northeastern United States: Sources and inputs, ecosystem effects, and management strategies | D154: BIOSCIENCE | E154: Article | G154: 10.1641/0006-3568(2001)051[0180:ADITNU]2.0.CO;2 | H154: http://dx.doi.org/10.1641/0006-3568(2001)051[0180:ADITNU]2.0.CO;2 | I154: Biology | J154: 45982 | K154: WOS:000168710400004 | L154: View Full Record in Web of Science
A155: J | B155: Pretty, JN; Brett, C; Gee, D; Hine, RE; Mason, CF; Morison, JIL; Raven, H; Rayment, MD; van der Bijl, G | C155: An assessment of the total external costs of UK agriculture | D155: AGRICULTURAL SYSTEMS | E155: Article | F155: This trans-disciplinary study assesses total external environmental and health costs of modern agriculture in the UK. A wide range of datasets have been analysed to assess cost distribution across sectors. We calculate the annual total external costs of UK agriculture in 1996 to be pound 2343 m (range for 1990-1996: pound 1149-3907 m), equivalent to pound 208/ha of arable and permanent pasture. Significant costs arise from contamination of drinking water with pesticides (pound 120 m/year), nitrate (pound 16 m), Cryptosporidium (pound 23 m) and phosphate and soil (pound 55 m), from damage to wildlife, habitats, hedgerows and drystone walls (pound 125 m), from emissions of gases (pound 1113 m), from soil erosion and organic carbon losses (pound 106 m), from food poisoning (pound 169 m), and from bovine spongiform encephalopathy (BSE) (pound 607 m). This study has only estimated those externalities that give rise to financial costs, and so is likely to underestimate the total negative impacts of modern agriculture. These data help to identify policy priorities, particularly over the most efficient way to internalise these external costs into prices. This would imply a redirection of public subsidies towards encouraging those positive externalities under-provided in the market place, combined with a mix of advisory and institutional mechanisms, regulatory and legal measures, and economic instruments to correct negative externalities. Further work examining the marginal costs and benefits of UK agriculture would help to inform future policy development. (C) 2000 Elsevier Science Ltd. All rights reserved. | G155: 10.1016/S0308-521X(00)00031-7 | H155: http://dx.doi.org/10.1016/S0308-521X(00)00031-7 | I155: Agriculture, Multidisciplinary | J155: 45982 | K155: WOS:000089669800003 | L155: View Full Record in Web of Science
A156: J | B156: Lemly, AD; Kingsford, RT; Thompson, JR | C156: Irrigated agriculture and wildlife conservation: Conflict on a global scale | D156: ENVIRONMENTAL MANAGEMENT | E156: Review | F156: The demand for water to support irrigated agriculture has led to the demise of wetlands and their associated wildlife for decades. This thirst for water is so pervasive that many wetlands considered to be hemispheric reserves for waterbirds have been heavily affected; for example, the California and Nevada wetlands in North America, the Macquarie Marshes in Australia, and the Aral Sea in central Asia. These and other major wetlands have lost most of their historic supplies of water and some have also experienced serious impacts from contaminated subsurface irrigation drainage. Now mere shadows of what they once were in terms of biodiversity and wildlife production, many of the so-called wetlands of international importance are no longer the key conservation strongholds they were in the past. The conflict between irrigated agriculture and wildlife conservation has reached a critical point on a global scale. Not only has local wildlife suffered, including the extinction of highly insular species, but a ripple effect has impacted migratory birds worldwide. Human societies reliant on wetlands for their livelihoods are also bearing the cost. Ironically, most of the degradation of these key wetlands occurred during a period of time when public environmental awareness and scientific assertion of the need for wildlife conservation was at an all-time high. However, designation of certain wetlands as reserves for wildlife by international review boards has not slowed their continued degradation. To reverse this trend, land and water managers and policy makers must assess the true economic costs of wetland loss and, depending on the outcome of the assessment. use the information as a basis for establishing legally enforceable water rights that protect wetlands from agricultural development. | G156: 10.1007/s002679910039 | H156: http://dx.doi.org/10.1007/s002679910039 | I156: Environmental Sciences | J156: 45982 | K156: WOS:000086118000003 | L156: View Full Record in Web of Science
A157: J | B157: Stoddard, JL; Jeffries, DS; Lükewille, A; Clair, TA; Dillon, PJ; Driscoll, CT; Forsius, M; Johannessen, M; Kahl, JS; Kellogg, JH; Kemp, A; Mannio, J; Monteith, DT; Murdoch, PS; Patrick, S; Rebsdorf, A; Skjelkvåle, BL; Stainton, MP; Traaen, T; van Dam, H; Webster, KE; Wieting, J; Wilander, A | C157: Regional trends in aquatic recovery from acidification in North America and Europe | D157: NATURE | E157: Article | F157: Rates of acidic deposition from the atmosphere ('acid rain') have decreased throughout the 1980s and 1990s across large portions of North America and Europe(1,2). Many recent studies have attributed observed reversals in surface-water acidification at national(3) and regional(4) scales to the declining deposition. To test whether emissions regulations have led to widespread recovery in surface-water chemistry, we analysed regional trends between 1980 and 1995 in indicators of acidification (sulphate, nitrate and base-cation concentrations, and measured (Gran) alkalinity) for 205 lakes and streams in eight regions of North America and Europe. Dramatic differences in trend direction and strength for the two decades are apparent. In concordance with general temporal trends in acidic deposition, lake and stream sulphate concentrations decreased in all regions with the exception of Great Britain; all but one of these regions exhibited stronger downward trends in the 1990s than in the 1980s. In contrast, regional declines in lake and stream nitrate concentrations were rare and, when detected, were very small. Recovery in alkalinity, expected wherever strong regional declines in sulphate concentrations have occurred, was observed in all regions of Europe, especially in the 1990s, but in only one region (of five) in North America. We attribute the lack of recovery in three regions (south/central Ontario, the Adirondack/Catskill mountains and midwestern North America) to strong regional declines in base-cation concentrations that exceed the decreases in sulphate concentrations. | G157: 10.1038/44114 | H157: http://dx.doi.org/10.1038/44114 | I157: Multidisciplinary Sciences | J157: 45982 | K157: WOS:000083054900046 | L157: View Full Record in Web of Science
A158: J | B158: Lambin, EF | C158: Monitoring forest degradation in tropical regions by remote sensing: some methodological issues | D158: GLOBAL ECOLOGY AND BIOGEOGRAPHY | E158: Article; Proceedings Paper | F158: Key issues related to the monitoring by remote sensing of open forest degradation in a tropical context are discussed. Degradation of forest-cover is often a complex process, with some degree of ecological reversibility and a strong interaction with climatic fluctuations. Only a representation of land cover as a continuous field of several biophysical variables can lead to an accurate detection of forest degradation. For this purpose, repetitive measurements of spectral, spatial and temporal indicators of the land surface have to be performed. Each set of indicators brings a specific type of information on the land cover. These indicators must therefore be combined to achieve a comprehensive description of the surface processes. The detection of inter-annual changes in landscape spatial structure is more likely to reveal long term and long lasting land-cover changes, while spectral indicators are more sensitive to fluctuations in primary productivity associated with climatic fluctuations. Different monitoring systems may be optimal for different ecosystems. A long: time series of observations is always required. The monitoring of the spatio-temporal distribution of biomass burning may also give indications of open forest degradation. | G158: 10.1046/j.1365-2699.1999.00123.x | H158: http://dx.doi.org/10.1046/j.1365-2699.1999.00123.x | I158: Ecology; Geography, Physical | J158: 45982 | K158: WOS:000084868000003 | L158: View Full Record in Web of Science
A159: J | B159: Likens, GE; Driscoll, CT; Buso, DC; Siccama, TG; Johnson, CE; Lovett, GM; Fahey, TJ; Reiners, WA; Ryan, DF; Martin, CW; Bailey, SW | C159: The biogeochemistry of calcium at Hubbard Brook | D159: BIOGEOCHEMISTRY | E159: Review | F159: A synthesis of the biogeochemistry of Ca was done during 1963-1992 in reference and human-manipulated forest ecosystems of the Hubbard Brook Experimental Forest (HBEF), NH. Results showed that there has been a marked decline in concentration and input of Ca in bulk precipitation, an overall decline in concentration and output of Ca in stream water, and marked depletion of Ca in soils of the HBEF since 1963. The decline in streamwater Ca was related strongly to a decline in SO(4),(2-)+NO(3),(-) in stream water during the period. The soil depletion of Ca was the result of leaching due to inputs of acid rain during the past 50 yr or so, to decreasing atmospheric inputs of Ca, and to changing amounts of net storage of Ca in biomass. As a result of the depletion of Ca, forest ecosystems at HBEF are much more sensitive to continuing inputs of strong acids in atmospheric deposition than expected based on long-term patterns of sulfur biogeochemistry. The Ca concentration and input in bulk precipitation ranged from a low of 1.0 mu mol/l and 15 mol/ha-yr in 1986-87 to a high of 8.0 mu mol/l and 77 mol/ha-yr in 1964-65, with a long-term mean of 2.74 mu mol/l during 1963-92. Average total atmospheric deposition was 61 and 29 mol/ha-yr in 1964-69 and 1987-92, respectively. Dry deposition is difficult to measure, but was estimated to be about 20% of total input in atmospheric deposition. Streamwater concentration reached a low of 21 mu mol/l in 1991-92 and a high of 41 mu mol/l in 1969-70, but outputs of Ca were lowest in 1964-65 (121 mol/ha-yr) and peaked in 1973-74 (475 mol/ha-yr). Gross outputs of Ca in stream water were positively and significantly related to streamflow, but the slope of this relation changed with time as Ca was depleted from the soil, and as the inputs of sulfate declined in both atmospheric deposition and stream water. Gross outputs of Ca in stream water consistently exceeded inputs in bulk precipitation. No seasonal pattern was observed for either bulk precipitation or stream water concentrations of Ca. Net soil release varied from 390 to 230 mol/ha-yr during 1964-69 and 1987-92, respectively. Of this amount, weathering release of Ca, based on plagioclase composition of the soil, was estimated at about 50 mol/ha-yr. Net biomass storage of Ca decreased from 202 to 54 mol/ha-yr, and throughfall plus streamflow decreased from 220 to 110 mol/ha-yr in 1964-69 and 1987-92, respectively. These ecosystem response patterns were related to acidification and to decreases in net biomass accretion during the study. Calcium return to soil by fine root turnover was about 270 mol/ha-yr, with 190 mol/ha-yr returning to the forest floor and 80 mol/ha-yr to the mineral soil. A lower content of Ca was observed with increasing elevation for most of the components of the watershed-ecosystems at HBEF. Possibly as a result, mortality of sugar maple increased significantly during 1982 to 1992 at high elevations of the HBEF. Interactions between biotic and abiotic control mechanisms were evident through elevational differences in soil cation exchange capacity (the exchangeable Ca concentration in soils was significantly and directly related to the organic matter content of the soils), in soil/till depth, and in soil water and in stream water concentrations at the HBEF, all of which tended to decrease with elevation. The exchangeable pool of Ca in the soil is about 6500 mol/ha, and its turnover time is quite rapid, about 3 yr. Nevertheless, the exchangeable pools of Ca at HBEF have been depleted markedly during the past 50 years or so, greater-than-21,125 mol/ha during 1940-1995. The annual gross uptake of trees is about 26-30% of the exchangeable pool in the soil. Some 7 to 8 times more Ca is cycled through trees than is lost in stream water each year, and resorption of Ca by trees is negligible at HBEF. Of the current inputs to the available nutrient compartment of the forest ecosystem, some 50% was provided by net soil release, 24% by leaching from the canopy, 20% by root exudates and 6% by atmospheric deposition. Clear cutting released large amounts of Ca to stream water, primarily because increased nitrification in the soil generated increased acidity and NO;, a mobile anion in drainage water; even larger amounts of Ca can be lost from the ecosystem in harvested timber products. The magnitude of Ca loss due to whole-tree harvest and acid rain leaching is comparable for forests similar to the HBEF, but losses from harvest must be superimposed on losses due to acid rain. | G159: 10.1023/A:1005984620681 | H159: http://dx.doi.org/10.1023/A:1005984620681 | I159: Environmental Sciences; Geosciences, Multidisciplinary | J159: 45982 | K159: WOS:000072671100001 | L159: View Full Record in Web of Science
A160: J | B160: LAWRENCE, GB; FULLER, RD; DRISCOLL, CT | C160: RELEASE OF ALUMINUM FOLLOWING WHOLE-TREE HARVESTING AT THE HUBBARD-BROOK-EXPERIMENTAL-FOREST, NEW-HAMPSHIRE | D160: JOURNAL OF ENVIRONMENTAL QUALITY | E160: Article | F160: From fall, 1983, through spring, 1984, an experimental watershed at the Hubbard Brook Experimental Forest in New Hampshire was commercially whole-tree harvested. Stream chemistry was monitored along an elevational gradient for approximately 1 yr prior to and 2 yr following the treatment in both the experimental watershed and an adjacent reference watershed. Whole-tree harvesting initially resulted in a large increase in stream NO3- and basic cation (Ca2+, Mg2+, Na+, and K+) concentrations and a decrease in stream sulfate concentrations. A decrease in pH and increase in Al concentrations followed. Elevational trends in stream chemistry were qualitatively similar before and after the cut, although the absolute concentrations of solutes changed markedly. These responses are explained by increased soil nitrification coupled with decreased vegetative uptake following the whole-tree harvest. Acidity generated by nitrification facilitated the mobilization of basic cations and increased anion adsorption. When NO3- production exceeded the release of basic cations, stream pH declined and Al concentrations increased. Aluminum was released in an entirely inorganic form resulting in potentially toxic concentrations in streamwater. | G160: 10.2134/jeq1987.00472425001600040016x | H160: http://dx.doi.org/10.2134/jeq1987.00472425001600040016x | I160: Environmental Sciences | J160: 45982 | K160: WOS:A1987K900200016 | L160: View Full Record in Web of Science

Sheet Raw Data - IPBES GA (#1645)
A1: Key | B1: Item Type | C1: Publication Year | D1: Author | E1: Title | F1: Publication Title | G1: ISBN | H1: ISSN | I1: DOI | J1: Url | K1: Abstract Note | L1: Date | M1: Date Added | N1: Date Modified | O1: Access Date | P1: Pages | Q1: Num Pages | R1: Issue | S1: Volume | T1: Number Of Volumes | U1: Journal Abbreviation | V1: Short Title | W1: Series | X1: Series Number | Y1: Series Text | Z1: Series Title | AA1: Publisher | AB1: Place | AC1: Language | AD1: Rights | AE1: Type | AF1: Archive | AG1: Archive Location | AH1: Library Catalog | AI1: Call Number | AJ1: Extra | AK1: Notes | AL1: File Attachments | AM1: Link Attachments | AN1: Manual Tags | AO1: Automatic Tags | AP1: Editor | AQ1: Series Editor | AR1: Translator | AS1: Contributor | AT1: Attorney Agent | AU1: Book Author | AV1: Cast Member | AW1: Commenter | AX1: Composer | AY1: Cosponsor | AZ1: Counsel | BA1: Interviewer | BB1: Producer | BC1: Recipient | BD1: Reviewed Author | BE1: Scriptwriter | BF1: Words By | BG1: Guest | BH1: Number | BI1: Edition | BJ1: Running Time | BK1: Scale | BL1: Medium | BM1: Artwork Size | BN1: Filing Date | BO1: Application Number | BP1: Assignee | BQ1: Issuing Authority | BR1: Country | BS1: Meeting Name | BT1: Conference Name | BU1: Court | BV1: References | BW1: Reporter | BX1: Legal Status | BY1: Priority Numbers | BZ1: Programming Language | CA1: Version | CB1: System | CC1: Code | CD1: Code Number | CE1: Section | CF1: Session | CG1: Committee | CH1: History | CI1: Legislative Body
A2: 39FKJ7Q5 | B2: journalArticle | C2: 2009 | D2: Barnes, David K. A.; Galgani, Francois; Thompson, Richard C.; Barlaz, Morton | E2: Accumulation and fragmentation of plastic debris in global environments | F2: Philosophical Transactions of the Royal Society B: Biological Sciences | I2: 10.1098/rstb.2008.0205 | L2: 2009 | M2: 2022-09-23 09:13:22 | N2: 2022-09-23T09:13:22Z | P2: 1985-1998 | R2: 1526 | S2: 364 | AN2: ipbes-global_chapter2.1_drivers
A3: RXPTGNSA | B3: journalArticle | C3: 2015 | D3: Barlow, Becky; Filyaw, Tanner; Workman, Sarah W. | E3: Non-timber forest products and forest stewardship plans | F3: USDA National Agroforestry Center Technical Note. AF Note–48, Forest Farming# 9. | L3: 2015 | M3: 2022-09-23 09:11:32 | N3: 2022-09-23T09:11:32Z | P3: 1-8 | S3: 2015 | AN3: ipbes-global_chapter2.1_drivers
A4: DAYL5CSF | B4: journalArticle | C4: 2002 | D4: Barnes, David K. A. | E4: Invasions by marine life on plastic debris | F4: Nature | H4: 0028-0836 | I4: 10.1038/416808a | J4: http://www.nature.com/articles/416808a | K4: Colonization by alien species poses one of the greatest threats to global biodiversity1. Here I investigate the colonization by marine organisms of drift debris deposited on the shores of 30 remote islands from the Arctic to the Antarctic (across all oceans) and find that human litter more than doubles the rafting opportunities for biota, particularly at high latitudes. Although the poles may be protected from invasion by freezing sea surface temperatures, these may be under threat as the fastest-warming areas anywhere2 are at these latitudes. | L4: 2002-04 | M4: 2022-09-21 12:15:33 | N4: 2022-09-21T12:15:33Z | P4: 808-809 | R4: 6883 | S4: 416 | AN4: ipbes-global_chapter2.1_drivers
A5: HWCDL2FE | B5: journalArticle | C5: 2005 | D5: Barnnhardt, Ray; Kawagley, Angayuqaq Oscar | E5: Indigenous Knowledge Systems and Alaska Native Ways of Knowing | F5: Anthropology Education Quarterly | I5: 10.1525/aeq.2005.36.1.008 | K5: Drawing on experiences across Fourth World contexts, with an emphasis on the Alaska context, this article seeks to extend our understandings of the learning processes within and at the intersection of diverse worldviews and knowledge systems. We outline the rationalefor a comprehensive program of educational initiatives closely articulated with the emergence of a new generation of Indigenous scholars who seek to move the role of Indigenous knowledge and learning from the margins to the center of educational research, thereby confronting some of the most intractable and salient educational issues of our times. [Indigenous knowledge, Indigenous epistemologies, Alaska Native education, Native science] A few years ago, a group of Alaska Native elders and educators were assembled to identify ways to more effectively utilize traditional knowledge systems and ways of knowing embedded in Native communities as a means of enriching the school curriculum and enlivening learning experiences of students. After two days of lengthy discussions on Indigenous worldviews, Native ways of knowing, cultural and intellectual property rights, and traditional ecological knowledge, an Inupiaq elder stood up and explained through an interpreter that he was going to describe how he and his brother were taught to hunt caribou by their father before guns were commonplace in the upper Kobuk River area of northern Alaska. The elder described how his father had been a highly respected hunter who always brought food home when he went out on hunting trips and shared it with others in the village. One day, at the time when he and his brother were coming of age, their father told them to prepare to go with him to check out a herd of caribou migrating through a valley a few miles distant. The brothers eagerly assembled their clothing and equipment and joined their father for their first caribou hunt. When they reached a ridge overlooking the nearby valley, they could see a large herd grazing and moving slowly across a grassy plain below. The father told his | L5: 2005 | M5: 2022-09-21 12:15:33 | N5: 2022-09-21T12:15:33Z | AN5: ipbes-global_chapter2.1_drivers
A6: GILF84AF | B6: book | C6: 1963 | D6: Barnett, Harold J.; Morse, Chandler | E6: Scarcity and Growth: The Economics of Natural Resource Availability | L6: 1963 | M6: 2022-09-21 12:15:33 | N6: 2022-09-21T12:15:33Z | AA6: Resources for the Future Press | AB6: New York; London | AN6: ipbes-global_chapter2.1_drivers
A7: FXH4WI8S | B7: book | C7: 2012 | D7: Barma, Naazneen; Kaiser, Kai; Le, Tuan Minh | E7: Rents to riches?: The political economy of natural resource-led development | L7: 2012 | M7: 2022-09-21 12:15:33 | N7: 2022-09-21T12:15:33Z | AA7: World Bank Publications | AN7: ipbes-global_chapter2.1_drivers
A8: GB2535EK | B8: journalArticle | C8: 2001 | D8: Barrett, Scott | E8: International cooperation for sale | F8: European Economic Review | H8: 00142921 | I8: 10.1016/S0014-2921(01)00082-4 | K8: This paper shows that strong asymmetry among countries warrants a change in the rules of the game of global public goods provision, with the consequence that cooperation by some countries is bought by others and aggregate welfare is increased, perhaps substantially. Side payments on their own have virtually no effect on the outcomes that can be sustained by self-enforcing cooperative agreements. But when the rules of the game are changed by strong asymmetry - when some countries are effectively 'committed' to being non-signatories to an agreement eschewing money transfers - side payments become the vehicle for increasing participation in a cooperative agreement. © 2001 Elsevier Science B.V. All rights reserved. | L8: 2001 | M8: 2022-09-21 12:15:33 | N8: 2022-09-21T12:15:33Z | AN8: ipbes-global_chapter2.1_drivers
A9: 9RKAG2MQ | B9: book | C9: 2018 | D9: Barlow, Jos; França, Filipe; Gardner, Toby A.; Hicks, Christina C.; Lennox, Gareth D.; Berenguer, Erika; Castello, Leandro; Economo, Evan P.; Ferreira, Joice; Guénard, Benoit; Gontijo Leal, Cecília; Isaac, Victoria; Lees, Alexander C.; Parr, Catherine L.; Wilson, Shaun K.; Young, Paul J.; Graham, Nicholas A. J. | E9: The future of hyperdiverse tropical ecosystems | G9: 4158601803011 | K9: The tropics contain the overwhelming majority of Earth's biodiversity: their terrestrial, freshwater and marine ecosystems hold more than three-quarters of all species, including almost all shallow-water corals and over 90% of terrestrial birds. However, tropical ecosystems are also subject to pervasive and interacting stressors, such as deforestation, overfishing and climate change, and they are set within a socio-economic context that includes growing pressure from an increasingly globalized world, larger and more affluent tropical populations, and weak governance and response capacities. Concerted local, national and international actions are urgently required to prevent a collapse of tropical biodiversity. | L9: 2018 | M9: 2022-09-21 12:15:33 | N9: 2022-09-21T12:15:33Z | Q9: 517–526 | S9: 559 | X9: 7715 | AA9: Nature Publishing Group | AN9: ipbes-global_chapter2.1_drivers
A10: 834W9B5B | B10: journalArticle | C10: 2013 | D10: Barrett, Scott | E10: Climate treaties and approaching catastrophes | F10: Journal of Environmental Economics and Management | H10: 00950696 | I10: 10.1016/j.jeem.2012.12.004 | K10: If the threshold that triggers climate catastrophe is known with certainty, and the benefits of avoiding catastrophe are high relative to the costs, treaties can easily coordinate countries' behavior so as to avoid the threshold. Where the net benefits of avoiding catastrophe are lower, treaties typically fail to help countries cooperate to avoid catastrophe, sustaining only modest cuts in emissions. These results are unaffected by uncertainty about the impact of catastrophe. By contrast, uncertainty about the catastrophic threshold normally causes coordination to collapse. Whether the probability density function has "thin" or "fat" tails makes little difference. © 2012 Elsevier Inc. | L10: 2013 | M10: 2022-09-21 12:15:33 | N10: 2022-09-21T12:15:33Z | AN10: ipbes-global_chapter2.1_drivers
A11: 5R9ETKR8 | B11: book | C11: 1999 | D11: Barrett, Scott | E11: A Theory of Full International Cooperation | G11: 0951-6298 | K11: This paper develops a coherent theory of international cooperation relying on the twin assumptions of individual and collective rationality. Using a linear version of the N-player prisoner?s dilemma game, I provide a formal proof of Olson?s conjecture that only a ?small? number of countries can sustain full cooperation by means of a self-enforcing agreement. Moreover, I find that this number is not fixed but depends on the nature of the cooperation problem; for some problems, three countries will be ?too many?, while for others even 200 countries will be a ?small? number. In addition, I find that the international system is only able to sustain global cooperation ? that is, cooperation involving 200 or so countries ? by a self-enforcing treaty when the gains to cooperation are ?small?. Finally, I find that the ability of the international system to sustain cooperation does not hinge on whether the compliance norm of customary international law has been internalized by states or whether compliance must instead be enforced by the use of treaty-based sanctions. The constraint on international cooperation is freerider deterrence, not compliance enforcement. KEY WORDS ? compliance ? free-riding ? game theory ? international cooperation ? renegotiation-proofness | L11: 1999 | M11: 2022-09-21 12:15:33 | N11: 2022-09-21T12:15:33Z | AN11: ipbes-global_chapter2.1_drivers
A12: WJGHBHKP | B12: journalArticle | C12: 2009 | D12: Cudney-Bueno, Richard; Basurto, Xavier | E12: Lack of cross-scale linkages reduces robustness of community-based fisheries management | F12: PloS one | I12: 10.1371/journal.pone.0006253 | L12: 2009 | M12: 2022-09-23 09:11:52 | N12: 2022-09-23T09:11:52Z | P12: e6253 | R12: 7 | S12: 4 | AN12: ipbes-global_chapter2.1_drivers
A13: B4JV82R2 | B13: journalArticle | C13: 2010 | D13: Demaria, Federico | E13: Shipbreaking at Alang–Sosiya (India): an ecological distribution conflict | F13: Ecological economics | I13: 10.1016/j.ecolecon.2010.09.006 | L13: 2010 | M13: 2022-09-23 09:11:13 | N13: 2022-09-23T09:11:13Z | P13: 250-260 | R13: 2 | S13: 70 | AN13: ipbes-global_chapter2.1_drivers
A14: QSZAC2CI | B14: journalArticle | C14: 2008 | D14: DeWeerdt, Sarah | E14: War and the Environment | F14: World Watch Magazine | L14: 2008 | M14: 2022-09-23 09:10:19 | N14: 2022-09-23T09:10:19Z | P14: 14-21 | R14: 1 | S14: 21 | AN14: ipbes-global_chapter2.1_drivers
A15: 3GXQFQTH | B15: journalArticle | C15: 2010 | D15: DeFries, R.; Pandey, D. | E15: Urbanization, the energy ladder and forest transitions in India's emerging economy | F15: Land Use Policy | I15: 10.1016/j.landusepol.2009.07.003 | L15: 2010 | M15: 2022-09-23 09:10:15 | N15: 2022-09-23T09:10:15Z | P15: 130-138 | R15: 2 | S15: 27 | AN15: ipbes-global_chapter2.1_drivers
A16: IRW5ITHN | B16: journalArticle | C16: 2014 | D16: Davis, Lucas W. | E16: The economic cost of global fuel subsidies | F16: American Economic Review | I16: 10.1257/aer.104.5.581 | L16: 2014 | M16: 2022-09-23 09:09:10 | N16: 2022-09-23T09:09:10Z | P16: 581-585 | R16: 5 | S16: 104 | AN16: ipbes-global_chapter2.1_drivers
A17: EXGRCRCA | B17: journalArticle | C17: 2014 | D17: Deikumah, Justus P.; McAlpine, Clive A.; Maron, Martine | E17: Mining matrix effects on West African rainforest birds | F17: Biological Conservation | I17: 10.1016/j.biocon.2013.11.030 | L17: 2014 | M17: 2022-09-23 09:07:05 | N17: 2022-09-23T09:07:05Z | P17: 334-343 | S17: 169 | AN17: ipbes-global_chapter2.1_drivers
A18: HNCIV9FG | B18: journalArticle | C18: 2002 | D18: Curran, S. | E18: Migration, Social Capital, and the Environment: Considering Migrant Selectivity and Networks in Relation to Coastal Ecosystems | F18: Population And Development Review | L18: 2002 | M18: 2022-09-23 09:06:45 | N18: 2022-09-23T09:06:45Z | P18: 89-125 | S18: 28 | AN18: ipbes-global_chapter2.1_drivers
A19: T384BYLF | B19: journalArticle | C19: 2016 | D19: de Vries, Frans P.; Hanley, Nick | E19: Incentive-based policy design for pollution control and biodiversity conservation: a review | F19: Environmental and Resource Economics | I19: 10.1007/s10640-015-9996-8 | L19: 2016 | M19: 2022-09-23 09:05:49 | N19: 2022-09-23T09:05:49Z | P19: 687-702 | R19: 4 | S19: 63 | AN19: ipbes-global_chapter2.1_drivers
A20: YGJAR2EX | B20: journalArticle | C20: 2018 | D20: Curtis, Philip G.; Slay, Christy M.; Harris, Nancy L.; Tyukavina, Alexandra; Hansen, Matthew C. | E20: Classifying drivers of global forest loss | F20: Science | H20: 0036-8075 | I20: 10.1126/science.aau3445 | L20: 2018 | M20: 2022-09-23 09:03:33 | N20: 2022-09-23T09:03:33Z | P20: 1108-1111 | R20: 6407 | S20: 361 | AN20: ipbes-global_chapter2.1_drivers
A21: L2DIME2F | B21: journalArticle | C21: 2008 | D21: Daily, G. C.; Matson, P. A. | E21: Ecosystem services: from theory to implementation | F21: Proc Natl Acad Sci US A | I21: 10.1073/pnas.0804960105 | K21: 1: Proc Natl Acad Sci US A. 2008 Jul 15;105(28):9455-6. Epub 2008 Jul 9. Click here to read Links. : from theory to implementation. | L21: 2008 | M21: 2022-09-23 09:01:37 | N21: 2022-09-23T09:01:37Z | AN21: ipbes-global_chapter2.1_drivers
A22: 2R9GWLUT | B22: journalArticle | C22: 2014 | D22: Davidson, Nick C. | E22: How much wetland has the world lost? Long-term and recent trends in global wetland area | F22: Marine and Freshwater Research | H22: 1323-1650 | I22: 10.1071/MF14173 | J22: http://www.publish.csiro.au/?paper=MF14173 | K22: It has been frequently stated, but without provision of supporting evidence, that the world has lost 50% of its wetlands (or 50% since 1900 AD). This review of 189 reports of change in wetland area finds that the reported long-term loss of natural wetlands averages between 54–57% but loss may have been as high as 87% since 1700 AD. There has been a much (3.7 times) faster rate of wetland loss during the 20th and early 21st centuries, with a loss of 64–71% of wetlands since 1900 AD. Losses have been larger and faster for inland than coastal natural wetlands. Although the rate of wetland loss in Europe has slowed, and in North America has remained low since the 1980s, the rate has remained high in Asia, where large-scale and rapid conversion of coastal and inland natural wetlands is continuing. It is unclear whether the investment by national governments in the Ramsar Convention on Wetlands has influenced these rates of loss. There is a need to improve the knowledge of change in wetland areas worldwide, particularly for Africa, the Neotropics and Oceania, and to improve the consistency of data on change in wetland areas in published papers and reports. | L22: 2014 | M22: 2022-09-23 08:16:33 | N22: 2022-09-23T08:16:33Z | O22: 2022-09-19 21:15:51 | P22: 934 | R22: 10 | S22: 65 | U22: Mar. Freshwater Res. | V22: How much wetland has the world lost? | AC22: en | AH22: DOI.org (Crossref) | AN22: ipbes-global_chapter2.1_drivers; ipbes-global_chapter2.2_nature; ipbes-global_chapter3
A23: WVEZKCDS | B23: journalArticle | C23: 2008 | D23: Diaz, Robert J.; Rosenberg, Rutger | E23: Spreading Dead Zones and Consequences for Marine Ecosystems | F23: Science | H23: 0036-8075, 1095-9203 | I23: 10.1126/science.1156401 | J23: https://www.science.org/doi/10.1126/science.1156401 | K23: Dead zones in the coastal oceans have spread exponentially since the 1960s and have serious consequences for ecosystem functioning. The formation of dead zones has been exacerbated by the increase in primary production and consequent worldwide coastal eutrophication fueled by riverine runoff of fertilizers and the burning of fossil fuels. Enhanced primary production results in an accumulation of particulate organic matter, which encourages microbial activity and the consumption of dissolved oxygen in bottom waters. Dead zones have now been reported from more than 400 systems, affecting a total area of more than 245,000 square kilometers, and are probably a key stressor on marine ecosystems. | L23: 2008-08-15 | M23: 2022-09-23 07:52:24 | N23: 2022-09-23T07:52:24Z | O23: 2022-09-19 21:16:43 | P23: 926-929 | R23: 5891 | S23: 321 | U23: Science | AC23: en | AH23: DOI.org (Crossref) | AN23: ipbes-global_chapter2.1_drivers; ipbes-global_chapter3; ipbes-global_chapter4; ipbes-global_glossary
A24: TI5IMXX3 | B24: book | C24: 2013 | D24: Descola, Philippe | E24: Beyond nature and culture | G24: 978-0-226-21236-4 | K24: "Originally published as Philippe Descola, Par-delà nature et culture (Paris: Editions Gallimard, 2005) © Editions Gallimard, Paris, 2005"--Title page verso. "Successor to Claude Levi-Strauss at the College de France, Philippe Descola has become one of the most important anthropologists working today, and Beyond Nature and Culture has been a major influence in European intellectual life since its French publication in 2005. Here, finally, it is brought to English-language readers. At its heart is a question central to both anthropology and philosophy: what is the relationship between nature and culture? Culture - as a collective human making, of art, language, and so forth - is often seen as essentially different than nature, which is portrayed as a collective of the nonhuman world, of plants, animals, geology, and natural forces. Descola shows this essential difference to be, however, not only a specifically Western notion, but also a very recent one. Drawing on ethnographic examples from around the world and theoretical understandings from cognitive science, structural analysis, and phenomenology, he formulates a sophisticated new framework, the "four ontologies"--Animism, totemism, naturalism, and analogism - to account for all the ways we relate ourselves to nature. By thinking beyond nature and culture as a simple dichotomy, Descola offers nothing short of a fundamental reformulation by which anthropologists and philosophers can see the world afresh"--provided by publisher. Trompe-l'oeil nature. Configurations of continuity ; The wild and the domesticated ; The great divide -- The structures of experience. The schemas of practice ; Relations with the self and relations with others -- The dispositions of being. Animism restored ; Totemism as an ontology ; The certainties of naturalism ; The dizzying prospects of analogy ; Terms, relations, categories -- The ways of the world. The institution of collectives ; Metaphysics of morals -- An ecology of relations. Forms of attachment ; The traffic of souls ; Histories of structures -- Epilogue : the spectrum of possibilities. | L24: 2013 | M24: 2022-09-21 14:49:23 | N24: 2022-09-21T14:49:23Z | Q24: 488 | AA24: The University of Chicago Press | AB24: Chicago | AN24: ipbes-global_chapter1; ipbes-global_chapter2.1_drivers; ipbes-global_chapter2.2_nature; ipbes-global_chapter2.3_ncp; ipbes-global_chapter5
A25: MGR6IL5Z | B25: journalArticle | C25: 2002 | D25: Derraik, José G. B. | E25: The pollution of the marine environment by plastic debris: a review | F25: Marine Pollution Bulletin | H25: 02727714 | I25: 10.1016/j.ecss.2016.01.036 | J25: https://www.sciencedirect.com/science/article/pii/S0025326X02002205 http://www.ncbi.nlm.nih.gov/pubmed/12405208 | K25: The deleterious effects of plastic debris on the marine environment were reviewed by bringing together most of the literature published so far on the topic. A large number of marine species is known to be harmed and/or killed by plastic debris, which could jeopardize their survival, especially since many are already endangered by other forms of anthropogenic activities. Marine animals are mostly affected through entanglement in and ingestion of plastic litter. Other less known threats include the use of plastic debris by ‘‘invader” species and the absorption of polychlorinated biphenyls from ingested plastics. Less conspicuous forms, such as plastic pellets and ‘‘scrubbers” are also hazardous. To address the problem of plastic debris in the oceans is a difficult task, and a variety of approaches are urgently required. Some of the ways to mitigate the problem are discussed. | L25: 2002 | M25: 2022-09-21 12:15:33 | N25: 2022-09-21T12:15:33Z | P25: 842-852 | S25: 44 | AN25: ipbes-global_chapter2.1_drivers
A26: 6XWGEGKU | B26: journalArticle | C26: 2015 | D26: Dhiaulhaq, Ahmad; De Bruyn, Toon; Gritten, David | E26: The use and effectiveness of mediation in forest and land conflict transformation in Southeast Asia: Case studies from Cambodia, Indonesia and Thailand | F26: Environmental Science and Policy | H26: 18736416 | I26: 10.1016/j.envsci.2014.10.009 | J26: http://dx.doi.org/10.1016/j.envsci.2014.10.009 | K26: The abundance and intensity of forest and land conflicts in Southeast Asia highlights the importance of sound and robust strategies in transforming the conflicts. This study aims to increase the understanding of the role of mediation in transforming these conflicts, examine the effectiveness of mediation, gain insights into the challenges as well as opportunities to improve mediation practices. This was achieved by analyzing six mediation cases in Cambodia, Indonesia and Thailand. Various data acquisition methods were used including literature review, expert workshop, semi-structured interviews and focus group discussions. A conflict mediation analysis framework was also developed and applied. Our findings suggest that mediation has played an important role in facilitating the process of conflict transformation. It has facilitated the creation of a conducive environment for multi-stakeholder dialog, built trust among the conflict parties, as well as assisted problem solving processes, resulting in mutually agreed solutions, improved relationships, and commitment to long-term cooperation. The parties also felt that successful mediation has also contributed to the improved social, economic, and environmental conditions in the study sites. However, the study found that mediation is not a silver bullet and that mediation alone is not enough in dealing with the underlying causes of conflict, specifically the structural inequalities. Other challenges in the application of mediation have also been identified such as the capacity requirements, as well as the costs involved.In moving forward, the paper makes recommendations to promote mediation for conflict transformation at policy and institutional levels, and suggests how to promote mediation and raise awareness about the availability and effectiveness of mediation to conflicting parties and the general public. | L26: 2015 | M26: 2022-09-21 12:15:33 | N26: 2022-09-21T12:15:33Z | P26: 132-145 | S26: 45 | AN26: ipbes-global_chapter2.1_drivers
A27: UDEUVUYR | B27: journalArticle | C27: 2013 | D27: De Groot, Rudolf S.; Blignaut, James; Van Der Ploeg, Sander; Aronson, James; Elmqvist, Thomas; Farley, Joshua | E27: Benefits of Investing in Ecosystem Restoration | F27: Conservation Biology | H27: 15231739 | I27: 10.1111/cobi.12158 | K27: Measures aimed at conservation or restoration of ecosystems are often seen as net-cost projects by governments and businesses because they are based on incomplete and often faulty cost-benefit analyses. After screening over 200 studies, we examined the costs (94 studies) and benefits (225 studies) of ecosystem restoration projects that had sufficient reliable data in 9 different biomes ranging from coral reefs to tropical forests. Costs included capital investment and maintenance of the restoration project, and benefits were based on the monetary value of the total bundle of ecosystem services provided by the restored ecosystem. Assuming restoration is always imperfect and benefits attain only 75% of the maximum value of the reference systems over 20 years, we calculated the net present value at the social discount rates of 2% and 8%. We also conducted 2 threshold cum sensitivity analyses. Benefit-cost ratios ranged from about 0.05:1 (coral reefs and coastal systems, worst-case scenario) to as much as 35:1 (grasslands, best-case scenario). Our results provide only partial estimates of benefits at one point in time and reflect the lower limit of the welfare benefits of ecosystem restoration because both scarcity of and demand for ecosystem services is increasing and new benefits of natural ecosystems and biological diversity are being discovered. Nonetheless, when accounting for even the incomplete range of known benefits through the use of static estimates that fail to capture rising values, the majority of the restoration projects we analyzed provided net benefits and should be considered not only as profitable but also as high-yielding investments. Beneficios de Invertir en la Restauración de Ecosistemas. | L27: 2013 | M27: 2022-09-21 12:15:33 | N27: 2022-09-21T12:15:33Z | AN27: ipbes-global_chapter2.1_drivers
A28: FTW8FNE3 | B28: journalArticle | C28: 2010 | D28: DeFries, Ruth S.; Rudel, Thomas; Uriarte, Maria; Hansen, Matthew | E28: Deforestation driven by urban population growth and agricultural trade in the twenty-first century | F28: Nature Geoscience | H28: 17520894 | I28: 10.1038/ngeo756 | J28: http://dx.doi.org/10.1038/ngeo756 | K28: Nature Geoscience 3, 178 (2010). doi:10.1038/ngeo756 | L28: 2010 | M28: 2022-09-21 12:15:33 | N28: 2022-09-21T12:15:33Z | P28: 178-181 | R28: 3 | S28: 3 | AN28: ipbes-global_chapter2.1_drivers; ipbes-global_chapter2.2_nature; ipbes-global_chapter4; ipbes-global_chapter5
A29: LU26SX29 | B29: book | C29: 2003 | D29: Dankers, Cora; Liu, P. | E29: Environmental and Social Standards, Certification for cash crops | J29: http://www.fao.org/3/a-y5136e.pdf | L29: 2003 | M29: 2022-09-21 12:15:33 | N29: 2022-09-21T12:15:33Z | AA29: Food and Agriculture Organisation of the United Nations | AB29: Rome | AN29: ipbes-global_chapter2.1_drivers; ipbes-global_glossary
A30: 2PBJU2AT | B30: journalArticle | C30: 2017 | D30: Crouzeilles, Renato; Ferreira, Mariana S.; Chazdon, Robin L.; Lindenmayer, David B.; Sansevero, Jerônimo B. B.; Monteiro, Lara; Iribarrem, Alvaro; Latawiec, Agnieszka E.; Strassburg, Bernardo B. N. | E30: Ecological restoration success is higher for natural regeneration than for active restoration in tropical forests | F30: Science Advances | H30: 2375-2548 | I30: 10.1126/sciadv.1701345 | J30: http://advances.sciencemag.org/lookup/doi/10.1126/sciadv.1701345 | K30: Is active restoration the best approach to achieve ecological restoration success (the return to a reference condition, that is, old-growth forest) when compared to natural regeneration in tropical forests? Our meta-analysis of 133 studies demonstrated that natural regeneration surpasses active restoration in achieving tropical forest restoration success for all three biodiversity groups (plants, birds, and invertebrates) and five measures of vegetation structure (cover, density, litter, biomass, and height) tested. Restoration success for biodiversity and vegetation structure was 34 to 56% and 19 to 56% higher in natural regeneration than in active restoration systems, respectively, after controlling for key biotic and abiotic factors (forest cover, precipitation, time elapsed since restoration started, and past disturbance). Biodiversity responses were based primarily on ecological metrics of abundance and species richness (74%), both of which take far less time to achieve restoration success than similarity and composition. This finding challenges the widely held notion that natural forest regeneration has limited conservation value and that active restoration should be the default ecological restoration strategy. The proposition that active restoration achieves greater restoration success than natural regeneration may have arisen because previous comparisons lacked controls for biotic and abiotic factors; we also did not find any difference between active restoration and natural regeneration outcomes for vegetation structure when we did not control for these factors. Future policy priorities should align the identified patterns of biophysical and ecological conditions where each or both restoration approaches are more successful, cost-effective, and compatible with socioeconomic incentives for tropical forest restoration. | L30: 2017-11 | M30: 2022-09-21 12:15:33 | N30: 2022-09-21T12:15:33Z | P30: e1701345 | R30: 11 | S30: 3 | AN30: ipbes-global_chapter2.1_drivers; ipbes-global_chapter5
A31: D234LJVM | B31: report | C31: 2011 | D31: Deininger, Klaus; Byerlee, Derek; Lindsay, Jonathan; Norton, Andrew; Selod, Harris; Stickler, Mercedes | E31: Rising Global Interest in Farmland. Can It Yield Sustainable and Equitable Benefits? | J31: https://siteresources.worldbank.org/DEC/Resources/Rising-Global-Interest-in-Farmland.pdf | L31: 2011 | M31: 2022-09-21 12:15:33 | N31: 2022-09-21T12:15:33Z | AA31: The World Bank | AB31: Washington | AN31: ipbes-global_chapter2.1_drivers
A32: VM3AK3KK | B32: journalArticle | C32: 1999 | D32: Deacon, Robert T. | E32: Deforestation and Ownership: Evidence from Historical Accounts and Contemporary Data | F32: Land Economics | H32: 00237639 | I32: 10.2307/3147182 | J32: www.jstor.org/stable/3147182 | K32: [Historical accounts of forest cover changes over the last three millennia are compared to contemporaneous human history, to shed light on factors contributing to large scale changes in forest stocks. Insecure ownership, for example, during wartime and periods of unrest, tends to accompany deforestation, as does population growth, and as does declining agricultural yields. A simple model of forest stocks and agricultural yields that captures these relationships is formulated to guide empirical analysis. Estimates based on cross-country data support the proposition that agricultural yields tend to be low and deforestation rates rapid where ownership is inscure.] | L32: 1999 | M32: 2022-09-21 12:15:33 | N32: 2022-09-21T12:15:33Z | P32: 341-359 | R32: 3 | S32: 75 | AF32: JSTOR | AN32: ipbes-global_chapter2.1_drivers
A33: 8KGJZBP6 | B33: journalArticle | C33: 2017 | D33: Da-Rocha, José-María; Sempere, Jaume | E33: ITQs, Firm Dynamics and Wealth Distribution: Does Full Tradability Increase Inequality? | F33: Environmental and Resource Economics | H33: 0924-6460 | I33: 10.1007/s10640-016-0017-3 | J33: http://link.springer.com/10.1007/s10640-016-0017-3 | K33: Concerns over the re-distributive e ects of individual transferable quotas (ITQ's) have led to restrictions on their tradability. We consider a general equilibrium model with rm dynamics to evaluate the redistributive impact of changing the tradability of ITQs. A change in tradability would happen, for example, if permits are allowed to be traded as a separate asset from ownership of an active rm. If the property right is associated with ownership of an active rm, the permit can be leased in each period but it is not possible to exit the industry and keep the right. However, allowing the permits to be traded as a separate asset has two e ects. First, it leads to a greater concentration of production in the industry. Second, it directly converts a non-tradable asset into a tradable one, and this is equivalent to giving a lump sum transfer to all rms. The rst e ect implies a concentration in revenues, while the second implies a redistribution of wealth. We calibrate our model to match the observed increase in revenue inequality in the Northeast Multispecies (Ground sh) U.S. Fishery. We show that although observed revenue inequality {measured by the Gini coe cient{ increases by 12%, wealth inequality is reduced by 40%.}} | L33: 2017-10 | M33: 2022-09-21 12:15:33 | N33: 2022-09-21T12:15:33Z | P33: 249-273 | R33: 2 | S33: 68 | AN33: ipbes-global_chapter2.1_drivers
A34: QE45MIP3 | B34: report | C34: 2016 | D34: Davis, Lucas W. | E34: The Environmental Cost of Global Fuel Subsidies | J34: http://www.nber.org/papers/w22105 | K34: Despite increasing calls for reform many countries continue to provide subsidies for gasoline and diesel. This paper quantifies the external costs of global fuel subsidies using the latest available data and estimates from the World Bank and International Monetary Fund. Under preferred assumptions about supply and demand elasticities, current subsidies cause $44 billion in external costs annually. This includes $8 billion from carbon dioxide emissions, $7 billion from local pollutants, $12 billion from traffic congestion, and $17 billion from accidents. Government incentives for alternative fuel vehicles are unlikely to cost-effectively reduce these externalities as they do little to address traffic congestion or accidents, and only indirectly address carbon dioxide and local pollutants. | L34: 2016 | M34: 2022-09-21 12:15:33 | N34: 2022-09-21T12:15:33Z | AA34: National Bureau of Economic Research | AE34: Working Paper | AN34: ipbes-global_chapter2.1_drivers | BH34: 22105
A35: CN5HXV2A | B35: report | C35: 2017 | D35: Cronin, Julie Anne; Fullerton, Don; Sexton, Steven E. | E35: Vertical and horizontal redistributions from a carbon tax and rebate | L35: 2017 | M35: 2022-09-21 12:15:33 | N35: 2022-09-21T12:15:33Z | AA35: National Bureau of Economic Research | AN35: ipbes-global_chapter2.1_drivers
A36: JVPNUYJV | B36: journalArticle | C36: 2010 | D36: Crowder, Kyle; Downey, Liam | E36: Interneighborhood Migration, Race, and Environmental Hazards: Modeling Microlevel Processes of Environmental Inequality | F36: American Journal of Sociology | H36: 0002-9602 | I36: 10.1086/649576 | J36: http://www.journals.uchicago.edu/doi/10.1086/649576 | K36: This study combines longitudinal individual‐level data with neighborhood‐level industrial hazard data to examine the extent and sources of environmental inequality. Results indicate that profound racial and ethnic differences in proximity to industrial pollution persist when differences in individual education, household income, and other microlevel characteristics are controlled. Examination of underlying migration patterns further reveals that black and Latino householders move into neighborhoods with significantly higher hazard levels than do comparable whites and that racial differences in proximity to neighborhood pollution are maintained more by these disparate mobility destinations than by differential effects of pollution on the decision to move. | L36: 2010-01 | M36: 2022-09-21 12:15:33 | N36: 2022-09-21T12:15:33Z | P36: 1110-1149 | R36: 4 | S36: 115 | AN36: ipbes-global_chapter2.1_drivers
A37: 3V77XW5Z | B37: journalArticle | C37: 2007 | D37: Dasgupta, Aniruddha; Beard, Victoria A. | E37: Community Driven Development, Collective Action and Elite Capture in Indonesia | F37: Development and Change | H37: 0012-155X | I37: 10.1111/j.1467-7660.2007.00410.x | J37: https://doi.org/10.1111/j.1467-7660.2007.00410.x | K37: ABSTRACT In response to the well documented limitations of top-down, modernist and authoritarian approaches that have dominated development, practitioners and academics increasingly promote more community-based approaches. The World Bank uses the term ?community driven development? to describe projects that increase a community's control over the development process. In an analysis of a community driven poverty alleviation project in Indonesia, this article examines the vulnerability of such an approach to elite capture. The expected relationships among a community's capacity for collective action, elite control over project decisions and elite capture of project benefits were not found. In cases where the project was controlled by elites, benefits continued to be delivered to the poor, and where power was the most evenly distributed, resource allocation to the poor was restricted. Communities where both non-elites and elites participated in democratic self-governance, however, did demonstrate an ability to redress elite capture when it occurred. | L37: 2007-03-01 | M37: 2022-09-21 12:15:33 | N37: 2022-09-21T12:15:33Z | O37: 2019-11-06 00:00:00 | P37: 229-249 | R37: 2 | S37: 38 | U37: Development and Change | AN37: ipbes-global_chapter2.1_drivers
A38: QLM3JK9R | B38: journalArticle | C38: 2001 | D38: Cropper, Maureen; Puri, Jyotsna; Griffiths, Charles | E38: Predicting the Location of Deforestation : The Role of Roads and Protected Areas in North Thailand | F38: Land Economics | H38: 00237639 | I38: 10.3368/le.77.2.172 | K38: Abstract: Using plot level data, we estimate a bivariate probit model to explain land clearing and the siting of protected areas in North Thailand in 1986. The model suggests that protected areas (national parks and wildlife sanctuaries together) did not reduce the likelihood of forest clearing; however, wildlife sanctuaries may have reduced the probability of deforestation. Road building, by reducing impedance-weighted distance to market, has promoted clearing, especially near the forest fringe. We simulate the impact of further road building to show where road building is likely to have greatest impact and where it is likely to threaten protected areas. (JEL Q23, Q28, R40) | L38: 2001 | M38: 2022-09-21 12:15:33 | N38: 2022-09-21T12:15:33Z | P38: 172-186 | R38: 2 | S38: 77 | AN38: ipbes-global_chapter2.1_drivers
A39: P4XHMK4E | B39: journalArticle | C39: 2015 | D39: Dalin, Carole; Qiu, Huanguang; Hanasaki, Naota; Mauzerall, Denise L.; Rodriguez-Iturbe, Ignacio | E39: Balancing water resource conservation and food security in China | F39: Proceedings of the National Academy of Sciences | H39: 0027-8424 | I39: 10.1073/pnas.1504345112 | K39: China's economic growth is expected to continue into the next decades, accompanied by sustained urbanization and industrialization. The associated increase in demand for land, water resources, and rich foods will deepen the challenge of sustainably feeding the population and balancing agricultural and environmental policies. We combine a hydrologic model with an economic model to project China's future food trade patterns and embedded water resources by 2030 and to analyze the effects of targeted irrigation reductions on this system, notably on national agricultural water consumption and food self-sufficiency. We simulate interprovincial and international food trade with a general equilibrium welfare model and a linear programming optimization, and we obtain province-level estimates of commodities' virtual water content with a hydrologic model. We find that reducing irrigated land in regions highly dependent on scarce river flow and nonrenewable groundwater resources, such as Inner Mongolia and the greater Beijing area, can improve the efficiency of agriculture and trade regarding water resources. It can also avoid significant consumption of irrigation water across China (up to 14.8 km3/y, reduction by 14%), while incurring relatively small decreases in national food self-sufficiency (e.g., by 3% for wheat). Other researchers found that a national, rather than local, water policy would have similar effects on food production but would only reduce irrigation water consumption by 5%. | L39: 2015 | M39: 2022-09-21 12:15:33 | N39: 2022-09-21T12:15:33Z | AN39: ipbes-global_chapter2.1_drivers
A40: T9HCL2I8 | B40: journalArticle | C40: 2008 | D40: Curran, Sara R.; Cooke, Abigail M. | E40: Unexpected Outcomes of Thai Cassava Trade : A Case of Global Complexity and Local Unsustainability | F40: Globalizations | H40: 1474-7731 | I40: 10.1080/14747730802057449 | K40: Tracing the Thai cassava (Manihot esculenta) trade network, between 1960 and 2000, offers a compelling example of global complexity at work. The emergence of Thailand's dominance of world export markets caught the world by surprise. The opening up of a European market for cassava was supposed to be met by Brazilian and Indonesian producers. Instead, Thailand took over the market by 1975. Several factors facilitated this emergence including: entrepreneurial diasporic networks of Thai-Chinese traders, local political economy conditions in both Europe and Thailand, and ecological conditions in Thailand. These same factors also shaped the subsequent timing of the closing of the European market, the emergence of a new industry association, the creation of new cassava products, and the expansion to other markets. Furthermore, the dynamic nature of cassava market yielded equivocal outcomes for both Europe and Thai farmers. A Chinese version of this article's abstract is available online at: www.informaworld.com/rglo | L40: 2008 | M40: 2022-09-21 12:15:33 | N40: 2022-09-21T12:15:33Z | AN40: ipbes-global_chapter2.1_drivers
A41: FQ5TCWES | B41: journalArticle | C41: 2002 | D41: Dayton-Johnson, Jeff; Bardhan, Pranab | E41: Inequality and conservation on the local commons: A theoretical exercise | F41: Economic Journal | H41: 00130133 | I41: 10.1111/1468-0297.00731 | K41: To analyse the effect of asset inequality on co-operation within a group, we consider a two-player nonco-operative model of conservation of a common-pool resource. Overexploitation by one user affects another's payoff by reducing the next-period catch. We give necessary and sufficient conditions such that conservation is a Nash equilibrium, and show that increasing inequality does not, in general, favour full conservation. However, once inequality is sufficiently great, further inequality can raise efficiency. Thus, the relationship between inequality and economic efficiency is U-shaped. Finally, we analyse the implications for conservation if players have earning opportunities outside the commons. | L41: 2002 | M41: 2022-09-21 12:15:33 | N41: 2022-09-21T12:15:33Z | AN41: ipbes-global_chapter2.1_drivers
A42: HFJPDWG4 | B42: journalArticle | C42: 2017 | D42: Dawson, Wayne; Moser, Dietmar; van Kleunen, Mark; Kreft, Holger; Pergl, Jan; Pyšek, Petr; Weigelt, Patrick; Winter, Marten; Lenzner, Bernd; Blackburn, Tim M.; Dyer, Ellie E.; Cassey, Phillip; Scrivens, Sally L.; Economo, Evan P.; Guénard, Benoit; Capinha, César; Seebens, Hanno; García-Díaz, Pablo; Nentwig, Wolfgang; García-Berthou, Emili; Casal, Christine; Mandrak, Nicholas E.; Fuller, Pam; Meyer, Carsten; Essl, Franz | E42: Global hotspots and correlates of alien species richness across taxonomic groups | F42: Nature Ecology & Evolution | H42: 2397-334X | I42: 10.1038/s41559-017-0186 | K42: Human-mediated transport beyond biogeographic barriers has led to the introduction and establishment of alien species in new regions worldwide. However, we lack a global picture of established alien species richness for multiple taxonomic groups. Here, we assess global patterns and potential drivers of established alien species richness across eight taxonomic groups (amphibians, ants, birds, freshwater fishes, mammals, vascular plants, reptiles and spiders) for 186 islands and 423 mainland regions. Hotspots of established alien species richness are predominantly island and coastal mainland regions. Regions with greater gross domestic product per capita, human population density, and area have higher established alien richness, with strongest effects emerging for islands. Ants and reptiles, birds and mammals, and vascular plants and spiders form pairs of taxonomic groups with the highest spatial congruence in established alien richness, but drivers explaining richness differ between the taxa in each pair. Across all taxonomic groups, our results highlight the need to prioritize prevention of further alien species introductions to island and coastal mainland regions globally. | L42: 2017-06 | M42: 2022-09-21 12:15:33 | N42: 2022-09-21T12:15:33Z | P42: 0186 | R42: JUNE | S42: 1 | AN42: ipbes-global_chapter2.1_drivers
A43: RUIS5YQY | B43: journalArticle | C43: 2012 | D43: Datta, Saugato | E43: The impact of improved highways on Indian firms | F43: Journal of Development Economics | H43: 03043878 | I43: 10.1016/j.jdeveco.2011.08.005 | K43: India's Golden Quadrilateral Program, a major highway project, aimed at improving the quality and width of existing highways connecting the four largest cities in India. It affected the quality of highways available to firms in cities that lay along the routes of the four upgraded highways, while leaving the quality of highways available to firms in other cities unaffected. This feature of the project allows for a difference-in-difference estimation strategy, where status on and off the improved highways, and distance from them, are used as treatment variables. This strategy is implemented using data from the 2002 and 2005 rounds of the World Bank Enterprise Surveys for India. Firms in cities affected by the Golden Quadrilateral highway project reduced their average stock of input inventories by between 6 and 12days' worth of production. Firms in cities where road quality did not improve showed no significant changes. The reduction in stocks of input inventories also varied inversely with the distance between the city in which a firm was located and the nearest city on an improved highway. Firms on the Golden Quadrilateral were also more likely to have switched the supplier who provided them with their primary input, suggesting that they saw reason to re-optimize their choice of supplier after the arrival of better highways. Consistent with these findings, firms on the improved highways reported decreased transportation obstacles to production, while firms in control cities reported no such change. | L43: 2012 | M43: 2022-09-21 12:15:33 | N43: 2022-09-21T12:15:33Z | P43: 46-57 | R43: 1 | S43: 99 | AN43: ipbes-global_chapter2.1_drivers
A44: 4WEULRV2 | B44: journalArticle | C44: 2006 | D44: Darity, William A.; Mason, Patrick L.; Stewart, James B. | E44: The economics of identity: The origin and persistence of racial identity norms | F44: Journal of Economic Behavior and Organization | H44: 01672681 | I44: 10.1016/j.jebo.2004.09.005 | K44: This study uses evolutionary game theory to model the relationship between racial identity formation and inter-racial disparities in economic and non-economic outcomes. Starting with a fixed population of persons who are easily identified according to an exogenous criterion, for example, phenotype, we then allow individuals to pursue either a racialist or an individualist identity strategy in social interactions. The formation of identity norms imposes both positive and negative externalities on each person's identity actions. There are forces in the model that might push society toward racialism, individualism, or a mixed identity equilibrium, depending on matching assumptions, dynamic assumptions, parameter values, and initial conditions. ?? 2005. | L44: 2006 | M44: 2022-09-21 12:15:33 | N44: 2022-09-21T12:15:33Z | AN44: ipbes-global_chapter2.1_drivers
A45: WKX5F5ND | B45: journalArticle | C45: 1999 | D45: Daniels, Peter | E45: Economic gains from technology-intensive trade: an empirical assessment | F45: Camb. J. Econ. | H45: 14643545 | I45: 10.1093/cje/23.4.427 | K45: National investment in technological activity is commonly justified in terms of the positive impacts upon productivity, international competitiveness and related aspects of national economic performance. This premise has found a supportive theoretical framework in the new technology and growth models. Based on extended technology-gap models, this study examines cross-country empirical evidence on the relationship between technology-intensive trade performance (as a proxy for technological output) and per capita economic performance, utilising 1978 to 1992 data for around 45 nations. The results provide some support for a positive relationship between trade performance and economic returns. However, the weak and often inconsistent results suggest that the unconditional pursuit of technology-intensive trade improvements may not necessarily have the expected net benefits. Keywords:Technology, International trade, Economic welfare, Growth. | L45: 1999 | M45: 2022-09-21 12:15:33 | N45: 2022-09-21T12:15:33Z | AN45: ipbes-global_chapter2.1_drivers
A46: PNGC39KR | B46: journalArticle | C46: 2015 | D46: Damon, Maria; Zivin, Joshua Graff; Thirumurthy, Harsha | E46: Health shocks and natural resource management: Evidence from Western Kenya | F46: Journal of Environmental Economics and Management | H46: 10960449 | I46: 10.1016/j.jeem.2014.10.006 | K46: Poverty and altered planning horizons brought on by the HIV/AIDS epidemic can change individual discount rates, altering incentives to conserve natural resources. Using longitudinal household survey data from Western Kenya, we estimate the effects of health status on investments in soil quality, as indicated by households' agricultural land fallowing decisions. We first show that this effect is theoretically ambiguous: while health improvements lower discount rates and thus increase incentives to conserve natural resources, they also increase labor productivity and make it more likely that households can engage in labor-intensive resource extraction activities. We find that household size and composition are predictors of whether the effect of health improvements on discount rates dominates the productivity effect, or vice-versa. Since households with more and younger members are better able to reallocate labor to cope with productivity shocks, the discount rate effect dominates for these households and health improvements lead to greater levels of conservation. In smaller families with less substitutable labor, the productivity effect dominates and health improvements lead to greater environmental degradation. | L46: 2015 | M46: 2022-09-21 12:15:33 | N46: 2022-09-21T12:15:33Z | AN46: ipbes-global_chapter2.1_drivers
A47: BPEGJ9NI | B47: journalArticle | C47: 1999 | D47: Davis, J. A.; Froend, R. | E47: Loss and degradation of wetlands in southwestern Australia: Underlying causes, consequences and solutions | F47: Wetlands Ecology and Management | H47: 09234861 | I47: 10.1023/A:1008400404021 | K47: Many wetlands (estimated to be about 70%) have been lost in the coastal plain region of southwestern Australia since British settlement (in 1829), primarily as a result of infilling or drainage to create land for agricultural use or urban development. While further loss is almost universally acknowledged as undesirable, wetland degradation continues with little overt public recognition of the causes or consequences. Obvious and direct causes include nutrient enrichment, salinization, pollution with pesticides and heavy metals, the invasion of exotic flora and flora, loss of fringing vegetation and altered hydrological regimes occurring as a result of urbanization and agricultural practices. Underlying causes include a lack of understanding of wetland hydrology and ecology on behalf of both planning agencies and the private sector, and poor coordination of the many different agencies responsible for wet-land management. Public and political awareness of wetland values continues to increase, but sectoral organization and responsibilities for wetland management lag behind. Sufficient scientific information now exists for improved management, protection and restoration of wetlands in southwestern Australia. However, this improvement cannot occur without the necessary political will and corresponding sectoral responses needed to implement coordinated wetland management policies and actions. | L47: 1999 | M47: 2022-09-21 12:15:33 | N47: 2022-09-21T12:15:33Z | AN47: ipbes-global_chapter2.1_drivers
A48: HBK5IJKM | B48: journalArticle | C48: 2002 | D48: Dasgupta, Susmita; Laplante, Benoit; Wang, Hua; Wheeler, David | E48: Confronting the Environmental Kuznets Curve | L48: 2002 | M48: 2022-09-21 12:15:33 | N48: 2022-09-21T12:15:33Z | P48: 147-168 | R48: 1 | S48: 16 | AN48: ipbes-global_chapter2.1_drivers
A49: GVKJDHRY | B49: book | C49: 2016 | D49: DeClerck, F. A. J.; Jones, S. K.; Attwood, S.; Bossio, D.; Girvetz, E.; Chaplin-Kramer, B.; Enfors, E.; Fremier, A. K.; Gordon, L. J.; Kizito, F.; Lopez Noriega, I.; Matthews, N.; McCartney, M.; Meacham, M.; Noble, A.; Quintero, M.; Remans, Roseline; Soppe, Richard; Willemen, L.; Wood, S. L. R.; Zhang, W. | E49: Agricultural ecosystems and their services: the vanguard of sustainability? | G49: 1877-3435 | K49: Sustainable Development Goals offer an opportunity to improve human well-being while conserving natural resources. Ecosystem services highlight human well-being benefits ecosystems, including agricultural ecosystems, provides. Whereas agricultural systems produce the majority of our food, they drive significant environmental degradation. This tension between development and environmental conservation objectives is not an immutable outcome as agricultural systems are simultaneously dependents, and providers of ecosystem services. Recognizing this duality allows integration of environmental and development objectives and leverages agricultural ecosystem services for achieving sustainability targets. We propose a framework to operationalize ecosystem services and resilience-based interventions in agricultural landscapes and call for renewed efforts to apply resilience-based approaches to landscape management challenges and for refocusing ecosystem service research on human well-being outcomes. | L49: 2016 | M49: 2022-09-21 12:15:33 | N49: 2022-09-21T12:15:33Z | AN49: ipbes-global_chapter2.1_drivers
A50: QD6XISVR | B50: journalArticle | C50: 2018 | D50: Dell'Angelo, Jampel; Rulli, Maria Cristina; D'Odorico, Paolo | E50: The Global Water Grabbing Syndrome | F50: Ecological Economics | H50: 09218009 | I50: 10.1016/j.ecolecon.2017.06.033 | K50: Large-scale acquisitions of agricultural land in developing countries have been rapidly increasing in the last 10 years, contributing to a major agrarian transition from subsistence or small scale farming to large-scale commercial agriculture by agribusiness transnational corporations. Likely driven by recent food crises, new bioenergy policies, and financial speculations, this phenomenon has been often investigated from the economic development, human right, land tenure and food security perspectives, while its hydrologic implications have remained understudied. It has been suggested that a major driver of large-scale land acquisitions (LSLAs) is the quest for water resources that can be used (locally) to sustain agricultural production in the acquired land. The appropriation of water resources associated with LSLAs has often been termed ‘water grabbing', though to date a formal definition of such a normative and inherently pejorative term is missing. The intrinsic assumption is that the acquisition of water undergoes the same dynamics of unbalanced power relationships that underlie many LSLAs. Here we invoke hydrological theories of “green” and “blue” water flows to stress the extent to which water appropriations are inherently coupled to land acquisitions and specifically focus on blue water. We then propose a formal definition of blue water grabbing based both on biophysical conditions (water scarcity) and ethical implications (human right to food). Blue water grabs are appropriations of irrigation (i.e., blue) water in regions affected by undernourishment and where agricultural production is constrained by blue water availability. We use this framework to provide a global assessment of the likelihood that LSLAs entail blue water grabbing. | L50: 2018 | M50: 2022-09-21 12:15:33 | N50: 2022-09-21T12:15:33Z | P50: 276-285 | S50: 143 | AN50: ipbes-global_chapter2.1_drivers
A51: J36IMMXF | B51: bookSection | C51: 2014 | D51: Dell'Angelo, Jampel; McCord, Paul F.; Baldwin, Elizabeth; Cox, Michael E.; Gower, Drew; Caylor, Kelly; Evans, Tom P. | E51: Multilevel governance of irrigation systems and adaptation to climate change in Kenya | F51: The global water system in the Anthropocene | L51: 2014 | M51: 2022-09-21 12:15:33 | N51: 2022-09-21T12:15:33Z | P51: 323-341 | AA51: Springer | AN51: ipbes-global_chapter2.1_drivers
A52: M4LNT7W7 | B52: journalArticle | C52: 2013 | D52: DeFries, R.; Herold, M.; Verchot, L.; Macedo, M. N.; Shimabukuro, Y. | E52: Export-oriented deforestation in Mato Grosso: harbinger or exception for other tropical forests? | F52: Philosophical Transactions of the Royal Society B: Biological Sciences | H52: 0962-8436 | I52: 10.1098/rstb.2012.0173 | K52: The Brazilian state of Mato Grosso was a global deforestation hotspot in the early 2000s. Deforested land is used predominantly to produce meat for distal consumption either through cattle ranching or soya bean for livestock feed. Deforestation declined dramatically in the latter part of the decade through a combination of market forces, policies, enforcement and improved monitoring. This study assesses how representative the national-level drivers underlying Mato Grosso's export-oriented deforestation are in other tropical forest countries based on agricultural exports, commercial agriculture and urbanization. We also assess how pervasive the governance and technical monitoring capacity that enabled Mato Grosso's decline in deforestation is in other countries. We find that between 41 and 54 per cent of 2000-2005 deforestation in tropical forest countries (other than Brazil) occurred in countries with drivers similar to Brazil. Very few countries had national-level governance and capacity similar to Brazil. Results suggest that the ecological, hydrological and social consequences of land-use change for export-oriented agriculture as discussed in this Theme Issue were applicable in about one-third of all tropical forest countries in 2000-2005. However, the feasibility of replicating Mato Grosso's success with controlling deforestation is more limited. Production landscapes to support distal consumption similar to Mato Grosso are likely to become more prevalent and are unlikely to follow a land-use transition model with increasing forest cover. | L52: 2013 | M52: 2022-09-21 12:15:33 | N52: 2022-09-21T12:15:33Z | P52: 20120173-20120173 | R52: 1619 | S52: 368 | AN52: ipbes-global_chapter2.1_drivers
A53: 55GSL5XK | B53: manuscript | C53: 2014 | D53: De Stercke, S. | E53: Dynamics of Energy Systems: A Useful Perspective | K53: A long term study of the energy system from an output perspective shows its dynamics in terms of its basic driver: end-use. Long term energy system dynamics have traditionally been characterized using primary energy inputs. They therefore have a supply bias and do not show technological improvements in efficiency and productivity in the downstream components of the energy system, which historically have been both fundamental as well as dominant. How are the dynamics affected by taking an alternative view through an output lens? In this Interim Report, historical useful energy balances since 1900 for key countries and regions as well as the world are presented. The method for constructing them is documented. Rates of change, energy intensities, fuel shares, the sectoral breakup and the attribution according to end-use are compared between the primary, final and useful energy levels. The data show that useful energy measures paint a different picture: they reveal a sharper drop in carbon intensity and a better correlation with economic activity compared to traditional input-based measures based on primary energy inputs. An exergy layer is also added. This shows that there is a vast potential (in thermodynamic terms) to reduce primary energy use while providing the same useful exergy output. The data set is a foundation on which to build in developing new alternative measures of systems change and transitions that are closer to the ultimate output of energy systems: the provision of energy services. | L53: 2014 | M53: 2022-09-21 12:15:33 | N53: 2022-09-21T12:15:33Z | AB53: Laxenburg | AN53: ipbes-global_chapter2.1_drivers
A54: YVZNJRS4 | B54: journalArticle | C54: 2008 | D54: de Sherbinin, Alex; VanWey, Leah K.; McSweeney, Kendra; Aggarwal, Rimjhim; Barbieri, Alisson; Henry, Sabine; Hunter, Lori M.; Twine, Wayne; Walker, Robert | E54: Rural household demographics, livelihoods and the environment | F54: Global Environmental Change | H54: 09593780 | I54: 10.1016/j.gloenvcha.2007.05.005 | K54: This paper reviews and synthesizes findings from scholarly work on linkages among rural household demographics, livelihoods and the environment. Using the livelihood approach as an organizing framework, we examine evidence on the multiple pathways linking environmental variables and the following demographic variables: fertility, migration, morbidity and mortality, and lifecycles. Although the review draws on studies from the entire developing world, we find the majority of microlevel studies have been conducted in either marginal (mountainous or arid) or frontier environments, especially Amazonia. Though the linkages are mediated by many complex and often context-specific factors, there is strong evidence that dependence on natural resources intensifies when households lose human and social capital through adult morbidity and mortality, and qualified evidence for the influence of environmental factors on household decision-making regarding fertility and migration. Two decades of research on lifecycles and land cover change at the farm level have yielded a number of insights about how households make use of different land-use and natural resource management strategies at different stages. A thread running throughout the review is the importance of managing risk through livelihood diversification, ensuring future income security, and culture-specific norms regarding appropriate and desirable activities and demographic responses. Recommendations for future research are provided. ?? 2007 Elsevier Ltd. All rights reserved. | L54: 2008 | M54: 2022-09-21 12:15:33 | N54: 2022-09-21T12:15:33Z | AN54: ipbes-global_chapter2.1_drivers
A55: A7ZSBQXX | B55: journalArticle | C55: 2014 | D55: De Longueville, Florence; Hountondji, Yvon; Ozer, Pierre; Henry, Sabine | E55: The air quality in African rural environments. Preliminary implications for health: The case of respiratory disease in the northern Benin | F55: Water, Air, and Soil Pollution | H55: 15732932 | I55: 10.1007/s11270-014-2186-4 | K55: Recently, the World Health Organization's International Association for Research on Cancer classified outdoor air pollution as carcinogenic to humans and puts air pollution in the same category as tobacco smoke, UV radiation, and plutonium. The ambient air is polluted by emissions from motor vehicles, industrial processes, power generation, household combustion of solid fuel, and other sources. Dust storms lead to particulate levels that exceed internationally recommended levels, especially near the Sahara. However, this source of air pollution appears to be under-studied, particularly in the literature devoted to human health impacts in West Africa. More than 50% of the total dust emitted into the atmosphere comes from the Sahara. These aerosols contribute to increase the concentrations of particles smaller than 10 µm (PM10), which are breathable particles. This study is the first designed to assess the real impact of Saharan dust on air quality and respiratory health of children in a region of West Africa. Dust events having affected the Northern Benin during the dry seasons between 2003 and 2007 were determined. The analyzed health data are the monthly rates of acute lower respiratory infections (ALRI). Over the entire study period, 61 days of dust events were observed in the region. They recorded on average a daily PM10 concentration of 1017 µg m-3, more than 18 times higher than that calculated on all days without dust events. The study also highlighted a mean increase of 12.5% of ALRI rates during the months recording dust events. The use of daily health data should help to refine these initial results in the future. | L55: 2014 | M55: 2022-09-21 12:15:33 | N55: 2022-09-21T12:15:33Z | AN55: ipbes-global_chapter2.1_drivers
A56: 24FIZM9D | B56: bookSection | C56: 1997 | D56: Diamond, Jared | E56: Social Structure | F56: Guns, Germs and Steel: The Fates of Human Societies | K56: Almost all species of domesticated large mammals prove to be ones whose wild ancestors share three social characteristics: they live in herds; they maintain a well-developed dominance hierarchy among herd members; and the herds occupy overlapping home ranges rather than mutually exclusive territories...When the herd is on the move, its members maintain a stereotyped order: in the rear, the stallion; in the front, the top-ranking female, followed by her foals in order of age, with the youngest first; and behind her, the other mares in order of rank, each followed by her foals in order of age. In that way, many adults can coexist in the herd without constant fighting and with each other knowing its rank. | L56: 1997 | M56: 2022-09-21 12:15:33 | N56: 2022-09-21T12:15:33Z | AN56: ipbes-global_chapter2.1_drivers
A57: RKBMRUWE | B57: book | C57: 2013 | D57: Di Nunzio, Jack | E57: Conflict on the Nile: The future of transboundary water disputes over the world's longest river | K57: The impacts of the Nile on the politics of the North African region have been so significant that they threaten to spark an interstate conflict, which could potentially destabilise the whole area. The countries in the Basin depend heavily on the Nile, which is the only major renewable source of water in the area; consequently, it is essential to their food and water security. | L57: 2013 | M57: 2022-09-21 12:15:33 | N57: 2022-09-21T12:15:33Z | AA57: Future Directions International | AN57: ipbes-global_chapter2.1_drivers
A58: 3A5V9HVX | B58: journalArticle | C58: 2011 | D58: Deng, Xiangzheng; Huang, Jikun; Uchida, Emi; Rozelle, Scott; Gibson, John | E58: Pressure cookers or pressure valves: Do roads lead to deforestation in China? | F58: Journal of Environmental Economics and Management | H58: 00950696 | I58: 10.1016/j.jeem.2010.04.005 | L58: 2011 | M58: 2022-09-21 12:15:33 | N58: 2022-09-21T12:15:33Z | P58: 79-94 | R58: 1 | S58: 61 | AN58: ipbes-global_chapter2.1_drivers
A59: 6Y9AAZSF | B59: book | C59: 1985 | D59: Devall, Bill; Sessions, George | E59: Deep ecology | G59: 0-87905-247-3 | K59: "A Peregrine Smith book." | L59: 1985 | M59: 2022-09-21 12:15:33 | N59: 2022-09-21T12:15:33Z | Q59: 266 | AA59: Gibbs Smith | AN59: ipbes-global_chapter2.1_drivers
A60: MIFSHQGS | B60: journalArticle | C60: 2009 | D60: Dercon, Stefan; Gilligan, Daniel O.; Hoddinott, John; Woldehanna, Tassew | E60: The Impact of Agricultural Extension and Roads on Poverty and Consumption Growth in Fifteen Ethiopian Villages | F60: American Journal of Agricultural Economics | I60: 10.1111/j.1467-8276.2009.01325.x | L60: 2009 | M60: 2022-09-21 12:15:33 | N60: 2022-09-21T12:15:33Z | P60: 1007 | R60: 4 | S60: 91 | AN60: ipbes-global_chapter2.1_drivers
A61: AVLWAIML | B61: journalArticle | C61: 2010 | D61: Delmas, Magali; Blass, Vered Doctori | E61: Measuring corporate environmental performance: the trade-offs of sustainability ratings | F61: Business Strategy and the Environment | H61: 09644733 | I61: 10.1002/bse.676 | K61: Socially responsible investing (SRI) represents an investment process that refl ects environ-mental and social preferences. The fi nancial industry is in a unique position to move cor-porations towards corporate sustainability. However, there is often little transparency regarding the metrics used to evaluate corporate social and environmental performance and the trade-offs involved in the evaluation. In this paper we discuss the various trade-offs of sustainability screening methodologies. We show that the rating of companies varies signifi cantly according to whether the screening is based on toxic releases and regulatory compliance or on the quality of environmental policy and disclosure. We base our analysis on the evaluation of the performance of 15 fi rms in the chemical sector. The analysis indi-cates that fi rms that have the most advanced reporting and environmental management practices tend also to have higher levels of toxic releases and lower environmental compli-ance. We provide methodological recommendations to help stakeholders evaluate corpo-rate environmental performance. | L61: 2010-05 | M61: 2022-09-21 12:15:33 | N61: 2022-09-21T12:15:33Z | P61: 245-260 | R61: 4 | S61: 19 | AN61: ipbes-global_chapter2.1_drivers
A62: Z6L3MVBT | B62: journalArticle | C62: 1997 | D62: Agrawal, Arun; Yadama, Gautam | E62: How do local institutions mediate market and population pressures on resources? Forest Panchayats in Kumaon, India | F62: Development and change | I62: 10.1111/1467-7660.00050 | L62: 1997 | M62: 2022-09-23 09:12:09 | N62: 2022-09-23T09:12:09Z | P62: 435-465 | R62: 3 | S62: 28 | AN62: ipbes-global_chapter2.1_drivers
A63: K6ZKTFY3 | B63: journalArticle | C63: 2014 | D63: Agrawal, Arun | E63: Indigenous and Scientific Knowledge: Some Critical Comments | F63: Antropologi Indonesia; No 55 (1998): Jurnal Antropologi Indonesia | J63: http://journal.ui.ac.id/index.php/jai/article/view/3331/2618 %3C/div%3E | K63: Dalam artikel ini, penulis bertujuan untuk merangsang terjadinya debat tentang pengetahuan lokal ( indigenous knowledge ) bertitik tolak dari pendapatnya tentang adanya kontradiksi dan kelemahan-kelemahan konseptual dalam banyak tulisan tentang pengetahuan lokal. Pokok permasalahan yang dibahas dalam artikel ini terutama memfokus pada argumen penulis bahwa perbedaan antara pengetahuan lokal dan pengetahuan ilmiah atau Barat dapat menimbulkan masalah bagi mereka yang percaya atas makna penting dari pengetahuan lokal bagi pembangunan. Artikel ini mengkaji beberapa kontradiksi dan ironi yang terdapat dalam upaya memberikan penekanan pada makna penting pengetahuan lokal. Menurut penulis, pembedaan pengetahuan lokal dan pengetahuan Barat sebagai dua tipe pengetahuan merupakan hal yang tidak produktif dalam upaya melibatkan peranan pengetahuan lokal itu dalam pembangunan yang tangguh dan berkelanjutan. Penulis juga mengemukakan bahwa sebenarnya tidak ada sesuatu yang baru tentang retorika dan perwujudan pengetahuan lokal. Ia pun berpendapat bahwa strategi untuk menyusun arsip dan menyebarluaskan pengetahuan lokal itu juga bertentangan dengan konsep dasar dari pengetahuan lokal itu sendiri. Bagian akhir dari artikel ini secara tentantif menelusuri sejumlah kemungkinan dalam mencari jalan ke luar dari dilema ini. Di antaranya adalah melaksanakan preservasi pengetahuan lokal in situ . Upaya ini hanya akan berhasil bila penduduk setempat dapat memperoleh kontrol atas penggunaan lahan dan sumber-sumber daya alamnya. | L63: 2014 | M63: 2022-09-23 09:11:57 | N63: 2022-09-23T09:11:57Z | AN63: ipbes-global_chapter2.1_drivers
A64: BYIRWRCD | B64: journalArticle | C64: 2016 | D64: Agnew, Robert | E64: Race and youth crime: Why isn't the relationship stronger? | F64: Race and Justice | I64: 10.1177/2153368715597465 | L64: 2016 | M64: 2022-09-23 09:11:23 | N64: 2022-09-23T09:11:23Z | P64: 195-221 | R64: 3 | S64: 6 | AN64: ipbes-global_chapter2.1_drivers
A65: D464VL5D | B65: journalArticle | C65: 2001 | D65: Agrawal, Arun | E65: Common Property Institutions and Sustainable Governance of Resources | F65: World Development | H65: 0305750X | I65: 10.1016/S0305-750X(01)00063-8 | J65: https://linkinghub.elsevier.com/retrieve/pii/S0305750X01000638 | L65: 2001-10 | M65: 2022-09-23 06:27:59 | N65: 2022-09-23T06:27:59Z | O65: 2022-09-22 07:27:20 | P65: 1649-1672 | R65: 10 | S65: 29 | U65: World Development | AC65: en | AH65: DOI.org (Crossref) | AN65: ipbes-global_chapter2.1_drivers; ipbes-global_chapter6
A66: NKA6CW6T | B66: journalArticle | C66: 2009 | D66: Agnew, David J.; Pearce, John; Pramod, Ganapathiraju; Peatman, Tom; Watson, Reg; Beddington, John R.; Pitcher, Tony J. | E66: Estimating the Worldwide Extent of Illegal Fishing | F66: PLoS ONE | H66: 1932-6203 | I66: 10.1371/journal.pone.0004570 | J66: https://dx.plos.org/10.1371/journal.pone.0004570 | L66: 2009-02-25 | M66: 2022-09-23 06:27:55 | N66: 2022-09-23T06:27:55Z | O66: 2022-09-19 21:16:54 | P66: e4570 | R66: 2 | S66: 4 | U66: PLoS ONE | AC66: en | AH66: DOI.org (Crossref) | AN66: ipbes-global_chapter2.1_drivers; ipbes-global_chapter3 | AP66: Sandin, Stuart A.
A67: 4Y4P64FH | B67: journalArticle | C67: 2014 | D67: Agarwala, Matthew; Atkinson, Giles; Fry, Benjamin Palmer; Homewood, Katherine; Mourato, Susana; Rowcliffe, J. Marcus; Wallace, Graham; Milner-Gulland, E. J. | E67: Assessing the relationship between human well-being and ecosystem services: a review of frameworks | F67: Conservation and Society | H67: 0972-4923 | I67: 10.4103/0972-4923.155592 | J67: http://www.conservationandsociety.org/text.asp?2014/12/4/437/155592 | K67: Focusing on the most impoverished populations, we critically review and synthesise key themes from dominant frameworks for assessing the relationship between well-being and ecosystem services in developing countries. This requires a differentiated approach to conceptualising well-being that appropriately reflects the perspectives of the poorest-those most directly dependent on ecosystem services, and their vulnerability to external and policy-driven environmental change. The frameworks analysed draw upon environmental sciences, economics, psychology, sociology, and anthropology, and were selected on the basis of their demonstrated or potential ability to illustrate the relationship between environmental change and human well-being, as well as their prevalence in real world applications. Thus, the synthesis offered here is informed by the various theoretical, methodological, and hermeneutical contributions from each field to the notion of well-being. The review highlights several key dimensions that should be considered by those interested in understanding and assessing the impact of environmental change on the well-being of the world's poorest people: the importance of interdisciplinary consideration of well-being, the need for frameworks that integrate subjective and objective aspects of well-being, and the central importance of context and relational aspects of well-being. The review is of particular interest to those engaged in the post-2015 development agenda. | L67: 2014 | M67: 2022-09-21 12:15:33 | N67: 2022-09-21T12:15:33Z | P67: 437 | R67: 4 | S67: 12 | AN67: ipbes-global_chapter2.1_drivers
A68: ASRUW97B | B68: journalArticle | C68: 2010 | D68: Ahrends, A.; Burgess, N. D.; Milledge, S. A. H.; Bulling, M. T.; Fisher, B.; Smart, J. C. R.; Clarke, G. P.; Mhoro, B. E.; Lewis, S. L. | E68: Predictable waves of sequential forest degradation and biodiversity loss spreading from an African city | F68: Proceedings of the National Academy of Sciences | H68: 0027-8424 | I68: 10.1073/pnas.0914471107 | J68: http://www.ncbi.nlm.nih.gov/pubmed/20679200 http://www.pubmedcentral.nih.gov/articlerender.fcgi?artid=PMC2930481 http://www.pnas.org/cgi/doi/10.1073/pnas.0914471107 | K68: Tropical forest degradation emits carbon at a rate of approximately 0.5 Pgxy(-1), reduces biodiversity, and facilitates forest clearance. Understanding degradation drivers and patterns is therefore crucial to managing forests to mitigate climate change and reduce biodiversity loss. Putative patterns of degradation affecting forest stocks, carbon, and biodiversity have variously been described previously, but these have not been quantitatively assessed together or tested systematically. Economic theory predicts a systematic allocation of land to its highest use value in response to distance from centers of demand. We tested this theory to see if forest exploitation would expand through time and space as concentric waves, with each wave targeting lower value products. We used forest data along a transect from 10 to 220 km from Dar es Salaam (DES), Tanzania, collected at two points in time (1991 and 2005). Our predictions were confirmed: high-value logging expanded 9 kmxy(-1), and an inner wave of lower value charcoal production 2 kmxy(-1). This resource utilization is shown to reduce the public goods of carbon storage and species richness, which significantly increased with each kilometer from DES [carbon, 0.2 Mgxha(-1); 0.1 species per sample area (0.4 ha)]. Our study suggests that tropical forest degradation can be modeled and predicted, with its attendant loss of some public goods. In sub-Saharan Africa, an area experiencing the highest rate of urban migration worldwide, coupled with a high dependence on forest-based resources, predicting the spatiotemporal patterns of degradation can inform policies designed to extract resources without unsustainably reducing carbon storage and biodiversity. | L68: 2010-08 | M68: 2022-09-21 12:15:33 | N68: 2022-09-21T12:15:33Z | P68: 14556-14561 | R68: 33 | S68: 107 | AN68: ipbes-global_chapter2.1_drivers; ipbes-global_chapter5
A69: RB9AZVKL | B69: journalArticle | C69: 2005 | D69: Agrawal, Arun; Gupta, Krishna | E69: Decentralization and Participation: The Governance of Common Pool Resources in Nepal's Terai | F69: World Development | H69: 0305750X | I69: 10.1016/j.worlddev.2005.04.009 | K69: Decentralization has emerged as an important instrument of environmental and development policy in the last two decades. Presumed benefits of environmental policy decentralization depend in significant measure on broad participation in the programs that governments create to decentralize decision making related to resource management. This paper uses data from protected areas in Nepal's Terai to examine who participates in environmental decentralization programs. On the basis of our statistical analysis, we highlight the fact that the likelihood of participation in community-level user groups is greater for those who are economically and socially better-off. We also find that individuals who have greater access to and who visit government offices related to decentralization policies more often are also more likely to participate in user groups created by state officials. Finally, we find a negative correlation between education and levels of participation. Our study and analysis support the argument that for decentralization policies to be successful on equity issues, it is important to build institutional mechanisms that encourage poorer and more marginal households to access government officials, improve access to educational opportunities, and create incentives to promote more interactions between less powerful rural residents and government officials. | L69: 2005 | M69: 2022-09-21 12:15:33 | N69: 2022-09-21T12:15:33Z | P69: 1101-1114 | R69: 7 | S69: 33 | AN69: ipbes-global_chapter2.1_drivers
A70: TX2D4HE8 | B70: journalArticle | C70: 2009 | D70: Agarwal, Bina | E70: Gender and forest conservation: The impact of women's participation in community forest governance | F70: Ecological Economics | H70: 09218009 | I70: 10.1016/j.ecolecon.2009.04.025 | K70: Would enhancing women's presence in community institutions of forest governance improve resource conservation and regeneration? This paper focuses on this little addressed question. Based on the author's primary data on communities managing their local forests in parts of India and Nepal, it statistically assesses whether the gender composition of a local forest management group affects forest conservation outcomes, after controlling for other characteristics of the management group, aspects of institutional functioning, forest and population characteristics, and related factors. It is found that groups with a high proportion of women in their executive committee (EC)-the principal decision-making body-show significantly greater improvements in forest condition in both regions. Moreover, groups with all-women ECs in the Nepal sample have better forest regeneration and canopy growth than other groups, despite receiving much smaller and more degraded forests. Older EC members, especially older women, also make a particular difference, as does employing a guard. The beneficial impact of women's presence on conservation outcomes is attributable especially to women's contributions to improved forest protection and rule compliance. More opportunity for women to use their knowledge of plant species and methods of product extraction, as well as greater cooperation among women, are also likely contributory factors. ?? 2009 Elsevier B.V. All rights reserved. | L70: 2009 | M70: 2022-09-21 12:15:33 | N70: 2022-09-21T12:15:33Z | P70: 2785-2799 | R70: 11 | S70: 68 | AN70: ipbes-global_chapter2.1_drivers
