Workbook

Sheet Notes
B2: Ridley et al
B3: 10.1186/s13750-022-00279-7
B4: https://link.springer.com/article/10.1186/s13750-022-00279-7
B5: Raw - 1 | C5: Details of all 1069 records part of Ridley et al study
B6: Raw - 2 | C6: Result of data labelling done by authors for each document
B7: Enriched | C7: - Study_design - Column created based on author's "study_design" col; Adopt labels of Obs, Experimental, Review - realm - Based on ecoregoin column of author, create "realm" label which is essentially same. Only the col is renamed to be consistent with name and outputs are present in string list form.
B8: Curated - Labels | C8: Export of 933 WOS records and their labels of study design, realm, threat l1
B9: Ridely - Data Coding of Threats | C9: - Threats were classified according to the IUCN Red List threat classification scheme - Precision: L1 -> L3 (Lowest to highest) e.g. level 1 = Biological Resource Use & Level 2 = Hunting and Collecting Terrestrial Animals here threat precision is 2. - Precision studies below L2 & NOT "not captured by the IUCN criteria" coded as level 1 + unspecified - Precision = Other - threat satisfied the definition of threats used here but wasn’t covered by the IUCN classification This file filter: - Remove "unspec" coded rows - Remove "other" unspec rowsx - Remove cumulative precsion in serving lables

Sheet Raw - 1
A1: ArticleID | B1: Pub_Type | C1: Authors | D1: Year | E1: Title | F1: Pub_name | G1: Volume | H1: Issue | I1: Pages | J1: source | K1: "
A2: 23583 | B2: Journal Article | C2: Coll_etal | D2: 2015 | E2: 'Low-hanging fruit' for conservation of marine vertebrate species at risk in the Mediterranean Sea | F2: Global Ecology and Biogeography | G2: 24 | H2: 2 | I2: 226-239 | J2: PubDatabase
A3: 24558 | B3: Journal Article | C3: Lieske_etal | D3: 2020 | E3: “Seas of risk”: Assessing the threats to colonial-nesting seabirds in Eastern Canada | F3: Marine Policy | G3: 115 | H3: NA | I3: NA | J3: PubDatabase
A4: 25889 | B4: Journal Article | C4: Vasilakis_etal | D4: 2017 | E4: A balanced solution to the cumulative threat of industrialized wind farm development on cinereous vultures (Aegypius monachus) in south-eastern Europe | F4: PLoS ONE | G4: 12 | H4: 2 | I4: NA | J4: PubDatabase
A5: 25688 | B5: Journal Article | C5: Stoica_etal | D5: 2017 | E5: A case study in the Moldavian Central Plateau, Romania - habitat distribution, conservation status and human impact in a protected area | F5: Contributii Botanice | G5: 52 | H5: NA | I5: 119-131 | J5: PubDatabase
A6: 23785 | B6: Report | C6: Duran, M., Murillo, F. J., Serrano, A., Sayago-Gil, M., Parra, S., Diaz del, R., Sacau, M., Patrocinio, T. and Cristobo, J. | D6: 2008 | E6: A Case Study of available methodology for the identification of Vulnerable Ecosystems/Habitats in bottom deep-sea fisheries: Possibilities to apply this method in the NAFO Regulatory Area in order to select Marine Protected Areas | F6: NA | G6: NA | H6: NA | I6: NA | J6: PubDatabase
A7: 23461 | B7: Journal Article | C7: Caro_etal | D7: 2020 | E7: A case study of the coconut crab Birgus latro on Zanzibar highlights global threats and conservation solutions | F7: ORYX | G7: NA | H7: NA | I7: NA | J7: PubDatabase
A8: 25299 | B8: Journal Article | C8: Rasmussen_etal | D8: 2013 | E8: A catchment scale evaluation of multiple stressor effects in headwater streams | F8: Science of the Total Environment | G8: 442 | H8: NA | I8: 420-431 | J8: PubDatabase
A9: 24656 | B9: Journal Article | C9: Magness_etal | D9: 2011 | E9: A climate-change adaptation framework to reduce continental-scale vulnerability across conservation reserves | F9: Ecosphere | G9: 2 | H9: 10 | I9: 23 | J9: PubDatabase
A10: 23573 | B10: Journal Article | C10: Clay_etal | D10: 2019 | E10: A comprehensive large-scale assessment of fisheries bycatch risk to threatened seabird populations | F10: Journal of Applied Ecology | G10: 56 | H10: 8 | I10: 1882-1893 | J10: PubDatabase
A11: 23151 | B11: Journal Article | C11: Asner_etal | D11: 2009 | E11: A contemporary assessment of change in humid tropical forests | F11: Conservation Biology | G11: 23 | H11: 6 | I11: 1386-1395 | J11: PubDatabase
A12: 26057 | B12: Journal Article | C12: Wraith and Pickering | D12: 2019 | E12: A continental scale analysis of threats to orchids | F12: Biological Conservation | G12: 234 | H12: NA | I12: 42917 | J12: PubDatabase
A13: 25664 | B13: Journal Article | C13: Stafford_etal | D13: 2017 | E13: A Cross-Site Analysis of Neotropical Bird Hunting Profiles | F13: Tropical Conservation Science | G13: 10 | H13: NA | I13: NA | J13: PubDatabase
A14: 24696 | B14: Journal Article | C14: Marotta_etal | D14: 2011 | E14: A decision-support system in ICZM for protecting the ecosystems: Integration with the habitat directive | F14: Journal of Coastal Conservation | G14: 15 | H14: 3 | I14: 393-405 | J14: PubDatabase
A15: 25692 | B15: Journal Article | C15: Stortini_etal | D15: 2015 | E15: A decision-support tool to facilitate discussion of no-take boundaries for Marine Protected Areas during stakeholder consultation processes | F15: Journal for Nature Conservation | G15: 23 | H15: NA | I15: 45-52 | J15: PubDatabase
A16: 23868 | B16: Journal Article | C16: Fasola and Roesler | D16: 2018 | E16: A familiar face with a novel behavior raises challenges for conservation: American mink in arid Patagonia and a critically endangered bird | F16: Biological Conservation | G16: 218 | H16: NA | I16: 217-222 | J16: PubDatabase
A17: 25629 | B17: Journal Article | C17: Smolinski and Calkiewicz | D17: 2015 | E17: A fish-based index for assessing the ecological status of Polish transitional and coastal waters | F17: Marine Pollution Bulletin | G17: 101 | H17: 2 | I17: 497-506 | J17: PubDatabase
A18: 25026 | B18: Journal Article | C18: Ondei_etal | D18: 2019 | E18: A flexible tool to prioritize areas for conservation combining landscape units, measures of biodiversity, and threats | F18: Ecosphere | G18: 10 | H18: 9 | I18: NA | J18: PubDatabase
A19: 24868 | B19: Journal Article | C19: Morelli_etal | D19: 2020 | E19: A forecasting map of avian roadkill-risk in Europe: A tool to identify potential hotspots | F19: Biological Conservation | G19: 249 | H19: NA | I19: NA | J19: PubDatabase
A20: 24428 | B20: Journal Article | C20: Kostoski_etal | D20: 2010 | E20: A freshwater biodiversity hotspot under pressure - Assessing threats and identifying conservation needs for ancient Lake Ohrid | F20: Biogeosciences | G20: 7 | H20: 12 | I20: 3999-4015 | J20: PubDatabase
A21: 24242 | B21: Journal Article | C21: Howard_etal | D21: 2018 | E21: A freshwater conservation blueprint for California: Prioritizing watersheds for freshwater biodiversity | F21: Freshwater Science | G21: 37 | H21: 2 | I21: 417-431 | J21: PubDatabase
A22: 25381 | B22: Journal Article | C22: Robertson_etal | D22: 2004 | E22: A fuzzy classification technique for predicting species' distributions: Applications using invasive alien plants and indigenous insects | F22: Diversity and Distributions | G22: 10 | H22: 44717 | I22: 461-474 | J22: PubDatabase
A23: 25371 | B23: Journal Article | C23: Riolo | D23: 2006 | E23: A geographic information system for fisheries management in American Samoa | F23: Environmental Modelling and Software | G23: 21 | H23: 7 | I23: 1025-1041 | J23: PubDatabase
A24: 26032 | B24: Journal Article | C24: Winchell_etal | D24: 2012 | E24: A GIS-based approach to quantifying pesticide use site proximity to salmonid habitat | F24: ACS Symposium Series | G24: 1111 | H24: NA | I24: 183-196 | J24: PubDatabase
A25: 25078 | B25: Journal Article | C25: Pasqualini_etal | D25: 2011 | E25: A GIS-based multicriteria evaluation for aiding risk management Pinus pinaster Ait. Forests: A case study in Corsican island, western Mediterranean region | F25: Environmental Management | G25: 48 | H25: 1 | I25: 38-56 | J25: PubDatabase
A26: 23163 | B26: Journal Article | C26: Aubrecht_etal | D26: 2008 | E26: A global inventory of coral reef stressors based on satellite observed nighttime lights | F26: Geocarto International | G26: 23 | H26: 6 | I26: 467-479 | J26: PubDatabase
A27: 24125 | B27: Journal Article | C27: Halpern_etal | D27: 2008 | E27: A global map of human impact on marine ecosystems | F27: Science | G27: 319 | H27: 5865 | I27: 948-952 | J27: PubDatabase
A28: 24525 | B28: Journal Article | C28: Lewis_etal | D28: 2020 | E28: A Global Perspective on Firefly Extinction Threats | F28: BioScience | G28: 70 | H28: 2 | I28: 157-167 | J28: PubDatabase
A29: 24078 | B29: Journal Article | C29: Graham_etal | D29: 2016 | E29: A Global-Scale Evaluation of Primate Exposure and Vulnerability to Climate Change | F29: International Journal of Primatology | G29: 37 | H29: 2 | I29: 158-174 | J29: PubDatabase
A30: 25033 | B30: Journal Article | C30: Orgiazzi_etal | D30: 2016 | E30: A knowledge-based approach to estimating the magnitude and spatial patterns of potential threats to soil biodiversity | F30: Science of the Total Environment | G30: 545-546 | H30: NA | I30: 44136 | J30: PubDatabase
A31: 26042 | B31: Journal Article | C31: Winters_etal | D31: 2017 | E31: A low cost field-survey method for mapping seagrasses and their potential threats: an example from the northern Gulf of Aqaba, Red Sea | F31: Aquatic Conservation: Marine and Freshwater Ecosystems | G31: 27 | H31: 2 | I31: 324-339 | J31: PubDatabase
A32: 25158 | B32: Journal Article | C32: Pilcher_etal | D32: 2017 | E32: A low-cost solution for documenting distribution and abundance of endangered marine fauna and impacts from fisheries | F32: PLoS ONE | G32: 12 | H32: 12 | I32: NA | J32: PubDatabase
A33: 25529 | B33: Journal Article | C33: Selkoe_etal | D33: 2009 | E33: A map of human impacts to a "pristine" coral reef ecosystem, the Papah?naumoku?kea Marine National Monument | F33: Coral Reefs | G33: 28 | H33: 3 | I33: 635-650 | J33: PubDatabase
A34: 24659 | B34: Journal Article | C34: Magris_etal | D34: 2019 | E34: A modelling approach to assess the impact of land mining on marine biodiversity: Assessment in coastal catchments experiencing catastrophic events (SW Brazil) | F34: Science of the Total Environment | G34: 659 | H34: NA | I34: 828-840 | J34: PubDatabase
A35: 24777 | B35: Journal Article | C35: Menegon_etal | D35: 2018 | E35: A modelling framework for MSP-oriented cumulative effects assessment | F35: Ecological Indicators | G35: 91 | H35: NA | I35: 171-181 | J35: PubDatabase
A36: 23685 | B36: Journal Article | C36: De_etal | D36: 2020 | E36: A multiscale analysis of land use dynamics in the buffer zone of Rio Doce State Park, Minas Gerais, Brazil | F36: Journal of Environmental Planning and Management | G36: 63 | H36: 5 | I36: 935-957 | J36: PubDatabase
A37: 23086 | B37: Journal Article | C37: Alvarez-Romero_etal | D37: 2013 | E37: A novel approach to model exposure of coastal-marine ecosystems to riverine flood plumes based on remote sensing techniques | F37: Journal of Environmental Management | G37: 119 | H37: NA | I37: 194-207 | J37: PubDatabase
A38: 25234 | B38: Journal Article | C38: Pusparini_etal | D38: 2018 | E38: A pathway to recovery: The Critically Endangered Sumatran tiger Panthera tigris sumatrae in an 'in danger' UNESCO World Heritage Site | F38: ORYX | G38: 52 | H38: 1 | I38: 25-34 | J38: PubDatabase
A39: 24229 | B39: Journal Article | C39: Holon_etal | D39: 2018 | E39: A predictive model based on multiple coastal anthropogenic pressures explains the degradation status of a marine ecosystem: Implications for management and conservation | F39: Biological Conservation | G39: 222 | H39: NA | I39: 125-135 | J39: PubDatabase
A40: 24636 | B40: Journal Article | C40: Macdonald_etal | D40: 2013 | E40: A problem shared is a problem reduced: Seeking efficiency in the conservation of felids and primates | F40: Folia Primatologica | G40: 83 | H40: 44715 | I40: 171-215 | J40: PubDatabase
A41: 23631 | B41: Journal Article | C41: Cubero-Pardo_etal | D41: 2011 | E41: A proposal to define vulnerability of cetacean areas to human development: Variables and analysis procedures applied to the gulf of California | F41: Aquatic Conservation: Marine and Freshwater Ecosystems | G41: 21 | H41: 5 | I41: 433-447 | J41: PubDatabase
A42: 24745 | B42: Journal Article | C42: Mccullough_etal | D42: 2017 | E42: A range of possibilities: Assessing geographic variation in climate sensitivity of ponderosa pine using tree rings | F42: Forest Ecology and Management | G42: 402 | H42: NA | I42: 223-233 | J42: PubDatabase
A43: 23085 | B43: Journal Article | C43: Alvarez-Filip_etal | D43: 2019 | E43: A rapid spread of the stony coral tissue loss disease outbreak in the Mexican Caribbean | F43: PeerJ | G43: 2019 | H43: 11 | I43: NA | J43: PubDatabase
A44: 25891 | B44: Journal Article | C44: Vasyliuk_etal | D44: 2015 | E44: A review of major impact factors of hostilities influencing biodiversity in the Eastern Ukraine (Modeled On Selected Animal Species) | F44: Vestnik Zoologii | G44: 49 | H44: 2 | I44: 145-158 | J44: PubDatabase
A45: 23790 | B45: Journal Article | C45: Duvall and Barron | D45: 2000 | E45: A screening level probabilistic risk assessment of mercury in Florida Everglades food webs | F45: Ecotoxicology and Environmental Safety | G45: 47 | H45: 3 | I45: 298-305 | J45: PubDatabase
A46: 25808 | B46: Journal Article | C46: Treves_etal | D46: 2006 | E46: A simple, cost-effective method for involving stakeholders in spatial assessments of threats to biodiversity | F46: Human Dimensions of Wildlife | G46: 11 | H46: 1 | I46: 43-54 | J46: PubDatabase
A47: 24087 | B47: Journal Article | C47: Grech_etal | D47: 2008 | E47: A spatial assessment of the risk to a mobile marine mammal from bycatch | F47: Aquatic Conservation: Marine and Freshwater Ecosystems | G47: 18 | H47: 7 | I47: 1127-1139 | J47: PubDatabase
A48: 24856 | B48: Journal Article | C48: Mora | D48: 2018 | E48: A spatial framework for detecting anthropogenic impacts on predator-prey interactions that sustain ecological integrity in Mexico | F48: Ecological Processes | G48: 7 | H48: 1 | I48: NA | J48: PubDatabase
A49: 24897 | B49: Journal Article | C49: Muñoz_etal | D49: 2018 | E49: A spatial risk approach towards integrated marine spatial planning: A case study on European hake nursery areas in the North Alboran Sea | F49: Marine Environmental Research | G49: NA | H49: NA | I49: 190-207 | J49: PubDatabase
A50: 25588 | B50: Journal Article | C50: Silva_etal | D50: 2014 | E50: A spatially explicit approach to assess the collision risk between birds and overhead power lines: A case study with the little bustard | F50: Biological Conservation | G50: 170 | H50: NA | I50: 256-263 | J50: PubDatabase
A51: 24421 | B51: Journal Article | C51: Konstantopoulos_etal | D51: 2020 | E51: A spatially explicit impact assessment of road characteristics, road-induced fragmentation and noise on birds species in Cyprus | F51: Biodiversity | G51: 21 | H51: 1 | I51: 61-71 | J51: PubDatabase
A52: 23262 | B52: Journal Article | C52: Bedrosian_etal | D52: 2020 | E52: A Spatially Explicit Model to Predict the Relative Risk of Golden Eagle Electrocutions in the Northwestern Plains, USA | F52: Journal of Raptor Research | G52: 54 | H52: 2 | I52: 110-125 | J52: PubDatabase
A53: 24038 | B53: Journal Article | C53: Gimpel_etal | D53: 2013 | E53: A spatially explicit risk approach to support marine spatial planning in the German EEZ | F53: Marine Environmental Research | G53: 86 | H53: NA | I53: 56-69 | J53: PubDatabase
A54: 25114 | B54: Journal Article | C54: Pennino_etal | D54: 2017 | E54: A spatially explicit risk assessment approach: Cetaceans and marine traffic in the Pelagos Sanctuary (Mediterranean Sea) | F54: PLoS ONE | G54: 12 | H54: 6 | I54: NA | J54: PubDatabase
A55: 24404 | B55: Journal Article | C55: Klarenberg_etal | D55: 2019 | E55: A spatiotemporal natural-human database to evaluate road development impacts in an Amazon trinational frontier | F55: Scientific Data | G55: 6 | H55: 1 | I55: 44896 | J55: PubDatabase
A56: 26044 | B56: Journal Article | C56: Witt and Godley | D56: 2007 | E56: A step towards seascape scale conservation: Using vessel monitoring systems (VMS) to map fishing activity | F56: PLoS ONE | G56: 2 | H56: 10 | I56: NA | J56: PubDatabase
A57: 26047 | B57: Journal Article | C57: Wittig_etal | D57: 2007 | E57: A study of climate change and anthropogenic impacts in West Africa | F57: Environmental Science and Pollution Research | G57: 14 | H57: 3 | I57: 182-189 | J57: PubDatabase
A58: 24943 | B58: Journal Article | C58: Nelson_etal | D58: 2015 | E58: A time geographic approach for delineating areas of sustained wildlife use | F58: Annals of GIS | G58: 21 | H58: 1 | I58: 81-90 | J58: PubDatabase
A59: 24110 | B59: Journal Article | C59: Gunson_etal | D59: 2012 | E59: A tool to prioritize high-risk road mortality locations for wetland-forest herpetofauna in southern Ontario, Canada | F59: North-Western Journal of Zoology | G59: 8 | H59: 2 | I59: 409-413 | J59: PubDatabase
A60: 23816 | B60: Journal Article | C60: Elleouet_etal | D60: 2014 | E60: A trait-based approach for assessing and mapping niche overlap between native and exotic species: The mediterranean coastal fish fauna as a case study | F60: Diversity and Distributions | G60: 20 | H60: 11 | I60: 1333-1344 | J60: PubDatabase
A61: 25268 | B61: Journal Article | C61: Raimondo_etal | D61: 2019 | E61: A unified approach for protecting listed species and ecosystem services in isolated wetlands using community-level protection goals | F61: Science of the Total Environment | G61: 663 | H61: NA | I61: 465-478 | J61: PubDatabase
A62: 24039 | B62: Journal Article | C62: Giordano_etal | D62: 2008 | E62: Abundance and spatial distribution of Greater Rhea Rhea americana in two sites on the pampas grasslands with different land use | F62: Bird Conservation International | G62: 18 | H62: 1 | I62: 63-70 | J62: PubDatabase
A63: 24553 | B63: Journal Article | C63: Licata_etal | D63: 2019 | E63: Abundance, distribution and spread of the invasive Asian toad Duttaphrynus melanostictus in eastern Madagascar | F63: Biological Invasions | G63: 21 | H63: 5 | I63: 1615-1626 | J63: PubDatabase
A64: 24892 | B64: Journal Article | C64: Mullet_etal | D64: 2017 | E64: Acoustic Footprint of Snowmobile Noise and Natural Quiet Refugia in an Alaskan Wilderness | F64: Natural Areas Journal | G64: 37 | H64: 3 | I64: 332-349 | J64: PubDatabase
A65: 23700 | B65: Journal Article | C65: Deb_etal | D65: 2019 | E65: Adaptive management and planning for the conservation of four threatened large Asian mammals in a changing climate | F65: Mitigation and Adaptation Strategies for Global Change | G65: 24 | H65: 2 | I65: 259-280 | J65: PubDatabase
A66: 25515 | B66: Journal Article | C66: Sciarretta_etal | D66: 2016 | E66: Adaptive management of invasive pests in natural protected areas: The case of Matsucoccus feytaudi in Central Italy | F66: Bulletin of Entomological Research | G66: 106 | H66: 1 | I66: 43344 | J66: PubDatabase
A67: 24776 | B67: Journal Article | C67: Menegon_etal | D67: 2018 | E67: Addressing cumulative effects, maritime conflicts and ecosystem services threats through MSP-oriented geospatial webtools | F67: Ocean and Coastal Management | G67: 163 | H67: NA | I67: 417-436 | J67: PubDatabase
A68: 25697 | B68: Journal Article | C68: Struebig_etal | D68: 2018 | E68: Addressing human-tiger conflict using socio-ecological information on tolerance and risk | F68: Nature Communications | G68: 9 | H68: 1 | I68: NA | J68: PubDatabase
A69: 24197 | B69: Journal Article | C69: Herder_etal | D69: 2012 | E69: Alien invasion in Wallace's Dreamponds: Records of the hybridogenic "flowerhorn" cichlid in lake Matano, with an annotated checklist of fish species introduced to the Malili Lakes system in Sulawesi | F69: Aquatic Invasions | G69: 7 | H69: 4 | I69: 521-535 | J69: PubDatabase
A70: 24016 | B70: Report | C70: Gerlach | D70: 2002 | E70: Alien plant species threat assessment and management prioritization for Sequoia-Kings Canyon and Yosemite National Parks | F70: NA | G70: NA | H70: NA | I70: NA | J70: PubDatabase
A71: 25188 | B71: Journal Article | C71: Ponnampalam_etal | D71: 2015 | E71: Aligning conservation and research priorities for proactive species and habitat management: The case of dugongs Dugong dugon in Johor, Malaysia | F71: ORYX | G71: 49 | H71: 4 | I71: 743-749 | J71: PubDatabase
A72: 24720 | B72: Journal Article | C72: Mateo-Tomás_etal | D72: 2012 | E72: Alleviating human-wildlife conflicts: Identifying the causes and mapping the risk of illegal poisoning of wild fauna | F72: Journal of Applied Ecology | G72: 49 | H72: 2 | I72: 376-385 | J72: PubDatabase
A73: 25068 | B73: Journal Article | C73: Parry_etal | D73: 2009 | E73: Allocation of hunting effort by Amazonian smallholders: Implications for conserving wildlife in mixed-use landscapes | F73: Biological Conservation | G73: 142 | H73: 8 | I73: 1777-1786 | J73: PubDatabase
A74: 24585 | B74: Journal Article | C74: Liu_etal | D74: 2012 | E74: Almond organophosphate and pyrethroid use in the San Joaquin Valley and their associated environmental risk | F74: Journal of Soils and Sediments | G74: 12 | H74: 7 | I74: 1066-1078 | J74: PubDatabase
A75: 25488 | B75: Journal Article | C75: Scheele_etal | D75: 2019 | E75: Amphibian fungal panzootic causes catastrophic and ongoing loss of biodiversity | F75: Science | G75: 363 | H75: 6434 | I75: 1459-1463 | J75: PubDatabase
A76: 25654 | B76: Journal Article | C76: Spanowicz_etal | D76: 2020 | E76: An adaptive plan for prioritizing road sections for fencing to reduce animal mortality | F76: Conservation Biology | G76: NA | H76: NA | I76: NA | J76: PubDatabase
A77: 23699 | B77: Journal Article | C77: Deb_etal | D77: 2014 | E77: An alternative approach for delineating eco-sensitive zones around a wildlife sanctuary applying geospatial techniques | F77: Environmental Monitoring and Assessment | G77: 186 | H77: 4 | I77: 2641-2651 | J77: PubDatabase
A78: 23824 | B78: Journal Article | C78: Enríquez-Andrade_etal | D78: 2005 | E78: An analysis of critical areas for biodiversity conservation in the Gulf of California Region | F78: Ocean and Coastal Management | G78: 48 | H78: 1 | I78: 31-50 | J78: PubDatabase
A79: 23656 | B79: Journal Article | C79: Dang_etal | D79: 2019 | E79: An analysis of the spatial association between deforestation and agricultural field sizes in the tropics and subtropics | F79: PLoS ONE | G79: 14 | H79: 1 | I79: NA | J79: PubDatabase
A80: 26050 | B80: Journal Article | C80: Wolaver_etal | D80: 2018 | E80: An approach for evaluating changes in land-use from energy sprawl and other anthropogenic activities with implications for biotic resource management | F80: Environmental Earth Sciences | G80: 77 | H80: 5 | I80: NA | J80: PubDatabase
A81: 23155 | B81: Journal Article | C81: Astiaso_etal | D81: 2013 | E81: An estimation of urban fragmentation of natural habitats: Case studies of the 24 italian national parks | F81: Chemical Engineering Transactions | G81: 32 | H81: NA | I81: 49-54 | J81: PubDatabase
A82: 23560 | B82: Journal Article | C82: Clark and Tittensor | D82: 2010 | E82: An index to assess the risk to stony corals from bottom trawling on seamounts | F82: Marine Ecology | G82: 31 | H82: SUPPL. 1 | I82: 200-211 | J82: PubDatabase
A83: 25309 | B83: Journal Article | C83: Razgour_etal | D83: 2018 | E83: An integrated framework to identify wildlife populations under threat from climate change | F83: Molecular Ecology Resources | G83: 18 | H83: 1 | I83: 18-31 | J83: PubDatabase
A84: 25400 | B84: Journal Article | C84: Rodriguez-Merino_etal | D84: 2017 | E84: An invasion risk map for non-native aquatic macrophytes of the Iberian Peninsula | F84: Anales Del Jardin Botanico De Madrid | G84: 74 | H84: 1 | I84: 10 | J84: PubDatabase
A85: 23188 | B85: Journal Article | C85: Baig and Aldosari | D85: 2012 | E85: An investigation into the vanishing biodiversity: Implications for rural extension | F85: Bulgarian Journal of Agricultural Science | G85: 18 | H85: 3 | I85: 403-409 | J85: PubDatabase
A86: W26573 | B86: Report | C86: Nowell_etal | D86: 2016 | E86: An ounce of Prevention: Snow Leopard Crime Revisited | F86: TRAFFIC | G86: NA | H86: NA | I86: NA | J86: OrganisationalWebsite
A87: 23867 | B87: Conference Proceeding | C87: Farizal_etal | D87: 2020 | E87: Analysis of the Mount Tunggangan Wildlife Reserve Area Arrangement, Sragen, Central Java using Geographic Information Systems (GIS) with Ecological Sensitivity and Ecological Pressure Approaches | F87: NA | G87: NA | H87: NA | I87: 448 | J87: PubDatabase
A88: 25283 | B88: Journal Article | C88: Ramirez-Villegas_etal | D88: 2012 | E88: Analysis of threats to South American flora and its implications for conservation | F88: Journal for Nature Conservation | G88: 20 | H88: 6 | I88: 337-348 | J88: PubDatabase
A89: 23518 | B89: Journal Article | C89: Chen and Koprowski | D89: 2015 | E89: Animal occurrence and space use change in the landscape of anthropogenic noise | F89: Biological Conservation | G89: 192 | H89: NA | I89: 315-322 | J89: PubDatabase
A90: 23454 | B90: Journal Article | C90: Cardoso_etal | D90: 2018 | E90: Anthropic Pressure on the Diversity of Cactaceae in a Region of Atlantic Forest in Eastern Brazil | F90: Haseltonia | G90: 2018 | H90: 24 | I90: 28-35 | J90: PubDatabase
A91: 26080 | B91: Journal Article | C91: Yackulic_etal | D91: 2011 | E91: Anthropogenic and environmental drivers of modern range loss in large mammals | F91: Proceedings of the National Academy of Sciences of the United States of America | G91: 108 | H91: 10 | I91: 4024-4029 | J91: PubDatabase
A92: 23832 | B92: Journal Article | C92: Escobar_etal | D92: 2015 | E92: Anthropogenic disturbance and habitat loss for the red-listed Asiatic black bear (Ursus thibetanus): Using ecological niche modeling and nighttime light satellite imagery | F92: Biological Conservation | G92: 191 | H92: NA | I92: 400-407 | J92: PubDatabase
A93: 23951 | B93: Journal Article | C93: Fryxell_etal | D93: 2020 | E93: Anthropogenic Disturbance and Population Viability of Woodland Caribou in Ontario | F93: Journal of Wildlife Management | G93: NA | H93: NA | I93: NA | J93: PubDatabase
A94: 23290 | B94: Journal Article | C94: Benslimane_etal | D94: 2019 | E94: Anthropogenic stressors are driving a steep decline of hemipteran diversity in dune ponds in north-eastern Algeria | F94: Journal of Insect Conservation | G94: 23 | H94: 3 | I94: 475-488 | J94: PubDatabase
A95: 23960 | B95: Journal Article | C95: Gabriel_etal | D95: 2012 | E95: Anticoagulant rodenticides on our public and community lands: Spatial distribution of exposure and poisoning of a rare forest carnivore | F95: PLoS ONE | G95: 7 | H95: 7 | I95: NA | J95: PubDatabase
A96: 25879 | B96: Journal Article | C96: Vanthomme_etal | D96: 2017 | E96: Antipoaching standards in onshore hydrocarbon concessions drawn from a Central African case study | F96: Conservation Biology | G96: 31 | H96: 3 | I96: 696-706 | J96: PubDatabase
A97: 23282 | B97: Journal Article | C97: Bendell and Wan | D97: 2011 | E97: Application of aerial photography in combination with GIS for coastal management at small spatial scales: A case study of shellfish aquaculture | F97: Journal of Coastal Conservation | G97: 15 | H97: 4 | I97: 417-431 | J97: PubDatabase
A98: 24423 | B98: Journal Article | C98: Kope?_etal | D98: 2020 | E98: Application of airborne hyperspectral data for mapping of invasive alien Spiraea tomentosa L.: a serious threat to peat bog plant communities | F98: Wetlands Ecology and Management | G98: 28 | H98: 2 | I98: 357-373 | J98: PubDatabase
A99: 26033 | B99: Journal Article | C99: Winchell_etal | D99: 2014 | E99: Application of an approach for predicting pesticide concentrations in static water bodies using spatially explicit hydrography, landscape, and pesticide use data | F99: ACS Symposium Series | G99: 1168 | H99: NA | I99: 315-340 | J99: PubDatabase
A100: 24945 | B100: Journal Article | C100: Nematollahi_etal | D100: 2020 | E100: Application of InVEST habitat quality module in spatially vulnerability assessment of natural habitats (case study: Chaharmahal and Bakhtiari province, Iran) | F100: Environmental Monitoring and Assessment | G100: 192 | H100: 8 | I100: NA | J100: PubDatabase
...

Sheet Raw - 2
A1: ArticleID | B1: Authors | C1: Year | D1: Study_design | E1: Ecoregion | F1: Spatial_Scale | G1: Spatial_res_unit | H1: Spatial_res | I1: Continent_Ocean | J1: Country_EEZ | K1: Threat_metric | L1: Threat_data | M1: Threat | N1: Quantity_threats | O1: threat_precision | P1: threat_database | Q1: Pop_metric | R1: Pop_data | S1: pop_database | T1: tax_res | U1: tax_scope | V1: tax_kingdom | W1: plant_group | X1: animal_group
A2: 25370 | B2: Rímalová_etal | C2: 2014 | D2: Observational | E2: Freshwater | F2: National | G2: polygon | H2: NA | I2: europe | J2: Czech Republic | K2: survey | L2: Qualitative | M2: 8.1:SDAlienInv | N2: 1 | O2: level2 | P2: NA | Q2: survey | R2: Qualitative | S2: NA | T2: species | U2: order | V2: animalia | W2: na | X2: invertebrates
A3: 23013 | B3: Abade_etal | C3: 2018 | D3: Observational | E3: Terrestrial | F3: Local | G3: polygon | H3: na | I3: africa | J3: Tanzania, United Republic of | K3: literature | L3: Qualitative | M3: 1.1:DevResid;2.3:AgLivestock;5.1:UseAnimals;6.3:Other | N3: 4 | O3: cumulative | P3: na | Q3: survey | R3: Quantitative | S3: na | T3: species | U3: species | V3: animalia | W3: na | X3: mammal
A4: 23018 | B4: Abrahms_etal | C4: 2019 | D4: Observational | E4: Marine | F4: Local | G4: degrees | H4: 0.1 | I4: north pacific | J4: United States | K4: database | L4: Qualitative | M4: 4.3:ShipLane | N4: 1 | O4: level2 | P4: Channel Islands National Marine Sanctuary | Q4: modelled | R4: Quantitative | S4: NA | T4: species | U4: species | V4: animalia | W4: na | X4: mammal
A5: 23019 | B5: Abram_etal | C5: 2015 | D5: Observational | E5: Terrestrial | F5: Local | G5: km2 | H5: 1 | I5: asia | J5: Indonesia | K5: expert | L5: Quantitative | M5: 6.3:Other | N5: 1 | O5: level2 | P5: na | Q5: expert | R5: Quantitative | S5: NA | T5: species | U5: species | V5: animalia | W5: na | X5: mammal
A6: 23020 | B6: Abreo_etal | C6: 2019 | D6: Observational | E6: Marine | F6: Sub-national | G6: polygon | H6: na | I6: south china sea | J6: Philippines | K6: other | L6: Quantitative | M6: 9.4:PollGarbSW | N6: 1 | O6: level2 | P6: na | Q6: other | R6: Qualitative | S6: NA | T6: species | U6: phylum | V6: animalia | W6: na | X6: mammal;reptile
A7: 23022 | B7: Acevedo_etal | C7: 2007 | D7: Observational | E7: Terrestrial | F7: Sub-national | G7: km2 | H7: 1 | I7: europe | J7: Spain | K7: survey | L7: Qualitative | M7: 2.3:AgLivestock | N7: 1 | O7: level2 | P7: na | Q7: modelled;survey | R7: Quantitative | S7: NA | T7: species | U7: species | V7: animalia | W7: na | X7: mammal
A8: 23030 | B8: Adams and Setterfield | C8: 2015 | D8: Observational | E8: Terrestrial | F8: Sub-national | G8: m | H8: 250 | I8: australasia | J8: Australia | K8: literature | L8: Qualitative | M8: 8.1:SDAlienInv | N8: 1 | O8: level2 | P8: na | Q8: pchba;protected_area | R8: Qualitative | S8: NRETAS | T8: other | U8: other | V8: other | W8: na | X8: na
A9: 23046 | B9: Ahmad_etal | C9: 2015 | D9: Observational | E9: Terrestrial | F9: Local | G9: polygon | H9: NA | I9: asia | J9: India | K9: rs | L9: Qualitative | M9: 2.1:AgNTC;2.3:AgLivestock;1.4:DevUnspec | N9: 3 | O9: level2 | P9: NA | Q9: protected_area | R9: Qualitative | S9: NA | T9: other | U9: other | V9: other | W9: na | X9: na
A10: 23047 | B10: Ahmadi_etal | C10: 2019 | D10: Observational | E10: Terrestrial | F10: Multi-national | G10: km2 | H10: 1 | I10: asia | J10: Azerbaijan;Iran;Lebanon;Turkey | K10: modelled | L10: Quantitative | M10: 11.1:CC_Habitat | N10: 2 | O10: level2 | P10: NA | Q10: literature;survey | R10: Qualitative | S10: NA | T10: genus | U10: genus | V10: animalia | W10: na | X10: reptile
A11: 23061 | B11: Albouy_etal | C11: 2017 | D11: Observational | E11: Marine | F11: Global | G11: degrees | H11: 1 | I11: na | J11: na | K11: pcm | L11: Qualitative | M11: 1.2:DevComInd;3.1:OilGas;4.3:ShipLane;5.4:UseAquatic;8.1:SDAlienInv;9.1:PollDWW;11.1:CC_Habitat;11.3:CC_Temp;11.5:CC_other | N11: 10 | O11: cumulative | P11: Halpern_2008 | Q11: database | R11: Quantitative | S11: IUCN | T11: order | U11: order | V11: animalia | W11: na | X11: mammal
A12: 23062 | B12: Albright_etal | C12: 2017 | D12: Observational | E12: Terrestrial | F12: Sub-national | G12: degrees | H12: 0.125 | I12: north america | J12: United States | K12: modelled | L12: Quantitative | M12: 11.2:CC_Drought | N12: 1 | O12: level2 | P12: NA | Q12: survey | R12: Qualitative | S12: NA | T12: species | U12: order | V12: animalia | W12: na | X12: bird
A13: 23063 | B13: Alcaraz_etal | C13: 2015 | D13: Observational | E13: Freshwater | F13: Sub-national | G13: km2 | H13: 10 | I13: europe | J13: Spain | K13: survey | L13: Qualitative | M13: 8.1:SDAlienInv | N13: 1 | O13: level2 | P13: NA | Q13: survey | R13: Qualitative | S13: NA | T13: species | U13: species | V13: animalia | W13: na | X13: Fish
A14: 23051 | B14: Al-Chokhachy_etal | C14: 2014 | D14: Observational | E14: Freshwater | F14: Local | G14: polygon | H14: NA | I14: north america | J14: Canada;United States | K14: survey | L14: Quantitative | M14: 8.2:SDNativProb | N14: 1 | O14: level2 | P14: NA | Q14: survey | R14: Qualitative | S14: NA | T14: species | U14: family | V14: animalia | W14: na | X14: Fish
A15: 23064 | B15: Alexander and Waters | C15: 2000 | D15: Observational | E15: Terrestrial | F15: Local | G15: polygon | H15: NA | I15: north america | J15: Canada | K15: survey | L15: Qualitative | M15: 4.1:RoadRail | N15: 1 | O15: level2 | P15: na | Q15: survey | R15: qualitative | S15: NA | T15: species | U15: class | V15: animalia | W15: na | X15: mammal
A16: 23068 | B16: Alfred_etal | C16: 2010 | D16: Observational | E16: Terrestrial | F16: Sub-national | G16: m | H16: 2.5 | I16: asia | J16: Malaysia | K16: rs | L16: Qualitative | M16: 2.1:AgNTC;2.2:AgWood;4.1:RoadRail | N16: 3 | O16: level2 | P16: NA | Q16: survey | R16: Quantitative | S16: NA | T16: species | U16: species | V16: animalia | W16: na | X16: mammal
A17: 23071 | B17: Allan_etal | C17: 2017 | D17: Observational | E17: Terrestrial | F17: Global | G17: polygon | H17: NA | I17: na | J17: na | K17: pcm | L17: Quantitative | M17: 1.1:DevResid;1.2:DevComInd;1.3:DevRnR;2.1:AgNTC;2.3:AgLivestock;4.1:RoadRail;9.6:PollEnergy | N17: 7 | O17: cumulative | P17: HFI | Q17: protected_area | R17: Qualitative | S17: NaturalWorldHeritage | T17: other | U17: other | V17: other | W17: na | X17: na
A18: 23072 | B18: Allan_etal | C18: 2019 | D18: Observational | E18: Terrestrial | F18: Global | G18: km2 | H18: 30 | I18: na | J18: na | K18: pcm | L18: Quantitative | M18: 1.1:DevResid;1.2:DevComInd;2.1:AgNTC;2.3:AgLivestock;4.1:RoadRail;4.2:UtilityLine;5.1:UseAnimals;5.2:UsePlant;6.1:ActivRnR;6.3:Other;8.1:SDAlienInv;9.1:PollDWW;9.3:PollAgrFor;9.4:PollGarbSW;9.6:PollEnergy | N18: 15 | O18: cumulative | P18: HFI | Q18: database | R18: Quantitative | S18: IUCN | T18: phylum | U18: phylum | V18: animalia | W18: na | X18: mammal;amphibia;bird
A19: 23073 | B19: Almeida_etal | C19: 2014 | D19: Observational | E19: Freshwater | F19: Sub-national | G19: km2 | H19: 10 | I19: europe | J19: United Kingdom | K19: survey | L19: Qualitative | M19: 8.1:SDAlienInv | N19: 1 | O19: level2 | P19: NA | Q19: survey | R19: Qualitative | S19: NA | T19: species | U19: species | V19: animalia | W19: na | X19: invertebrates
A20: 23074 | B20: Almodóvar_etal | C20: 2012 | D20: Observational | E20: Freshwater | F20: Local | G20: polygon | H20: NA | I20: europe | J20: Spain | K20: survey | L20: Qualitative | M20: 11.3:CC_Temp | N20: 1 | O20: level2 | P20: NA | Q20: survey | R20: Qualitative | S20: NA | T20: species | U20: species | V20: animalia | W20: na | X20: Fish
A21: 23052 | B21: Al-Nasrawi_etal | C21: 2018 | D21: Observational | E21: Terrestrial | F21: Local | G21: m | H21: 0.8 | I21: australasia | J21: Australia | K21: rs | L21: Qualitative | M21: 11.1:CC_Habitat | N21: 1 | O21: level2 | P21: NA | Q21: rs | R21: Qualitative | S21: NA | T21: phylum | U21: phylum | V21: plantae | W21: mangrove;vegetation | X21: na
A22: 23080 | B22: Álvarez | C22: 2003 | D22: Observational | E22: Terrestrial | F22: National | G22: polygon | H22: NA | I22: south america | J22: Colombia | K22: literature | L22: Qualitative | M22: 6.2:WarConflict | N22: 1 | O22: level2 | P22: NA | Q22: literature | R22: Qualitative | S22: NA | T22: kingdom | U22: kingdom | V22: plantae | W22: forest | X22: na
A23: 23082 | B23: Alvarez-Berastegui_etal | C23: 2014 | D23: Observational | E23: Marine | F23: Sub-national | G23: m | H23: 300 | I23: mediterranean | J23: Spain | K23: expert;literature;survey | L23: Quantitative | M23: 1.1:DevResid;2.4:Aqua;5.4:UseAquatic;6.1:ActivRnR | N23: 4 | O23: cumulative | P23: NA | Q23: expert;literature;survey | R23: Quantitative | S23: NA | T23: domain | U23: domain | V23: animalia;plantae | W23: liliopsida | X23: fish
A24: 23083 | B24: Alvarez-Berrios and Mitchell | C24: 2015 | D24: Observational | E24: Terrestrial | F24: Multi-national | G24: m | H24: 250 | I24: south america | J24: Brazil;Bolivia;Peru;French Guyana;Suriname;Guyana;Venezuela;Colombia;Ecuador | K24: database;literature;rs | L24: Qualitative | M24: 3.2:MinQuar | N24: 1 | O24: level2 | P24: private mining GIS databases | Q24: rs | R24: quantitative | S24: NA | T24: kingdom | U24: kingdom | V24: plantae | W24: forest | X24: na
A25: 23085 | B25: Alvarez-Filip_etal | C25: 2019 | D25: Observational | E25: Marine | F25: Sub-national | G25: polygon | H25: na | I25: north atlantic | J25: Mexico | K25: survey | L25: Quantitative | M25: 8.6:DUnknownC | N25: 1 | O25: level2 | P25: na | Q25: survey | R25: qualitative | S25: NA | T25: class | U25: class | V25: animalia | W25: na | X25: invertebrates
A26: 23086 | B26: Alvarez-Romero_etal | C26: 2013 | D26: Observational | E26: Marine | F26: Sub-national | G26: m | H26: 500 | I26: south pacific | J26: Australia | K26: modelled;rs | L26: Quantitative | M26: 9.7:PollUnspec | N26: 1 | O26: level1 | P26: NA | Q26: rs | R26: Qualitative | S26: NA | T26: family | U26: domain | V26: animalia;plantae | W26: liliopsida | X26: invertebrates
A27: 23087 | B27: Alves_etal | C27: 2014 | D27: Observational | E27: Terrestrial | F27: Multi-national | G27: degrees | H27: 0.16 | I27: north america | J27: Canada;United States | K27: literature | L27: Qualitative | M27: 8.1:SDAlienInv | N27: 1 | O27: level2 | P27: NA | Q27: literature | R27: Qualitative | S27: NA | T27: family | U27: family | V27: animalia | W27: na | X27: mammal
A28: 25335 | B28: Amano_etal | C28: 2020 | D28: Observational | E28: Terrestrial | F28: Global | G28: degrees | H28: 1 | I28: na | J28: na | K28: database | L28: Quantitative | M28: 11.3:CC_Temp;11.5:CC_other | N28: 2 | O28: level2 | P28: CRU TS v4.01 | Q28: database;survey | R28: Quantitative | S28: International Bird Census_ICW | T28: class | U28: class | V28: animalia | W28: na | X28: bird
A29: 23091 | B29: Ambastha_etal | C29: 2010 | D29: Observational | E29: Terrestrial | F29: Local | G29: m | H29: 250 | I29: asia | J29: India | K29: rs | L29: Qualitative | M29: 1.1:DevResid;2.4:Aqua;2.5:AgUncpec | N29: 3 | O29: level2 | P29: NA | Q29: protected_area;rs | R29: Qualitative | S29: NA | T29: family | U29: family | V29: plantae | W29: liliopsida | X29: na
A30: 23100 | B30: Andersen_etal | C30: 2020 | D30: Observational | E30: Marine | F30: National | G30: km2 | H30: 2 | I30: north atlantic | J30: Denmark | K30: modelled | L30: Quantitative | M30: 7.2:WaterSystem;11.3:CC_Temp;9.7:PollUnspec;9.4:PollGarbSW;9.6:PollEnergy;1.2:DevComInd;2.4:Aqua;6.2:WarConflict;8.1:SDAlienInv;3.1:OilGas;3.3:Renew;4.2:UtilityLine;9.2:PollIndMil;4.3:ShipLane;6.1:ActivRnR;5.4:UseAquatic | N30: 16 | O30: cumulative | P30: NA | Q30: modelled | R30: Quantitative | S30: NA | T30: domain | U30: domain | V30: animalia;plantae | W30: liliopsida | X30: chordata
A31: W26591 | B31: Anderson_etal | C31: 2017 | D31: Observational | E31: Marine | F31: Local | G31: polygon | H31: NA | I31: north atlantic | J31: Belize | K31: survey | L31: Quantitative | M31: 8.1:SDAlienInv | N31: 1 | O31: level2 | P31: NA | Q31: protected_area | R31: Qualitative | S31: NA | T31: other | U31: other | V31: other | W31: na | X31: na
A32: 23105 | B32: Andrade-Díaz_etal | C32: 2019 | D32: Observational | E32: Terrestrial | F32: Sub-national | G32: NA | H32: NA | I32: south america | J32: Argentina | K32: database | L32: Qualitative | M32: 2.1:AgNTC;2.2:AgWood | N32: 2 | O32: cumulative | P32: geoportal.idesa.gob.ar | Q32: modelled | R32: Quantitative | S32: NA | T32: order | U32: order | V32: animalia | W32: na | X32: reptile
A33: 23106 | B33: Andréfouët_etal | C33: 2015 | D33: Observational | E33: Marine | F33: Multi-national | G33: m | H33: 30 | I33: south pacific | J33: Cook Islands;French Polynesia | K33: database;rs | L33: Quantitative | M33: 11.3:CC_Temp | N33: 1 | O33: level2 | P33: AVHRR Pathfinder V4.1 | Q33: literature | R33: Qualitative | S33: NA | T33: kingdom | U33: kingdom | V33: animalia | W33: na | X33: invertebrates
A34: 23114 | B34: Anjos_etal | C34: 2018 | D34: Observational | E34: Terrestrial | F34: Continental | G34: km2 | H34: 6 | I34: south america | J34: na | K34: modelled | L34: Quantitative | M34: 11.1:CC_Habitat | N34: 1 | O34: level2 | P34: na | Q34: rs | R34: qualitative | S34: NA | T34: kingdom | U34: kingdom | V34: plantae | W34: forest;habitat;habitat | X34: na
A35: 23117 | B35: Ansari and Golabi | C35: 2019 | D35: Observational | E35: Terrestrial | F35: Local | G35: polygon | H35: NA | I35: asia | J35: Iran | K35: rs;survey | L35: Qualitative | M35: 1.1:DevResid;2.1:AgNTC;2.3:AgLivestock | N35: 3 | O35: level1 | P35: NA | Q35: survey | R35: Qualitative | S35: NA | T35: species | U35: species | V35: animalia | W35: na | X35: mammal
A36: 23128 | B36: Araújo and Wang | C36: 2015 | D36: Observational | E36: Freshwater | F36: Sub-national | G36: polygon | H36: NA | I36: south america | J36: Brazil | K36: literature;rs | L36: Qualitative | M36: 7.2:WaterSystem | N36: 1 | O36: level2 | P36: NA | Q36: literature | R36: Qualitative | S36: NA | T36: species | U36: family | V36: animalia | W36: na | X36: mammal
A37: 23125 | B37: Araújo_etal | C37: 2008 | D37: Observational | E37: Terrestrial | F37: Continental | G37: km2 | H37: 50 | I37: europe | J37: na | K37: database | L37: Quantitative | M37: 1.1:DevResid;1.2:DevComInd;2.1:AgNTC;2.3:AgLivestock | N37: 3 | O37: level2 | P37: Eurostat2000 | Q37: modelled | R37: Qualitative | S37: NA | T37: class | U37: domain | V37: animalia;plantae | W37: tracheophyta | X37: bird;mammal;reptile;amphibia
A38: 23135 | B38: Arkema_etal | C38: 2014 | D38: Observational | E38: Marine | F38: National | G38: m | H38: 500 | I38: north atlantic | J38: Belize | K38: expert;modelled | L38: Quantitative | M38: 1.1:DevResid;1.2:DevComInd;1.3:DevRnR;2.4:Aqua;3.1:OilGas;4.3:ShipLane;5.4:UseAquatic;9.3:PollAgrFor;3.2:MinQuar;6.1:ActivRnR | N38: 10 | O38: level2 | P38: NA | Q38: expert | R38: Qualitative | S38: NA | T38: class | U38: domain | V38: animalia;plantae | W38: mangrove;liliopsida | X38: invertebrates
A39: 23138 | B39: Armenteras_etal | C39: 2013 | D39: Observational | E39: Terrestrial | F39: Local | G39: polygon | H39: NA | I39: south america | J39: Colombia | K39: rs | L39: Qualitative | M39: 2.3:AgLivestock;7.1:FireSystem;2.1:AgNTC | N39: 3 | O39: level2 | P39: NA | Q39: rs | R39: Qualitative | S39: NA | T39: kingdom | U39: kingdom | V39: plantae | W39: forest | X39: na
A40: 23142 | B40: Arroyave_etal | C40: 2020 | D40: Observational | E40: Terrestrial | F40: National | G40: polygon | H40: NA | I40: south america | J40: Colombia | K40: literature | L40: Qualitative;Quantitative | M40: 5.1:UseAnimals;6.3:Other | N40: 2 | O40: level2 | P40: NA | Q40: literature | R40: Qualitative | S40: NA | T40: class | U40: class | V40: animalia | W40: na | X40: reptile
A41: 23146 | B41: Asharfi_etal | C41: 2020 | D41: Observational | E41: Terrestrial | F41: Local | G41: m | H41: 20 | I41: asia | J41: Iran | K41: rs;survey | L41: Quantitative | M41: 1.2:DevComInd;9.2:PollIndMil | N41: 2 | O41: level2 | P41: NA | Q41: rs;survey | R41: Qualitative | S41: NA | T41: species | U41: kingdom | V41: plantae | W41: forest;magnoliopsida | X41: na
A42: 23147 | B42: Ashcroft_etal | C42: 2009 | D42: Observational | E42: Terrestrial | F42: Local | G42: polygon | H42: ha | I42: australasia | J42: Australia | K42: survey | L42: Quantitative | M42: 11.1:CC_Habitat | N42: 1 | O42: level2 | P42: na | Q42: survey | R42: qualitative | S42: NA | T42: kingdom | U42: kingdom | V42: plantae | W42: forest | X42: na
A43: 23150 | B43: Asner_etal | C43: 2008 | D43: Observational | E43: Terrestrial | F43: Local | G43: m | H43: 3 | I43: north america | J43: United States | K43: rs | L43: Qualitative | M43: 8.1:SDAlienInv | N43: 1 | O43: level2 | P43: NA | Q43: rs | R43: Qualitative | S43: NA | T43: kingdom | U43: kingdom | V43: plantae | W43: forest | X43: na
A44: 23151 | B44: Asner_etal | C44: 2009 | D44: Observational | E44: Terrestrial | F44: Global | G44: m | H44: 500 | I44: na | J44: na | K44: literature;rs | L44: Qualitative | M44: 2.3:AgLivestock;5.3:UseWood | N44: 2 | O44: level2 | P44: na | Q44: literature;rs | R44: qualitative | S44: NA | T44: kingdom | U44: kingdom | V44: plantae | W44: forest | X44: na
A45: 23154 | B45: Assuncao_etal | C45: 2019 | D45: Observational | E45: Terrestrial | F45: Sub-national | G45: degrees | H45: 0.5 | I45: south america | J45: Brazil | K45: pcm | L45: Quantitative | M45: 8.1:SDAlienInv | N45: 1 | O45: level2 | P45: Oliveria2018 | Q45: protected_area | R45: Quantitative | S45: NA | T45: other | U45: other | V45: other | W45: na | X45: na
A46: 23155 | B46: Astiaso_etal | C46: 2013 | D46: Observational | E46: Terrestrial | F46: National | G46: polygon | H46: na | I46: europe | J46: Italy | K46: modelled | L46: Quantitative | M46: 1.1:DevResid;1.2:DevComInd | N46: 2 | O46: level1 | P46: NA | Q46: protected_area | R46: Qualitative | S46: NA | T46: other | U46: other | V46: other | W46: na | X46: na
A47: 23160 | B47: Atkore_etal | C47: 2020 | D47: Observational | E47: Freshwater | F47: Sub-national | G47: NA | H47: NA | I47: asia | J47: India | K47: database;survey | L47: Quantitative | M47: 3.2:MinQuar;5.4:UseAquatic;9.1:PollDWW;9.3:PollAgrFor | N47: 4 | O47: level2 | P47: APHRODITE | Q47: survey | R47: quantitative | S47: NA | T47: class | U47: phylum | V47: animalia | W47: na | X47: fish
A48: 23163 | B48: Aubrecht_etal | C48: 2008 | D48: Observational | E48: Marine | F48: Global | G48: km | H48: km | I48: na | J48: na | K48: rs | L48: Quantitative | M48: 1.1:DevResid;3.1:OilGas;5.4:UseAquatic | N48: 3 | O48: cumulative | P48: DMSP Operational Linescan System (DMSP OLS) | Q48: rs | R48: qualitative | S48: NA | T48: order | U48: order | V48: animalia | W48: na | X48: invertebrates
A49: 23164 | B49: Auerbach_etal | C49: 2014 | D49: Observational | E49: Terrestrial | F49: Sub-national | G49: ha | H49: 25 | I49: australasia | J49: Australia | K49: modelled | L49: Quantitative | M49: 8.1:SDAlienInv;2.3:AgLivestock | N49: 2 | O49: level2 | P49: NA | Q49: literature | R49: Qualitative | S49: NA | T49: domain | U49: domain | V49: animalia;plantae | W49: tracheophyta | X49: chordata
A50: 23169 | B50: Avila_etal | C50: 2018 | D50: S_Review | E50: Marine | F50: Global | G50: degrees | H50: 0.5 | I50: na | J50: na | K50: literature | L50: Qualitative | M50: 2.4:Aqua;5.4:UseAquatic;4.3:ShipLane;6.1:ActivRnR;6.3:Other;9.1:PollDWW;9.4:PollGarbSW;9.6:PollEnergy;11.3:CC_Temp;11.1:CC_Habitat;11.4:CC_WetWeather;8.1:SDAlienInv;4.4:FlightPath | N50: 13 | O50: cumulative | P50: NA | Q50: literature | R50: Quantitative | S50: NA | T50: class | U50: class | V50: animalia | W50: na | X50: mammal
A51: 23170 | B51: Awkerman_etal | C51: 2016 | D51: Observational | E51: Marine | F51: Local | G51: m | H51: 90 | I51: north atlantic | J51: United States | K51: modelled | L51: Quantitative | M51: 3.1:OilGas | N51: 1 | O51: level2 | P51: NA | Q51: modelled | R51: Quantitative | S51: NA | T51: species | U51: species | V51: animalia | W51: na | X51: Fish
A52: 23171 | B52: Ayele_etal | C52: 2016 | D52: Observational | E52: Terrestrial | F52: Local | G52: m | H52: 30 | I52: africa | J52: Ethiopia | K52: rs | L52: Qualitative | M52: 2.1:AgNTC;2.3:AgLivestock | N52: 2 | O52: level2 | P52: na | Q52: rs | R52: qualitative | S52: NA | T52: kingdom | U52: kingdom | V52: plantae | W52: vegetation;forest;vegetation | X52: na
A53: 23177 | B53: Bacigalupe_etal | C53: 2019 | D53: Observational | E53: Terrestrial | F53: National | G53: km2 | H53: 1 | I53: south america | J53: Chile | K53: literature;survey | L53: Qualitative | M53: 8.1:SDAlienInv | N53: 1 | O53: level2 | P53: NA | Q53: literature;pchba;survey | R53: Quantitative | S53: BiodiversityHotspot | T53: class | U53: class | V53: animalia | W53: na | X53: amphibia
A54: 23185 | B54: Bahaa-El-Din_etal | C54: 2016 | D54: Observational | E54: Terrestrial | F54: Local | G54: polygon | H54: na | I54: africa | J54: Gabon | K54: survey | L54: Qualitative | M54: 1.1:DevResid;2.2:AgWood;5.1:UseAnimals;5.3:UseWood | N54: 4 | O54: cumulative | P54: NA | Q54: survey | R54: Qualitative | S54: NA | T54: species | U54: species | V54: animalia | W54: na | X54: mammal
A55: 23188 | B55: Baig and Aldosari | C55: 2012 | D55: Observational | E55: Terrestrial | F55: Local | G55: NA | H55: NA | I55: asia | J55: Pakistan | K55: rs | L55: Qualitative | M55: 1.4:DevUnspec | N55: 1 | O55: level1 | P55: NA | Q55: protected_area | R55: Qualitative | S55: RAMSAR | T55: other | U55: other | V55: other | W55: na | X55: na
A56: 23190 | B56: Bailey_etal | C56: 2017 | D56: Observational | E56: Terrestrial | F56: Sub-national | G56: km2 | H56: 25 | I56: north america | J56: United States | K56: rs | L56: Qualitative | M56: 1.1:DevResid;2.1:AgNTC;2.3:AgLivestock | N56: 2 | O56: level1 | P56: na | Q56: survey | R56: qualitative | S56: NA | T56: species | U56: species | V56: animalia | W56: na | X56: mammal
A57: 23196 | B57: Balasingham_etal | C57: 2018 | D57: Observational | E57: Freshwater | F57: Local | G57: polygon | H57: na | I57: north america | J57: Canada | K57: survey | L57: Qualitative | M57: 8.1:SDAlienInv | N57: 1 | O57: level2 | P57: na | Q57: survey | R57: qualitative | S57: NA | T57: species | U57: class | V57: animalia | W57: na | X57: Fish
A58: 23197 | B58: Baláž_etal | C58: 2014 | D58: Observational | E58: Freshwater | F58: Continental | G58: polygon | H58: na | I58: europe | J58: na | K58: survey | L58: Qualitative | M58: 8.1:SDAlienInv | N58: 1 | O58: level2 | P58: NA | Q58: survey | R58: Qualitative | S58: NA | T58: class | U58: class | V58: animalia | W58: na | X58: amphibia
A59: 23200 | B59: Balotari-Chiebao_etal | C59: 2018 | D59: Observational | E59: Terrestrial | F59: National | G59: km2 | H59: 25 | I59: europe | J59: Finland | K59: database | L59: Qualitative | M59: 3.3:Renew | N59: 1 | O59: level2 | P59: FinnishWindAtlas | Q59: rs | R59: Qualitative | S59: NA | T59: species | U59: species | V59: animalia | W59: na | X59: bird
A60: 23202 | B60: Balzotti_etal | C60: 2016 | D60: Observational | E60: Terrestrial | F60: Sub-national | G60: polygon | H60: na | I60: north america | J60: United States | K60: literature;modelled | L60: Quantitative | M60: 3.1:OilGas;8.1:SDAlienInv;11.1:CC_Habitat | N60: 3 | O60: cumulative | P60: NA | Q60: pchba | R60: Qualitative | S60: PAC;USFWS | T60: other | U60: other | V60: other | W60: na | X60: na
A61: 23207 | B61: Bangs_etal | C61: 2018 | D61: Observational | E61: Freshwater | F61: Local | G61: polygon | H61: na | I61: north america | J61: United States | K61: survey | L61: Qualitative | M61: 8.1:SDAlienInv | N61: 1 | O61: level2 | P61: na | Q61: survey | R61: qualitative | S61: NA | T61: species | U61: genus | V61: animalia | W61: na | X61: Fish
A62: 23211 | B62: Barbarossa_etal | C62: 2020 | D62: Observational | E62: Freshwater | F62: Global | G62: polygon | H62: na | I62: na | J62: na | K62: database | L62: Quantitative | M62: 7.2:WaterSystem | N62: 1 | O62: level2 | P62: GRanD;GOODD | Q62: database;literature | R62: qualitative | S62: IUCN | T62: phylum | U62: phylum | V62: animalia | W62: na | X62: fish
A63: 23222 | B63: Baret_etal | C63: 2006 | D63: Observational | E63: Terrestrial | F63: Local | G63: m | H63: 500 | I63: africa | J63: Mauritius | K63: survey | L63: Quantitative | M63: 8.1:SDAlienInv | N63: 1 | O63: level2 | P63: NA | Q63: pchba | R63: Qualitative | S63: BiodiversityHotspot | T63: other | U63: other | V63: other | W63: na | X63: na
A64: 23223 | B64: Barilani_etal | C64: 2007 | D64: Observational | E64: Terrestrial | F64: Multi-national | G64: NA | H64: NA | I64: europe | J64: France;Italy;Spain | K64: survey | L64: Qualitative | M64: 8.1:SDAlienInv | N64: 1 | O64: level2 | P64: NA | Q64: survey | R64: Qualitative | S64: NA | T64: species | U64: genus | V64: animalia | W64: na | X64: bird
A65: 23232 | B65: Barthelmess | C65: 2014 | D65: Observational | E65: Terrestrial | F65: Local | G65: m | H65: 30 | I65: north america | J65: United States | K65: survey | L65: Qualitative | M65: 4.1:RoadRail | N65: 1 | O65: level2 | P65: NA | Q65: survey | R65: Qualitative | S65: NA | T65: class | U65: class | V65: animalia | W65: na | X65: mammal
A66: 23234 | B66: Bartolino_etal | C66: 2012 | D66: Observational | E66: Marine | F66: Sub-national | G66: km2 | H66: 1369 | I66: north pacific | J66: Alaska | K66: survey | L66: Quantitative | M66: 5.4:UseAquatic | N66: 1 | O66: level2 | P66: NA | Q66: survey | R66: Quantitative | S66: NA | T66: species | U66: species | V66: animalia | W66: na | X66: fish
A67: 23236 | B67: Bartz_etal | C67: 2015 | D67: Observational | E67: Freshwater | F67: Local | G67: m | H67: 30 | I67: north america | J67: United States | K67: rs | L67: Qualitative | M67: 1.4:DevUnspec | N67: 1 | O67: level1 | P67: NA | Q67: literature | R67: Qualitative | S67: Ford etal 2011 | T67: species | U67: species | V67: animalia | W67: na | X67: fish
A68: 23237 | B68: Barve_etal | C68: 2005 | D68: Observational | E68: Terrestrial | F68: Local | G68: ha | H68: 30 | I68: asia | J68: India | K68: literature;survey | L68: Quantitative | M68: 1.1:DevResid;2.1:AgNTC;2.3:AgLivestock;5.1:UseAnimals;5.2:UsePlant;5.3:UseWood;7.1:FireSystem;8.1:SDAlienInv | N68: 8 | O68: level1 | P68: NA | Q68: protected_area | R68: Qualitative | S68: NA | T68: other | U68: other | V68: other | W68: na | X68: na
A69: 23242 | B69: Bass_etal | C69: 2010 | D69: Observational | E69: Terrestrial | F69: Sub-national | G69: km2 | H69: 100 | I69: south america | J69: Ecuador | K69: literature | L69: Qualitative | M69: 3.1:OilGas | N69: 1 | O69: level2 | P69: NA | Q69: literature;protected_area | R69: Qualitative | S69: NA | T69: class | U69: domain | V69: animalia;plantae | W69: tracheophyta | X69: amphibia;bird;mammal
A70: 23247 | B70: Battiston_etal | C70: 2012 | D70: Observational | E70: Terrestrial | F70: Local | G70: m | H70: 0.5 | I70: europe | J70: France | K70: rs | L70: Qualitative | M70: 1.1:DevResid;4.1:RoadRail | N70: 2 | O70: level2 | P70: NA | Q70: survey | R70: Qualitative | S70: NA | T70: species | U70: species | V70: animalia | W70: na | X70: mammal
A71: 23249 | B71: Bax_etal | C71: 2019 | D71: Observational | E71: Terrestrial | F71: Sub-national | G71: NA | H71: NA | I71: south america | J71: Peru | K71: database | L71: Qualitative | M71: 3.2:MinQuar;3.1:OilGas;2.2:AgWood | N71: 3 | O71: level2 | P71: MINAGRI;INGEMMET;PeruPetro | Q71: database;pchba | R71: Quantitative | S71: MINAM;BirdLife | T71: other | U71: other | V71: other | W71: na | X71: na
A72: 23252 | B72: Baynard_etal | C72: 2017 | D72: Observational | E72: Terrestrial | F72: Sub-national | G72: m | H72: 1 | I72: north america | J72: United States | K72: rs | L72: Qualitative | M72: 3.1:OilGas;3.3:Renew | N72: 1 | O72: level2 | P72: NA | Q72: protected_area;rs | R72: Qualitative | S72: NA | T72: kingdom | U72: kingdom | V72: plantae | W72: habitat | X72: na
A73: 23256 | B73: Beaudry_etal | C73: 2008 | D73: Observational | E73: Terrestrial | F73: Local | G73: polygon | H73: na | I73: north america | J73: United States | K73: modelled;survey | L73: Quantitative | M73: 4.1:RoadRail | N73: 1 | O73: level2 | P73: NA | Q73: survey | R73: Qualitative | S73: NA | T73: species | U73: order | V73: animalia | W73: na | X73: reptile
A74: 23258 | B74: Bebbington_etal | C74: 2018 | D74: Observational | E74: Terrestrial | F74: Multi-national | G74: polygon | H74: na | I74: asia;south america | J74: Brazil;Peru;Indonesia | K74: database;expert;literature | L74: Quantitative | M74: 3.1:OilGas;4.1:RoadRail;3.2:MinQuar;2.2:AgWood;2.1:AgNTC;5.3:UseWood | N74: 6 | O74: level2 | P74: NA | Q74: database;expert;literature;protected_area | R74: Qualitative | S74: NA | T74: kingdom | U74: kingdom | V74: plantae | W74: forest | X74: na
A75: 23261 | B75: Becker and Zamudio | C75: 2011 | D75: Observational | E75: Terrestrial | F75: National | G75: km2 | H75: 1 | I75: north america | J75: Costa Rica | K75: database | L75: Qualitative | M75: 8.1:SDAlienInv | N75: 1 | O75: level2 | P75: NA | Q75: database | R75: Qualitative | S75: NA | T75: order | U75: order | V75: animalia | W75: na | X75: amphibia
A76: 23262 | B76: Bedrosian_etal | C76: 2020 | D76: Observational | E76: Terrestrial | F76: Sub-national | G76: km2 | H76: 1 | I76: north america | J76: United States | K76: modelled | L76: Quantitative | M76: 4.2:UtilityLine | N76: 1 | O76: level2 | P76: NA | Q76: literature | R76: Quantitative | S76: NA | T76: species | U76: species | V76: animalia | W76: na | X76: bird
A77: 23266 | B77: Bejaoui_etal | C77: 2020 | D77: Observational | E77: Freshwater | F77: Local | G77: polygon | H77: na | I77: africa | J77: Tunisia | K77: literature | L77: Qualitative | M77: 2.4:Aqua;1.1:DevResid;1.2:DevComInd;4.3:ShipLane;5.4:UseAquatic | N77: 5 | O77: level1 | P77: NA | Q77: survey | R77: Qualitative | S77: NA | T77: species | U77: species | V77: animalia | W77: na | X77: invertebrates
A78: 23276 | B78: Bellard_etal | C78: 2016 | D78: Observational | E78: Terrestrial | F78: Global | G78: minutes | H78: 10 | I78: na | J78: na | K78: database | L78: Quantitative | M78: 8.1:SDAlienInv | N78: 1 | O78: level2 | P78: IUCN | Q78: database | R78: Quantitative | S78: IUCN | T78: class | U78: phylum | V78: animalia | W78: na | X78: mammal;bird;reptile;amphibia
A79: 23278 | B79: Belpaire_etal | C79: 2015 | D79: Observational | E79: Freshwater | F79: Sub-national | G79: polygon | H79: na | I79: europe | J79: Belgium | K79: survey | L79: Quantitative | M79: 9.2:PollIndMil | N79: 1 | O79: level2 | P79: na | Q79: survey | R79: qualitative | S79: NA | T79: species | U79: species | V79: animalia | W79: na | X79: Fish
A80: 23280 | B80: Ben Rais_etal | C80: 2016 | D80: Observational | E80: Marine | F80: Sub-national | G80: degrees | H80: 0.1 | I80: mediterranean | J80: Tunisia | K80: expert;literature | L80: Quantitative | M80: 2.4:Aqua;5.1:UseAnimals;4.3:ShipLane;8.1:SDAlienInv;9.1:PollDWW;9.2:PollIndMil;9.3:PollAgrFor;3.1:OilGas;11.3:CC_Temp | N80: 9 | O80: level2 | P80: NA | Q80: database | R80: Qualitative | S80: FishMed | T80: phylum | U80: phylum | V80: animalia | W80: na | X80: fish
A81: 23282 | B81: Bendell and Wan | C81: 2011 | D81: Observational | E81: Marine | F81: Local | G81: polygon | H81: NA | I81: north pacific | J81: Canada | K81: rs;survey | L81: Qualitative | M81: 2.4:Aqua | N81: 1 | O81: level2 | P81: NA | Q81: modelled | R81: Quantitative | S81: NA | T81: class | U81: class | V81: animalia | W81: na | X81: bird
A82: 23285 | B82: Bennett_etal | C82: 2010 | D82: Observational | E82: Freshwater | F82: Sub-national | G82: polygon | H82: NA | I82: north america | J82: Canada | K82: survey | L82: Qualitative | M82: 8.1:SDAlienInv | N82: 1 | O82: level2 | P82: NA | Q82: survey | R82: Qualitative | S82: NA | T82: species | U82: species | V82: animalia | W82: na | X82: Fish
A83: 23290 | B83: Benslimane_etal | C83: 2019 | D83: Observational | E83: Freshwater | F83: Local | G83: polygon | H83: na | I83: africa | J83: Algeria | K83: rs | L83: Qualitative | M83: 2.5:AgUncpec;4.1:RoadRail;1.4:DevUnspec;7.2:WaterSystem | N83: 4 | O83: level1 | P83: NA | Q83: protected_area | R83: Qualitative | S83: NA | T83: other | U83: other | V83: other | W83: na | X83: na
A84: 23293 | B84: Berthon_etal | C84: 2018 | D84: Observational | E84: Terrestrial | F84: National | G84: km2 | H84: 1 | I84: australasia | J84: Australia | K84: database;literature | L84: Qualitative | M84: 8.1:SDAlienInv | N84: 1 | O84: level2 | P84: Government | Q84: database;literature | R84: Qualitative | S84: Government | T84: family | U84: family | V84: plantae | W84: magnoliopsida | X84: na
A85: 23301 | B85: Bezeng_etal | C85: 2020 | D85: Observational | E85: Terrestrial | F85: National | G85: km2 | H85: 1 | I85: africa | J85: South Africa | K85: literature | L85: Quantitative | M85: 8.1:SDAlienInv | N85: 1 | O85: level2 | P85: NA | Q85: database;protected_area | R85: Qualitative | S85: SouthAfricanProtectedAreaDatabase | T85: other | U85: other | V85: other | W85: na | X85: na
A86: 23303 | B86: Bhatt_etal | C86: 2016 | D86: Observational | E86: Freshwater | F86: National | G86: NA | H86: NA | I86: asia | J86: India | K86: database;modelled | L86: Quantitative | M86: 1.1:DevResid;2.5:AgUncpec;8.1:SDAlienInv | N86: 3 | O86: cumulative | P86: India-WRIS | Q86: modelled | R86: Quantitative | S86: FishBase | T86: phylum | U86: phylum | V86: animalia | W86: na | X86: fish
A87: 23304 | B87: Bhola_etal | C87: 2012 | D87: Observational | E87: Terrestrial | F87: Local | G87: km2 | H87: 25 | I87: africa | J87: Kenya | K87: literature;survey | L87: Quantitative | M87: 2.3:AgLivestock;2.1:AgNTC;1.1:DevResid | N87: 3 | O87: level2 | P87: NA | Q87: survey | R87: Quantitative | S87: NA | T87: species | U87: class | V87: animalia | W87: na | X87: mammal
A88: 23306 | B88: Bi_etal | C88: 2020 | D88: Observational | E88: Marine | F88: Multi-national | G88: NA | H88: NA | I88: north atlantic | J88: United States;Mexico;Cuba;Bahamas;Dominican Republic;Dominica;Trinidad and Tobago;Barbados;Grenada;Saint Lucia;Martinique;Aruba;Antigua and Barbuda;Anguilla;Bonaire; British Virgin Islands;Cayman Islands;Dominica;Guadeloupe;Jamaica;Montserrat;Navassa Island;Puerto Rico;Saba; Saint Kitts and Nevis;Saint Vincent and the Grenadines;Turks and Caicos Islands;United States Virgin Islands;Belize;Haiti;Honduras;Colombia;Panama; Curaçao; Saint-Barthélemy; Sint-Eustatius; Collectivity of Saint Martin; Nicaragua | K88: database | L88: Qualitative | M88: 5.4:UseAquatic | N88: 1 | O88: level2 | P88: PelagicObserverProgram_POP | Q88: database | R88: Qualitative | S88: POP | T88: class | U88: class | V88: animalia | W88: na | X88: bird
A89: 23313 | B89: Binothman | C89: 2016 | D89: Observational | E89: Terrestrial | F89: Sub-national | G89: polygon | H89: na | I89: asia | J89: Saudi Arabia | K89: survey | L89: Qualitative | M89: 5.1:UseAnimals | N89: 1 | O89: level2 | P89: NA | Q89: survey | R89: Quantitative | S89: NA | T89: species | U89: genus | V89: animalia | W89: na | X89: bird
A90: 23315 | B90: Birkmanis_etal | C90: 2020 | D90: Observational | E90: Marine | F90: National | G90: km2 | H90: 81 | I90: indian ocean | J90: Australia | K90: database | L90: Quantitative | M90: 5.1:UseAnimals | N90: 1 | O90: level2 | P90: AustalianBureauofAgricultural and ResourceEconomicsandSciences_ABARES | Q90: database | R90: Quantitative | S90: NA | T90: genus | U90: class | V90: animalia | W90: na | X90: Fish
A91: 23318 | B91: Bisi_etal | C91: 2019 | D91: Observational | E91: Terrestrial | F91: Local | G91: polygon | H91: m | I91: asia | J91: Myanmar (Burma) | K91: survey | L91: Qualitative | M91: 5.1:UseAnimals | N91: 1 | O91: level2 | P91: na | Q91: survey | R91: qualitative | S91: NA | T91: species | U91: class | V91: animalia | W91: na | X91: mammal
A92: 23330 | B92: Böhm_etal | C92: 2013 | D92: Observational | E92: Marine;Terrestrial | F92: Global | G92: km2 | H92: 7770 | I92: na | J92: na | K92: database | L92: Quantitative | M92: 2.2:AgWood;2.5:AgUncpec;5.1:UseAnimals | N92: 3 | O92: level2 | P92: IUCNredlist | Q92: database | R92: Quantitative | S92: IUCNredlist | T92: class | U92: class | V92: animalia | W92: na | X92: reptile
A93: 23331 | B93: Böhm_etal | C93: 2016 | D93: Observational | E93: Marine;Terrestrial | F93: Global | G93: km2 | H93: 7770 | I93: na | J93: na | K93: database | L93: Quantitative | M93: 11.3:CC_Temp;11.2:CC_Drought;11.5:CC_other | N93: 3 | O93: level1 | P93: IUCNredlist | Q93: database | R93: Quantitative | S93: IUCNredlist | T93: class | U93: class | V93: animalia | W93: na | X93: reptile
A94: 23337 | B94: Bonesi_etal | C94: 2007 | D94: Observational | E94: Freshwater | F94: Local | G94: km2 | H94: 25 | I94: europe | J94: United Kingdom | K94: literature | L94: Qualitative | M94: 8.1:SDAlienInv | N94: 1 | O94: level2 | P94: NA | Q94: literature | R94: Qualitative | S94: NA | T94: species | U94: species | V94: animalia | W94: na | X94: mammal
A95: 23340 | B95: Borah_etal | C95: 2016 | D95: Observational | E95: Terrestrial | F95: Sub-national | G95: km2 | H95: 100 | I95: asia | J95: India | K95: survey | L95: Qualitative | M95: 4.1:RoadRail | N95: 1 | O95: level2 | P95: na | Q95: survey | R95: quantitative | S95: NA | T95: species | U95: species | V95: animalia | W95: na | X95: mammal
A96: 23343 | B96: Borrelli_etal | C96: 2015 | D96: Observational | E96: Terrestrial | F96: Local | G96: m | H96: 500 | I96: south america | J96: Colombia | K96: rs | L96: Quantitative | M96: 7.1:FireSystem | N96: 1 | O96: level2 | P96: NA | Q96: protected_area | R96: Qualitative | S96: NA | T96: other | U96: other | V96: other | W96: na | X96: na
A97: 23345 | B97: Bose_etal | C97: 2020 | D97: Observational | E97: Terrestrial | F97: Sub-national | G97: m | H97: 100 | I97: europe | J97: Germany | K97: modelled | L97: Quantitative | M97: 3.3:Renew | N97: 1 | O97: level2 | P97: NA | Q97: survey | R97: Quantitative | S97: NA | T97: species | U97: species | V97: animalia | W97: na | X97: bird
A98: 23350 | B98: Bouchard_etal | C98: 2015 | D98: Observational | E98: Terrestrial | F98: Local | G98: polygon | H98: NA | I98: africa | J98: South Africa | K98: survey | L98: Qualitative | M98: 8.1:SDAlienInv;6.1:ActivRnR | N98: 2 | O98: level2 | P98: NA | Q98: protected_area | R98: Qualitative | S98: NA | T98: other | U98: other | V98: other | W98: na | X98: na
A99: 23353 | B99: Boulanger_etal | C99: 2014 | D99: Observational | E99: Terrestrial | F99: Sub-national | G99: polygon | H99: NA | I99: north america | J99: Canada | K99: literature | L99: Qualitative | M99: 4.1:RoadRail | N99: 1 | O99: level2 | P99: NA | Q99: rs | R99: Qualitative | S99: NA | T99: species | U99: species | V99: animalia | W99: na | X99: mammal
A100: 23355 | B100: Bourgoin_etal | C100: 2020 | D100: Observational | E100: Terrestrial | F100: Sub-national | G100: m | H100: 10 | I100: asia | J100: Thailand | K100: rs | L100: Qualitative | M100: 2.1:AgNTC;2.3:AgLivestock;2.2:AgWood | N100: 1 | O100: level1 | P100: NA | Q100: rs | R100: Qualitative | S100: NA | T100: kingdom | U100: kingdom | V100: plantae | W100: forest | X100: na
...

Sheet Raw - 3 (Typology)
A1: Typologies | C1: *Where multiple, use a semi-colon to delimit (applies to: 2.1; 2.4; 2.7; 2.8; 3.3; 3.4; 4.3;4.4)
A3: Field Code | B3: 1.1 | C3: 2.1 | D3: 2.2 | E3: 2.3 | F3: 3.1 | G3: 3.2 | H3: 3.3 | I3: 3.4 | J3: 3.5 | K3: 3.6 | L3: 3.7 | M3: 4.1 | N3: 4.2 | O3: 4.3 | P3: 4.4 | R3: 4.5 | S3: 4.6 | T3: 5.1 | U3: 5.2 | V3: 5.3 | W3: 5.4 | X3: 5.5 | Y3: 5.6 | Z3: 5.7 | AA3: 5.8 | AB3: 6
A4: Data Field | B4: Article_ID | C4: Date_Coded | D4: Coded_by | E4: Inclusion | F4: Study_design | G4: Ecoregion | H4: Spatial_scale | I4: Spatial_res_unit | J4: Spatial_res | K4: Continent_Ocean | L4: Country_EEZ | M4: Threat_metric | N4: Threat_data | O4: Threat_database | P4: Threat | R4: Quantity_threats | S4: threat_precision | T4: Pop_metric | U4: Pop_data | V4: Pop_database | W4: Tax.res | X4: Tax.scope | Y4: Taxa.kingdom | Z4: animal.group | AA4: plant.group | AB4: Comment
A5: Data Type | B5: text | C5: Date | D5: Text | E5: binary | F5: Text | G5: Text | H5: Text | I5: Text | J5: numeric | K5: text | L5: text | M5: text | N5: text | O5: text | P5: list | R5: numeric | S5: list | T5: list | U5: list | V5: list | W5: list | X5: list | Y5: list | Z5: text | AA5: text | AB5: text
A6: Info | B6: EPPI4 ID | C6: Removed after coding was consolidated between the two reviewers | I6: na applied if polygon | K6: na applied if global | L6: na applied if spatial scale > country | O6: name of data source | R6: Number of tier 2 threats (3.6) | V6: name of data source | Z6: class | AA6: class | AB6: Removed after consolidation
C7: The date that the coding was applied | D7: The reviewer that coded the article | E7: Marks any decisions made regarding inclusion after the full-text screening stage | F7: The nature of the investigation | G7: The ecoregion(s) that the threat map covers | H7: The spatial scales covered by threat maps within the study | I7: The resolution at which the distribution of threats was presented | J7: The units that the spatial resolution was given in | K7: The broad geographic region that the threat map covers. Oceans = marine, continents = terrestrial an freshwater | L7: The country or countries that threat maps within the article cover. | M7: The methods used to collect and present data on where threats occur | N7: The type of data used to represent where threats occur | P7: Categories of human-driven threat according to Salafsky(2008). | R7: The number of distinct threat categories (4.4) mapped in each study. | S7: The thematic precision of the presentation of threats. See extended definitions | T7: The method used to collect and present data on the presence of individuals of a wild species | U7: The type of data used to collect and present data on the presence of individuals of a wild species | W7: See extended definitions | X7: See extended definitions | Z7: See extended definitions | AA7: See extended definitions
A10: Entry values | C10: dd.mm.yy | D10: FR | E10: 1=include | F10: Experimental | G10: Terrestrial | H10: Global | I10: km2 | K10: Africa | L10: na | M10: PCM | N10: Quantitative | O10: e.g. HFI (human footprint index) | P10: 1.1:DevResid | Q10: Housing & urban area | R10: 1 to 42 | S10: cumulative | T10: database | U10: Quantitative | V10: e.g IUCN | W10: Domain | X10: Domain | Y10: Animalia
D11: EH | E11: 0=exclude | F11: Observational | G11: Freshwater | H11: Continental | I11: degrees | K11: Antarctica | L11: Aruba | M11: RS | N11: Qualitative | O11: na (if source type is not database) | P11: 1.2:DevComInd | Q11: Commercial & industrial areas | S11: level1 | T11: survey | U11: Qualitative | V11: na (if source type is not database) | W11: Kingdom | X11: Kingdom | Y11: Plantae
F12: S_Review | G12: Marine | H12: Multi-national | I12: na | K12: Europe | L12: Antigua and Barbuda | M12: database | P12: 1.3:DevRnR | Q12: Tourism & recreation areas | S12: level2 | T12: PCHBA | W12: Phylum | X12: Phylum | Y12: na
H13: National | I13: m | K13: North America | L13: Afghanistan | M13: literature | P13: 1.4:DevUnspec | Q13: Unspecified Residential & commercial development | T13: Protected_Area | W13: Class | X13: Class
H14: Sub-national | I14: ha | K14: South America | L14: Algeria | M14: Survey | P14: 2.1:AgNTC | Q14: Annual & perennial non-timber crops | T14: Expert | W14: Order | X14: Order
H15: Local | I15: minutes | K15: Asia | L15: Azerbaijan | M15: Modelled | P15: 2.2:AgWood | Q15: Wood & pulp plantations | T15: RS | W15: Family | X15: Family
I16: m2 | K16: Australasia | L16: Albania | M16: Expert | P16: 2.3:AgLivestock | Q16: Livestock farming & ranching | T16: Literature | W16: Genus | X16: Genus
I17: arc_seconds | K17: Arctic_Ocean | L17: Armenia | M17: Other | P17: 2.4:Aqua | Q17: Marine & freshwater aquaculture | T17: Other | W17: Species | X17: Species
I18: nm2 | K18: North_Atlantic_Ocean | L18: Andorra | P18: 2.5:AgUncpec | Q18: Unspecified Agriculture & aquaculture | T18: Modelled | W18: na | X18: na
K19: South_Atlantic_Ocean | L19: Angola | P19: 3.1:OilGas | Q19: Oil & gas drilling
K20: Indian_Ocean | L20: American Samoa | P20: 3.2:MinQuar | Q20: Mining & quarrying
K21: North_Pacific_Ocean | L21: Argentina | P21: 3.3:Renew | Q21: Renewable energy
K22: South_Pacific_Ocean | L22: Australia | P22: 3.4:EnergUnspec | Q22: Unspecified Energy production & mining
K23: Mediterannean | L23: Austria | P23: 4.1:RoadRail | Q23: Roads & railroads
K24: South China Sea | L24: Anguilla | P24: 4.2:UtilityLine | Q24: Utility & service lines
K25: CaspianSea | L25: Antarctica | P25: 4.3:ShipLane | Q25: Shipping lanes
K26: Southern Ocean | L26: Bahrain | P26: 4.4:FlightPath | Q26: Flight paths
K27: na | L27: Barbados | P27: 4.5.UnspecLine | Q27: Unspecified Transportation & service corridors
L28: Botswana | P28: 5.1:UseAnimals | Q28: Hunting & collecting terrestrial animals
L29: Bermuda | P29: 5.2:UsePlant | Q29: Gathering terrestrial plants
L30: Belgium | P30: 5.3:UseWood | Q30: Logging & wood harvesting
L31: Bahamas, The | P31: 5.4:UseAquatic | Q31: Fishing & harvesting aquatic resources
L32: Bangladesh | P32: 5.5:UseUnspec | Q32: Unspecified Biological resource use
L33: Belize | P33: 6.1:ActivRnR | Q33: Recreational activities
L34: Bosnia and Herzegovina | P34: 6.2:WarConflict | Q34: War, civil unrest & military exercises
L35: Bolivia | P35: 6.3:Other | Q35: Work & other activities
L36: Myanmar (Burma) | P36: 7.1:FireSystem | Q36: Fire & fire suppression
L37: Benin | P37: 7.2:WaterSystem | Q37: Dams & water management/use
L38: Byelarus | P38: 7.3:OtherSystem | Q38: Other ecosystem modifications
L39: Solomon Islands | P39: 8.1:SDAlienInv | Q39: Invasive non-native/alien species/diseases
... L57: Comoros | P57: 12.0:Other | Q57: Other threat
L58: Colombia
L59: Northern Mariana Islands
L60: Costa Rica
L61: Central African Republic
L62: Cuba
L63: Cape Verde
L64: Cook Islands
L65: Cyprus
L66: Denmark
L67: Djibouti
L68: Dominica
L69: Jarvis Island
... L261: Zimbabwe

Sheet Raw -4 (Extended Definitions)
A1: Extended Definitions
A3: 3.1 Study Design
B4: Observational | E4: Variables are not actively manipulated
B5: Experimental | E5: For the sake of this analysis all research which manipulates variables regardless of tightly controlled conditions will be classed as experimental (e.g. exclusion experiments in a natural setting)
B6: S_Review | E6: Systematic review (including meta-analyses). Novel syntheses of data gathered from existing literature.
A7: 3.3 Spatial Scale
B8: Global | E8: The study extent is the whole world
B9: Continental | E9: Study extent covers over 3/4 of a continent or an ocean. This excludes studies of individual countries that encompass > ¾ of the area of the continent (e.g. Australia).
B10: Multi-national | E10: Study extent is defined by the boundary of more than one country, or sites across multiple countries (>10,000km2)
B11: National | E11: Study extent is defined by the boundary of one country
B12: Sub-national | E12: Study extent is larger than 10,000km2 within a single country
B13: Local | E13: Study extent is less than 10,000km2
A14: 3.4 Spatial Resolution Units
B15: The spatial unit used to display the threat map
A16: 3.5 Spatial Resolution
B17: The size of single units that were mapped within the study, rather than the resolution in which data was gathered
A19: 4.1 Threat Metric
B20: PCM | E20: Pre-calculated metric (e.g. Human Footprint Index if accessed as an already computed index)
B21: Database | E21: Existing dataset of human activities or threats to species (e.g. FAO, IUCN, fishing logbook data, repositories of citizen science collected data)
B22: RS | E22: Remotely sensed primary data (Satellite data, aerial surveys, GPS trackers, Remote vessel monitoring systems (VMS). *The use of ground-level camera traps should be classed under ‘survey’)
B23: Literature | E23: Data on threat distribution gathered from existing literature (E.g. Mapping locations of studies that observe threats in a systematic review, using findings from existing peer-reviewed literature or other paper-based sources or archives) E.g. Scraping data from previous published peer-reviewed literature E.g. Scraping data from news reports, paper-based archives or other non-published literature sources )
B24: Survey | E24: Primary collection of data via ground level survey methods to identify presence/absence or intensity of threat (e.g. line transects, camera traps, point counts)
B25: Modelled | E25: Predicted distributions of a current threat based on occurance or susceptibility data (e.g. invasive species or climate change risk)
B26: Expert Judgement | E26: The spatial distribution of threats to species is determined by primary expert elicitation methods (e.g. Interviews, participatory mapping processes, questionnaires)
B27: Other | E27: Any other metric used to determine the spatial distribution of threat to species (e.g. Web scraping Social Media, and data gathered from museum specimens)
A28: 4.6 threat_precision
B29: Cumulative | E29: Individual threats are all mapped together as a single index
B30: Level 1 | E30: Threats are presented individually at the most coarse level of the threat classifcation framework (e.g. Agriculture/Aquaculture, Development, Biological resource use)
B31: Level 2 | E31: Threats are presented individually at a precision greater than level 2 in the threat classifcation framework or finer (e.g. Residential development, livestock farming, hunting)
A32: 5.1 Population Metric
B33: Literature | E33: Secondary data on species distribution gathered from existing literature
B34: Database | E34: Existing dataset of species distributions (e.g. IUCN, or iNaturalist)
B35: Modelled | E35: Predicted distribution of species based on occurance data (e.g. EEO, and habitat suitability modelling)
B36: Survey | E36: Primary data collected on the presence/absence or density of target species through ground-level observations (e.g. line transects, camera traps, point counts)
B37: PCHBA | E37: Pre-calculated high Biodiversity Areas. Identified from previous work to be of high value for biodiversity. E.g. biodiversity hotspots or key biodiversity areas (e.g. Myers 2000 Biodiversity Hotspot, Key Biodiversity areas (Important Bird and Biodiversity Areas, Alliance for zero extinction sites, critical ecosystem partnership)
B38: Protected Area | E38: Any land or sea that is legislatively protected from some or any disturbance (e.g. IUCN PA categories 1a, 1b, 2, and 4, RAMSAR sites, and UNESCO Natural World heritage sites, Marine protected areas)
B39: Expert Judgement | E39: Expert elicitation methods were used to determine the spatial distribution of species within the study area
B40: Other | E40: Any other metric type used to determine the spatial distribution of species within the study area (e.g. social media)
A42: 4.2 Threat data & 5.2 Population data
B43: Quantitative | E43: The measure for population and threat used for each spatial unit is a numeric value. E.g intensity, frequency, density
B44: Qualitative | E44: The measure for population and threat used for each spatial unit does not have a numeric value. E.g categories or presence/absence
A46: 5.4 Taxanomic resolution
B47: The lowest level of taxonomic hierachy that includes all species mapped as a single taxonomic unit
A48: 5.5 Taxonomic scope
B49: The lowest level of taxonomic hierachy that includes all species studied
A50: 5.7 animal group & 5.8 plant group
B51: List the taxa included at minimum class level. If taxa included are from a single definable group, for which the reporting of class here would assume the inclusion of multiple other non-studied species, enter that group name here e.g. Seagrass.

Sheet Enriched
A1: ArticleID | B1: study_design | C1: realm | D1: threats_l1 | E1: threats_l0 | F1: Threat_metric | G1: Pop_metric | H1: tax_kingdom | I1: Continent_Ocean | J1: Country_EEZ | K1: Study_design_orig | L1: Ecoregion | M1: Threat_orig | N1: threat_precision | O1: threat_database | P1: Quantity_threats | Q1: Threat_data | R1: Pop_data | S1: pop_database | T1: animal_group | U1: tax_res | V1: tax_scope | W1: plant_group | X1: Spatial_Scale | Y1: Spatial_res_unit | Z1: Spatial_res | AA1: unspec_other
A2: 24053 | B2: =K2 -> Observational | C2: ["Freshwater"] | D2: ["Housing & urban area"] | E2: ["Residential & commercial development"] | F2: database;expert;rs | G2: survey | H2: animalia | I2: south america | J2: Argentina | K2: Observational | L2: Freshwater | M2: 1.1:DevResid | N2: level1 | O2: ArgentineanGeorgraphicINstitute | P2: 1 | Q2: Qualitative | R2: Quantitative | S2: NA | T2: mammal | U2: species | V2: species | W2: na | X2: Local | Y2: degrees | Z2: 0.05 | AA2: FALSE
A3: 23515 | B3: =K3 -> Observational | C3: ["Marine", "Terrestrial"] | D3: ["Housing & urban area"] | E3: ["Residential & commercial development"] | F3: literature;rs | G3: literature;rs | H3: plantae | I3: indian ocean | J3: Malaysia | K3: Observational | L3: Marine;Terrestrial | M3: 1.1:DevResid | N3: level2 | O3: na | P3: 1 | Q3: Qualitative | R3: qualitative | S3: NA | T3: na | U3: phylum | V3: phylum | W3: mangrove | X3: Local | Y3: polygon | Z3: na | AA3: FALSE
A4: 23795 | B4: =K4 -> Observational | C4: ["Terrestrial"] | D4: ["Housing & urban area"] | E4: ["Residential & commercial development"] | F4: database | G4: literature;modelled | H4: plantae | I4: north america | J4: United States | K4: Observational | L4: Terrestrial | M4: 1.1:DevResid | N4: level2 | O4: US.CensusBureau2014 | P4: 1 | Q4: Qualitative | R4: Qualitative | S4: NA | T4: na | U4: species | V4: genus | W4: magnoliopsida | X4: Sub-national | Y4: km2 | Z4: 1 | AA4: FALSE
A5: 23832 | B5: =K5 -> Observational | C5: ["Terrestrial"] | D5: ["Housing & urban area"] | E5: ["Residential & commercial development"] | F5: rs | G5: database | H5: animalia | I5: asia | J5: na | K5: Observational | L5: Terrestrial | M5: 1.1:DevResid | N5: level2 | O5: NA | P5: 1 | Q5: Qualitative | R5: Qualitative | S5: IUCNredlist | T5: mammal | U5: species | V5: species | W5: na | X5: Continental | Y5: km2 | Z5: 21.16 | AA5: FALSE
A6: 23869 | B6: =K6 -> Observational | C6: ["Terrestrial"] | D6: ["Housing & urban area"] | E6: ["Residential & commercial development"] | F6: rs | G6: literature;rs | H6: plantae | I6: asia | J6: China | K6: Observational | L6: Terrestrial | M6: 1.1:DevResid | N6: level2 | O6: NA | P6: 1 | Q6: Qualitative | R6: Qualitative | S6: NA | T6: na | U6: kingdom | V6: kingdom | W6: habitat | X6: Sub-national | Y6: m | Z6: 30 | AA6: FALSE
A7: 23906 | B7: =K7 -> Observational | C7: ["Terrestrial"] | D7: ["Housing & urban area"] | E7: ["Residential & commercial development"] | F7: database | G7: protected_area | H7: other | I7: europe | J7: Italy | K7: Observational | L7: Terrestrial | M7: 1.1:DevResid | N7: level2 | O7: ItalianMilitaryGeographicalInstitute | P7: 1 | Q7: Qualitative | R7: Qualitative | S7: NA | T7: na | U7: other | V7: other | W7: na | X7: Sub-national | Y7: polygon | Z7: NA | AA7: FALSE
A8: 24418 | B8: =K8 -> Observational | C8: ["Terrestrial"] | D8: ["Housing & urban area"] | E8: ["Residential & commercial development"] | F8: database | G8: survey | H8: plantae | I8: north america | J8: United States | K8: Observational | L8: Terrestrial | M8: 1.1:DevResid | N8: level2 | O8: NA | P8: 1 | Q8: Quantitative | R8: Qualitative | S8: NA | T8: na | U8: kingdom | V8: kingdom | W8: vegetation | X8: Sub-national | Y8: NA | Z8: NA | AA8: FALSE
A9: 24565 | B9: =K9 -> Observational | C9: ["Terrestrial"] | D9: ["Housing & urban area"] | E9: ["Residential & commercial development"] | F9: literature;rs | G9: literature | H9: animalia | I9: asia | J9: China | K9: Observational | L9: Terrestrial | M9: 1.1:DevResid | N9: level2 | O9: na | P9: 1 | Q9: Qualitative | R9: qualitative | S9: NA | T9: bird | U9: genus | V9: genus | W9: na | X9: Local | Y9: polygon | Z9: na | AA9: FALSE
A10: 24667 | B10: =K10 -> Observational | C10: ["Terrestrial"] | D10: ["Housing & urban area"] | E10: ["Residential & commercial development"] | F10: database | G10: literature | H10: plantae | I10: europe | J10: Italy | K10: Observational | L10: Terrestrial | M10: 1.1:DevResid | N10: level2 | O10: NA | P10: 1 | Q10: Qualitative | R10: Qualitative | S10: NA | T10: na | U10: kingdom | V10: kingdom | W10: vegetation | X10: Sub-national | Y10: polygon | Z10: NA | AA10: FALSE
A11: 24748 | B11: =K11 -> Observational | C11: ["Terrestrial"] | D11: ["Housing & urban area"] | E11: ["Residential & commercial development"] | F11: database | G11: pchba;protected_area | H11: other | I11: na | J11: na | K11: Observational | L11: Terrestrial | M11: 1.1:DevResid | N11: level2 | O11: NA | P11: 1 | Q11: Quantitative | R11: Qualitative | S11: NA | T11: na | U11: other | V11: other | W11: na | X11: Global | Y11: polygon | Z11: NA | AA11: FALSE
A12: 24886 | B12: =K12 -> Observational | C12: ["Terrestrial"] | D12: ["Housing & urban area"] | E12: ["Residential & commercial development"] | F12: rs | G12: protected_area | H12: other | I12: africa | J12: Mozambique | K12: Observational | L12: Terrestrial | M12: 1.1:DevResid | N12: level2 | O12: NA | P12: 1 | Q12: Qualitative | R12: Qualitative | S12: NA | T12: na | U12: other | V12: other | W12: na | X12: Local | Y12: m | Z12: 60 | AA12: FALSE
A13: W26588 | B13: =K13 -> Observational | C13: ["Terrestrial"] | D13: ["Housing & urban area"] | E13: ["Residential & commercial development"] | F13: database | G13: pchba | H13: other | I13: na | J13: na | K13: Observational | L13: Terrestrial | M13: 1.1:DevResid | N13: level2 | O13: CCILandCover | P13: 1 | Q13: Quantitative | R13: Qualitative | S13: KBA | T13: na | U13: other | V13: other | W13: na | X13: Global | Y13: polygon | Z13: NA | AA13: FALSE
A14: 23155 | B14: =K14 -> Observational | C14: ["Terrestrial"] | D14: ["Housing & urban area", "Commercial & industrial areas"] | E14: ["Residential & Commercial Development"] | F14: modelled | G14: protected_area | H14: other | I14: europe | J14: Italy | K14: Observational | L14: Terrestrial | M14: 1.1:DevResid;1.2:DevComInd | N14: level1 | O14: NA | P14: 2 | Q14: Quantitative | R14: Qualitative | S14: NA | T14: na | U14: other | V14: other | W14: na | X14: National | Y14: polygon | Z14: na | AA14: FALSE
A15: 23938 | B15: =K15 -> Observational | C15: ["Terrestrial"] | D15: ["Housing & urban area", "Commercial & industrial areas", "Tourism & recreation areas", "Annual & perennial non-timber crops", "Wood & pulp plantations", "Livestock farming & ranching", "Roads & railroads"] | E15: ["Residential & Commercial Development", "Agriculture & Aquaculture", "Transportation & Service Corridors"] | F15: database;rs | G15: database | H15: animalia | I15: europe | J15: Italy | K15: Observational | L15: Terrestrial | M15: 1.1:DevResid;1.2:DevComInd;1.3:DevRnR;2.1:AgNTC;2.2:AgWood;2.3:AgLivestock;4.1:RoadRail | N15: level1 | O15: CorineLandCover | P15: 7 | Q15: Qualitative | R15: Quantitative | S15: NationalEcologicalNetwork | T15: mammal | U15: class | V15: class | W15: na | X15: Local | Y15: polygon | Z15: NA | AA15: FALSE
A16: 23071 | B16: =K16 -> Observational | C16: ["Terrestrial"] | D16: ["Housing & urban area", "Commercial & industrial areas", "Tourism & recreation areas", "Annual & perennial non-timber crops", "Livestock farming & ranching", "Roads & railroads", "Excess energy"] | E16: ["Residential & Commercial Development", "Agriculture & Aquaculture", "Transportation & Service Corridors", "Pollution"] | F16: pcm | G16: protected_area | H16: other | I16: na | J16: na | K16: Observational | L16: Terrestrial | M16: 1.1:DevResid;1.2:DevComInd;1.3:DevRnR;2.1:AgNTC;2.3:AgLivestock;4.1:RoadRail;9.6:PollEnergy | N16: cumulative | O16: HFI | P16: 7 | Q16: Quantitative | R16: Qualitative | S16: NaturalWorldHeritage | T16: na | U16: other | V16: other | W16: na | X16: Global | Y16: polygon | Z16: NA | AA16: FALSE
A17: 23399 | B17: =K17 -> Observational | C17: ["Terrestrial"] | D17: ["Housing & urban area", "Commercial & industrial areas", "Tourism & recreation areas", "Annual & perennial non-timber crops", "Livestock farming & ranching", "Roads & railroads", "Excess energy"] | E17: ["Residential & Commercial Development", "Agriculture & Aquaculture", "Transportation & Service Corridors", "Pollution"] | F17: database | G17: protected_area | H17: other | I17: asia | J17: China | K17: Observational | L17: Terrestrial | M17: 1.1:DevResid;1.2:DevComInd;1.3:DevRnR;2.1:AgNTC;2.3:AgLivestock;4.1:RoadRail;9.6:PollEnergy | N17: cumulative | O17: NA | P17: 7 | Q17: Quantitative | R17: Qualitative | S17: NA | T17: na | U17: other | V17: other | W17: na | X17: National | Y17: km2 | Z17: 1 | AA17: FALSE
A18: 23657 | B18: =K18 -> Observational | C18: ["Terrestrial"] | D18: ["Housing & urban area", "Commercial & industrial areas", "Tourism & recreation areas", "Annual & perennial non-timber crops", "Livestock farming & ranching", "Roads & railroads", "Excess energy"] | E18: ["Residential & Commercial Development", "Agriculture & Aquaculture", "Transportation & Service Corridors", "Pollution"] | F18: modelled | G18: rs | H18: plantae | I18: asia | J18: China | K18: Observational | L18: Terrestrial | M18: 1.1:DevResid;1.2:DevComInd;1.3:DevRnR;2.1:AgNTC;2.3:AgLivestock;4.1:RoadRail;9.6:PollEnergy | N18: cumulative | O18: HFI;resdc.cn | P18: 7 | Q18: Quantitative | R18: Qualitative | S18: NA | T18: na | U18: kingdom | V18: kingdom | W18: habitat | X18: Sub-national | Y18: km2 | Z18: 1 | AA18: FALSE
A19: 23726 | B19: =K19 -> Observational | C19: ["Terrestrial"] | D19: ["Housing & urban area", "Commercial & industrial areas", "Tourism & recreation areas", "Annual & perennial non-timber crops", "Livestock farming & ranching", "Roads & railroads", "Excess energy"] | E19: ["Residential & Commercial Development", "Agriculture & Aquaculture", "Transportation & Service Corridors", "Pollution"] | F19: pcm | G19: database | H19: animalia | I19: na | J19: na | K19: Observational | L19: Terrestrial | M19: 1.1:DevResid;1.2:DevComInd;1.3:DevRnR;2.1:AgNTC;2.3:AgLivestock;4.1:RoadRail;9.6:PollEnergy | N19: cumulative | O19: HFI | P19: 7 | Q19: Quantitative | R19: Qualitative | S19: IUCNredlist | T19: mammal | U19: class | V19: class | W19: na | X19: Global | Y19: km2 | Z19: 1 | AA19: FALSE
A20: 24108 | B20: =K20 -> Observational | C20: ["Terrestrial"] | D20: ["Housing & urban area", "Commercial & industrial areas", "Tourism & recreation areas", "Annual & perennial non-timber crops", "Livestock farming & ranching", "Roads & railroads", "Excess energy"] | E20: ["Residential & Commercial Development", "Agriculture & Aquaculture", "Transportation & Service Corridors", "Pollution"] | F20: pcm | G20: database | H20: animalia | I20: na | J20: na | K20: Observational | L20: Terrestrial | M20: 1.1:DevResid;1.2:DevComInd;1.3:DevRnR;2.1:AgNTC;2.3:AgLivestock;4.1:RoadRail;9.6:PollEnergy | N20: cumulative | O20: HFI | P20: 7 | Q20: Quantitative | R20: Quantitative | S20: GARD_GlobalAssessmentOfReptileDistributions | T20: reptile | U20: class | V20: class | W20: na | X20: Global | Y20: degrees | Z20: 1 | AA20: FALSE
A21: 25734 | B21: =K21 -> Observational | C21: ["Terrestrial"] | D21: ["Housing & urban area", "Commercial & industrial areas", "Tourism & recreation areas", "Annual & perennial non-timber crops", "Livestock farming & ranching", "Roads & railroads", "Excess energy"] | E21: ["Residential & Commercial Development", "Agriculture & Aquaculture", "Transportation & Service Corridors", "Pollution"] | F21: database | G21: protected_area | H21: other | I21: south america | J21: Ecuador | K21: Observational | L21: Terrestrial | M21: 1.1:DevResid;1.2:DevComInd;1.3:DevRnR;2.1:AgNTC;2.3:AgLivestock;4.1:RoadRail;9.6:PollEnergy | N21: cumulative | O21: Various | P21: 7 | Q21: Quantitative | R21: Qualitative | S21: NA | T21: na | U21: other | V21: other | W21: na | X21: Sub-national | Y21: m | Z21: 100 | AA21: FALSE
A22: 25830 | B22: =K22 -> Observational | C22: ["Terrestrial"] | D22: ["Housing & urban area", "Commercial & industrial areas", "Tourism & recreation areas", "Annual & perennial non-timber crops", "Livestock farming & ranching", "Roads & railroads", "Excess energy"] | E22: ["Residential & Commercial Development", "Agriculture & Aquaculture", "Transportation & Service Corridors", "Pollution"] | F22: pcm | G22: database;rs | H22: animalia | I22: na | J22: na | K22: Observational | L22: Terrestrial | M22: 1.1:DevResid;1.2:DevComInd;1.3:DevRnR;2.1:AgNTC;2.3:AgLivestock;4.1:RoadRail;9.6:PollEnergy | N22: cumulative | O22: HFI_Venter2016 | P22: 7 | Q22: Quantitative | R22: Qualitative | S22: MoveBank | T22: mammal | U22: class | V22: class | W22: na | X22: Global | Y22: km2 | Z22: 1 | AA22: FALSE
A23: 24314 | B23: =K23 -> Observational | C23: ["Terrestrial"] | D23: ["Housing & urban area", "Commercial & industrial areas", "Tourism & recreation areas", "Annual & perennial non-timber crops", "Livestock farming & ranching", "Roads & railroads", "Excess energy", "Excess energy"] | E23: ["Residential & Commercial Development", "Agriculture & Aquaculture", "Transportation & Service Corridors", "Pollution"] | F23: database;rs | G23: protected_area | H23: other | I23: north america | J23: United States | K23: Observational | L23: Terrestrial | M23: 1.1:DevResid;1.2:DevComInd;1.3:DevRnR;2.1:AgNTC;2.3:AgLivestock;4.1:RoadRail;9.6:PollEnergy;9.6:PollEnergy | N23: level2 | O23: DMSP-OLS | P23: 7 | Q23: Quantitative | R23: qualitative | S23: NA | T23: na | U23: other | V23: other | W23: na | X23: Sub-national | Y23: km2 | Z23: 1 | AA23: FALSE
A24: 23135 | B24: =K24 -> Observational | C24: ["Marine"] | D24: ["Housing & urban area", "Commercial & industrial areas", "Tourism & recreation areas", "Marine & freshwater aquaculture", "Oil & gas drilling", "Shipping lanes", "Fishing & harvesting aquatic resources", "Agricultural & forestry effluents", "Mining & quarrying", "Recreational activities"] | E24: ["Residential & Commercial Development", "Agriculture & Aquaculture", "Energy Production & Mining", "Transportation & Service Corridors", "Biological Resource Use", "Pollution", "Human Intrusions & Disturbance"] | F24: expert;modelled | G24: expert | H24: animalia;plantae | I24: north atlantic | J24: Belize | K24: Observational | L24: Marine | M24: 1.1:DevResid;1.2:DevComInd;1.3:DevRnR;2.4:Aqua;3.1:OilGas;4.3:ShipLane;5.4:UseAquatic;9.3:PollAgrFor;3.2:MinQuar;6.1:ActivRnR | N24: level2 | O24: NA | P24: 10 | Q24: Quantitative | R24: Qualitative | S24: NA | T24: invertebrates | U24: class | V24: domain | W24: mangrove;liliopsida | X24: National | Y24: m | Z24: 500 | AA24: FALSE
A25: 26127 | B25: =K25 -> Observational | C25: ["Marine"] | D25: ["Housing & urban area", "Commercial & industrial areas", "Habitat shifting & alteration", "Temperature extremes", "Oil & gas drilling", "Shipping lanes", "Fishing & harvesting aquatic resources", "Invasive non-native/alien species/diseases", "Industrial & military effluents", "Agricultural & forestry effluents", "Excess energy"] | E25: ["Residential & Commercial Development", "Climate Change & Severe Weather", "Energy Production & Mining", "Transportation & Service Corridors", "Biological Resource Use", "Invasive & Other Problematic Species, Genes & Diseases", "Pollution"] | F25: expert;literature;modelled | G25: expert;literature | H25: animalia | I25: na | J25: na | K25: Observational | L25: Marine | M25: 1.1:DevResid;1.2:DevComInd;11.1:CC_Habitat;11.3:CC_Temp;3.1:OilGas;4.3:ShipLane;5.4:UseAquatic;8.1:SDAlienInv;9.2:PollIndMil;9.3:PollAgrFor;9.6:PollEnergy | N25: level2 | O25: na | P25: 11 | Q25: Quantitative | R25: qualitative | S25: NA | T25: Fish | U25: genus | V25: genus | W25: na | X25: Global | Y25: km2 | Z25: 1 | AA25: FALSE
A26: 24842 | B26: =K26 -> Observational | C26: ["Terrestrial"] | D26: ["Housing & urban area", "Commercial & industrial areas", "Annual & perennial non-timber crops", "Wood & pulp plantations"] | E26: ["Residential & Commercial Development", "Agriculture & Aquaculture"] | F26: rs | G26: rs | H26: plantae | I26: asia | J26: India | K26: Observational | L26: Terrestrial | M26: 1.1:DevResid;1.2:DevComInd;2.1:AgNTC;2.2:AgWood | N26: level2 | O26: NA | P26: 4 | Q26: Qualitative | R26: Qualitative | S26: NA | T26: na | U26: kingdom | V26: kingdom | W26: forest;habitat | X26: Sub-national | Y26: NA | Z26: NA | AA26: FALSE
A27: 23125 | B27: =K27 -> Observational | C27: ["Terrestrial"] | D27: ["Housing & urban area", "Commercial & industrial areas", "Annual & perennial non-timber crops", "Livestock farming & ranching"] | E27: ["Residential & Commercial Development", "Agriculture & Aquaculture"] | F27: database | G27: modelled | H27: animalia;plantae | I27: europe | J27: na | K27: Observational | L27: Terrestrial | M27: 1.1:DevResid;1.2:DevComInd;2.1:AgNTC;2.3:AgLivestock | N27: level2 | O27: Eurostat2000 | P27: 3 | Q27: Quantitative | R27: Qualitative | S27: NA | T27: bird;mammal;reptile;amphibia | U27: class | V27: domain | W27: tracheophyta | X27: Continental | Y27: km2 | Z27: 50 | AA27: FALSE
A28: 25077 | B28: =K28 -> Observational | C28: ["Terrestrial"] | D28: ["Housing & urban area", "Commercial & industrial areas", "Annual & perennial non-timber crops", "Livestock farming & ranching", "Oil & gas drilling", "Mining & quarrying", "Roads & railroads", "Utility & service lines", "Dams & water management/use"] | E28: ["Residential & Commercial Development", "Agriculture & Aquaculture", "Energy Production & Mining", "Transportation & Service Corridors", "Natural System Modifications"] | F28: rs | G28: literature | H28: animalia | I28: north america | J28: Canada | K28: Observational | L28: Terrestrial | M28: 1.1:DevResid;1.2:DevComInd;2.1:AgNTC;2.3:AgLivestock;3.1:OilGas;3.2:MinQuar;4.1:RoadRail;4.2:UtilityLine;7.2:WaterSystem | N28: level2 | O28: na | P28: 10 | Q28: Qualitative | R28: qualitative | S28: CaribouScienceAssessmnet | T28: mammal | U28: species | V28: species | W28: na | X28: Sub-national | Y28: m | Z28: 30 | AA28: FALSE
A29: 23072 | B29: =K29 -> Observational | C29: ["Terrestrial"] | D29: ["Housing & urban area", "Commercial & industrial areas", "Annual & perennial non-timber crops", "Livestock farming & ranching", "Roads & railroads", "Utility & service lines", "Hunting & collecting terrestrial animals", "Gathering terrestrial plants", "Recreational activities", "Work & other activities", "Invasive non-native/alien species/diseases", "Domestic & urban waste water", "Agricultural & forestry effluents", "Garbage & solid waste", "Excess energy"] | E29: ["Residential & Commercial Development", "Agriculture & Aquaculture", "Transportation & Service Corridors", "Biological Resource Use", "Human Intrusions & Disturbance", "Invasive & Other Problematic Species, Genes & Diseases", "Pollution"] | F29: pcm | G29: database | H29: animalia | I29: na | J29: na | K29: Observational | L29: Terrestrial | M29: 1.1:DevResid;1.2:DevComInd;2.1:AgNTC;2.3:AgLivestock;4.1:RoadRail;4.2:UtilityLine;5.1:UseAnimals;5.2:UsePlant;6.1:ActivRnR;6.3:Other;8.1:SDAlienInv;9.1:PollDWW;9.3:PollAgrFor;9.4:PollGarbSW;9.6:PollEnergy | N29: cumulative | O29: HFI | P29: 15 | Q29: Quantitative | R29: Quantitative | S29: IUCN | T29: mammal;amphibia;bird | U29: phylum | V29: phylum | W29: na | X29: Global | Y29: km2 | Z29: 30 | AA29: FALSE
A30: 23477 | B30: =K30 -> Observational | C30: ["Terrestrial"] | D30: ["Housing & urban area", "Commercial & industrial areas", "Annual & perennial non-timber crops", "Livestock farming & ranching", "Dams & water management/use"] | E30: ["Residential & Commercial Development", "Agriculture & Aquaculture", "Natural System Modifications"] | F30: rs | G30: rs | H30: plantae | I30: south america | J30: Brazil | K30: Observational | L30: Terrestrial | M30: 1.1:DevResid;1.2:DevComInd;2.1:AgNTC;2.3:AgLivestock;7.2:WaterSystem | N30: level2 | O30: TerraClassInitiative_TC; Landsat | P30: 5 | Q30: Qualitative | R30: qualitative | S30: NA | T30: na | U30: kingdom | V30: kingdom | W30: forest | X30: Sub-national | Y30: km2 | Z30: 100 | AA30: FALSE
A31: 24050 | B31: =K31 -> Observational | C31: ["Marine", "Terrestrial"] | D31: ["Housing & urban area", "Commercial & industrial areas", "Annual & perennial non-timber crops", "Marine & freshwater aquaculture", "Oil & gas drilling", "Mining & quarrying"] | E31: ["Residential & Commercial Development", "Agriculture & Aquaculture", "Energy Production & Mining"] | F31: rs | G31: rs | H31: plantae | I31: na | J31: na | K31: Observational | L31: Marine;Terrestrial | M31: 1.1:DevResid;1.2:DevComInd;2.1:AgNTC;2.4:Aqua;3.1:OilGas;3.2:MinQuar | N31: level1 | O31: na | P31: 6 | Q31: Qualitative | R31: qualitative | S31: NA | T31: na | U31: phylum | V31: phylum | W31: mangrove | X31: Global | Y31: m | Z31: 30 | AA31: FALSE
A32: 24862 | B32: =K32 -> Observational | C32: ["Freshwater", "Marine", "Terrestrial"] | D32: ["Housing & urban area", "Commercial & industrial areas", "Wood & pulp plantations", "Roads & railroads"] | E32: ["Residential & Commercial Development", "Agriculture & Aquaculture", "Transportation & Service Corridors", "Pollution"] | F32: database | G32: database | H32: animalia | I32: na | J32: na | K32: Observational | L32: Freshwater;Marine;Terrestrial | M32: 1.1:DevResid;1.2:DevComInd;2.2:AgWood;2.5:AgUncpec;4.1:RoadRail;9.7:PollUnspec | N32: cumulative | O32: IUCN;EORA | P32: 6 | Q32: Quantitative | R32: quantitative | S32: IUCNredlist | T32: animal | U32: kingdom | V32: kingdom | W32: na | X32: Global | Y32: polygon | Z32: na | AA32: TRUE
A33: 26092 | B33: =K33 -> Observational | C33: ["Terrestrial"] | D33: ["Housing & urban area", "Commercial & industrial areas", "Livestock farming & ranching", "Mining & quarrying", "Roads & railroads", "Excess energy"] | E33: ["Residential & Commercial Development", "Agriculture & Aquaculture", "Energy Production & Mining", "Transportation & Service Corridors", "Pollution"] | F33: database;modelled | G33: pchba | H33: other | I33: asia | J33: China | K33: Observational | L33: Terrestrial | M33: 1.1:DevResid;1.2:DevComInd;2.3:AgLivestock;3.2:MinQuar;4.1:RoadRail;9.6:PollEnergy | N33: cumulative | O33: Various | P33: 6 | Q33: Quantitative | R33: qualitative | S33: NA | T33: na | U33: other | V33: other | W33: na | X33: Sub-national | Y33: km2 | Z33: 1 | AA33: FALSE
A34: 25028 | B34: =K34 -> Observational | C34: ["Freshwater", "Marine", "Terrestrial"] | D34: ["Housing & urban area", "Commercial & industrial areas", "Livestock farming & ranching", "Gathering terrestrial plants"] | E34: ["Residential & Commercial Development", "Agriculture & Aquaculture", "Biological Resource Use", "Pollution"] | F34: survey | G34: survey | H34: animalia | I34: asia | J34: Turkey | K34: Observational | L34: Freshwater;Marine;Terrestrial | M34: 1.1:DevResid;1.2:DevComInd;2.3:AgLivestock;5.2:UsePlant;9.7:PollUnspec | N34: level2 | O34: na | P34: 5 | Q34: Quantitative | R34: quantitative | S34: NA | T34: bird | U34: class | V34: class | W34: na | X34: Local | Y34: km2 | Z34: 1 | AA34: TRUE
A35: 24766 | B35: =K35 -> Observational | C35: ["Freshwater", "Terrestrial"] | D35: ["Housing & urban area", "Commercial & industrial areas", "Oil & gas drilling", "Mining & quarrying", "Roads & railroads", "Utility & service lines", "Dams & water management/use"] | E35: ["Residential & Commercial Development", "Agriculture & Aquaculture", "Energy Production & Mining", "Transportation & Service Corridors", "Natural System Modifications"] | F35: literature;rs | G35: database;expert;literature;rs | H35: animalia | I35: asia | J35: Iran | K35: Observational | L35: Freshwater;Terrestrial | M35: 1.1:DevResid;1.2:DevComInd;2.5:AgUncpec;3.1:OilGas;3.2:MinQuar;4.1:RoadRail;4.2:UtilityLine;7.2:WaterSystem | N35: level2 | O35: GUANSAR_2013 | P35: 8 | Q35: Quantitative | R35: quantitative | S35: NA | T35: bird;mammal | U35: phylum | V35: phylum | W35: na | X35: Sub-national | Y35: m | Z35: 30 | AA35: TRUE
A36: 23988 | B36: =K36 -> Observational | C36: ["Terrestrial"] | D36: ["Housing & urban area", "Commercial & industrial areas", "Renewable energy", "Roads & railroads", "Utility & service lines", "Hunting & collecting terrestrial animals", "Fishing & harvesting aquatic resources", "Fire & fire suppression", "Dams & water management/use", "Garbage & solid waste"] | E36: ["Residential & Commercial Development", "Agriculture & Aquaculture", "Energy Production & Mining", "Transportation & Service Corridors", "Biological Resource Use", "Natural System Modifications", "Pollution"] | F36: database | G36: database | H36: animalia | I36: europe | J36: Portugal | K36: Observational | L36: Terrestrial | M36: 1.1:DevResid;1.2:DevComInd;2.5:AgUncpec;3.3:Renew;4.1:RoadRail;4.2:UtilityLine;5.1:UseAnimals;5.4:UseAquatic;7.1:FireSystem;7.2:WaterSystem;9.4:PollGarbSW | N36: level2 | O36: Wildlife Rehabilitation Centre | P36: 11 | Q36: Quantitative | R36: quantitative | S36: NA | T36: bird | U36: class | V36: class | W36: na | X36: Sub-national | Y36: polygon | Z36: na | AA36: TRUE
A37: 24222 | B37: =K37 -> Observational | C37: ["Freshwater", "Terrestrial"] | D37: ["Housing & urban area", "Commercial & industrial areas", "Roads & railroads", "Mining & quarrying", "Utility & service lines"] | E37: ["Residential & Commercial Development", "Agriculture & Aquaculture", "Transportation & Service Corridors", "Energy Production & Mining"] | F37: database | G37: protected_area | H37: other | I37: north america | J37: United States | K37: Observational | L37: Freshwater;Terrestrial | M37: 1.1:DevResid;1.2:DevComInd;2.5:AgUncpec;4.1:RoadRail;3.2:MinQuar;4.2:UtilityLine | N37: level2 | O37: Various | P37: 6 | Q37: Qualitative | R37: Qualitative | S37: NA | T37: na | U37: other | V37: other | W37: na | X37: Sub-national | Y37: m | Z37: 30 | AA37: TRUE
A38: 24150 | B38: =K38 -> Observational | C38: ["Terrestrial"] | D38: ["Housing & urban area", "Commercial & industrial areas", "Oil & gas drilling", "Tourism & recreation areas", "Shipping lanes"] | E38: ["Residential & Commercial Development", "Energy Production & Mining", "Transportation & Service Corridors", "Agriculture & Aquaculture"] | F38: modelled;rs | G38: database | H38: animalia;plantae | I38: africa;asia;europe | J38: France;Italy;Lebanon;Tunisia | K38: Observational | L38: Terrestrial | M38: 1.1:DevResid;1.2:DevComInd;3.1:OilGas;1.3:DevRnR;4.3:ShipLane;2.5:AgUncpec | N38: cumulative | O38: NA | P38: 6 | Q38: Quantitative | R38: Quantitative | S38: NA | T38: animal | U38: domain | V38: domain | W38: plant | X38: Local | Y38: m | Z38: 15 | AA38: TRUE
A39: 24790 | B39: =K39 -> Observational | C39: ["Marine"] | D39: ["Housing & urban area", "Commercial & industrial areas", "Oil & gas drilling", "Shipping lanes", "Fishing & harvesting aquatic resources", "Invasive non-native/alien species/diseases", "Agricultural & forestry effluents", "Industrial & military effluents", "Air-borne pollutants", "Habitat shifting & alteration", "Domestic & urban waste water", "Excess energy"] | E39: ["Residential & Commercial Development", "Energy Production & Mining", "Transportation & Service Corridors", "Biological Resource Use", "Invasive & Other Problematic Species, Genes & Diseases", "Pollution", "Climate Change & Severe Weather"] | F39: modelled | G39: modelled | H39: animalia;plantae | I39: mediterranean | J39: Bosnia and Herzegovina; France; Italy; Greece; Croatia; Macedonia; Monaco;Montenegro; Spain;Slovenia;San Marino;Albania;Malta;Cyprus;Turkey;Morocco;Algeria;Tunisia;Libya;Egypt;Israel;Syria;Lebanon;Georgia;Turkey;Bulgaria;Ukraine;Romania;Russia | K39: Observational | L39: Marine | M39: 1.1:DevResid;1.2:DevComInd;3.1:OilGas;4.3:ShipLane;5.4:UseAquatic;8.1:SDAlienInv;9.3:PollAgrFor;9.2:PollIndMil;9.5:PollAir;11.1:CC_Habitat;9.1:PollDWW;9.6:PollEnergy | N39: cumulative | O39: NA | P39: 12 | Q39: Quantitative | R39: Quantitative | S39: NA | T39: fish | U39: domain | V39: domain | W39: habitat | X39: Multi-national | Y39: km2 | Z39: 1 | AA39: FALSE
A40: 24962 | B40: =K40 -> Observational | C40: ["Terrestrial"] | D40: ["Housing & urban area", "Commercial & industrial areas", "Roads & railroads", "Recreational activities"] | E40: ["Residential & Commercial Development", "Transportation & Service Corridors", "Human Intrusions & Disturbance"] | F40: database;survey | G40: survey | H40: animalia | I40: north america | J40: United States | K40: Observational | L40: Terrestrial | M40: 1.1:DevResid;1.2:DevComInd;4.1:RoadRail;6.1:ActivRnR | N40: level2 | O40: NA | P40: 4 | Q40: Quantitative | R40: Qualitative | S40: NA | T40: mammal | U40: order | V40: order | W40: na | X40: Local | Y40: km2 | Z40: 1 | AA40: FALSE
A41: 24269 | B41: =K41 -> Observational | C41: ["Marine", "Terrestrial"] | D41: ["Housing & urban area", "Tourism & recreation areas", "Annual & perennial non-timber crops", "Marine & freshwater aquaculture", "Habitat shifting & alteration"] | E41: ["Residential & Commercial Development", "Agriculture & Aquaculture", "Climate Change & Severe Weather"] | F41: rs | G41: rs | H41: plantae | I41: asia | J41: Malaysia | K41: Observational | L41: Marine;Terrestrial | M41: 1.1:DevResid;1.3:DevRnR;2.1:AgNTC;2.4:Aqua;11.1:CC_Habitat | N41: level2 | O41: NA | P41: 5 | Q41: Qualitative | R41: Qualitative | S41: NA | T41: na | U41: species | V41: phylum | W41: mangrove | X41: Local | Y41: NA | Z41: NA | AA41: FALSE
A42: 25865 | B42: =K42 -> Observational | C42: ["Terrestrial"] | D42: ["Housing & urban area", "Tourism & recreation areas", "Wood & pulp plantations", "Livestock farming & ranching", "Roads & railroads", "Hunting & collecting terrestrial animals", "Gathering terrestrial plants", "Logging & wood harvesting", "Fishing & harvesting aquatic resources", "Recreational activities"] | E42: ["Residential & Commercial Development", "Agriculture & Aquaculture", "Transportation & Service Corridors", "Biological Resource Use", "Human Intrusions & Disturbance"] | F42: expert;survey | G42: survey | H42: animalia;plantae | I42: south america | J42: Suriname | K42: Observational | L42: Terrestrial | M42: 1.1:DevResid;1.3:DevRnR;2.2:AgWood;2.3:AgLivestock;2.5:AgUncpec;4.1:RoadRail;5.1:UseAnimals;5.2:UsePlant;5.3:UseWood;5.4:UseAquatic;6.1:ActivRnR | N42: level2 | O42: na | P42: 11 | Q42: Qualitative | R42: qualitative | S42: NA | T42: bird;mammal;reptile | U42: species | V42: domain | W42: forest;plant;liliopsida | X42: Local | Y42: polygon | Z42: na | AA42: TRUE
A43: 23841 | B43: =K43 -> Observational | C43: ["Terrestrial"] | D43: ["Housing & urban area", "Tourism & recreation areas", "Roads & railroads", "Annual & perennial non-timber crops"] | E43: ["Residential & Commercial Development", "Transportation & Service Corridors", "Agriculture & Aquaculture"] | F43: rs | G43: rs | H43: plantae | I43: asia | J43: Philippines | K43: Observational | L43: Terrestrial | M43: 1.1:DevResid;1.3:DevRnR;4.1:RoadRail;2.1:AgNTC | N43: level2 | O43: NA | P43: 4 | Q43: Qualitative | R43: Qualitative | S43: NA | T43: na | U43: kingdom | V43: kingdom | W43: forest | X43: Local | Y43: m | Z43: 30 | AA43: FALSE
A44: 25496 | B44: Review | C44: ["Marine"] | D44: ["Housing & urban area", "Tourism & recreation areas", "Recreational activities", "Oil & gas drilling", "Mining & quarrying", "Other ecosystem modifications", "Invasive non-native/alien species/diseases", "Hunting & collecting terrestrial animals", "Gathering terrestrial plants", "Industrial & military effluents"] | E44: ["Residential & Commercial Development", "Human Intrusions & Disturbance", "Energy Production & Mining", "Natural System Modifications", "Invasive & Other Problematic Species, Genes & Diseases", "Biological Resource Use", "Pollution"] | F44: literature | G44: literature | H44: animalia | I44: na | J44: na | K44: S_Review | L44: Marine | M44: 1.1:DevResid;1.3:DevRnR;6.1:ActivRnR;3.1:OilGas;3.2:MinQuar;7.3:OtherSystem;8.1:SDAlienInv;5.1:UseAnimals;5.2:UsePlant;9.2:PollIndMil | N44: cumulative | O44: NA | P44: 10 | Q44: Qualitative | R44: Qualitative | S44: NA | T44: invertebrates | U44: species | V44: species | W44: na | X44: Global | Y44: polygon | Z44: NA | AA44: FALSE
A45: 25127 | B45: =K45 -> Observational | C45: ["Terrestrial"] | D45: ["Housing & urban area", "Tourism & recreation areas", "Recreational activities", "Work & other activities"] | E45: ["Residential & Commercial Development", "Human Intrusions & Disturbance"] | F45: database;modelled | G45: pchba | H45: other | I45: antarctica | J45: Antarctica | K45: Observational | L45: Terrestrial | M45: 1.1:DevResid;1.3:DevRnR;6.1:ActivRnR;6.3:Other | N45: cumulative | O45: Various | P45: 4 | Q45: Quantitative | R45: Qualitative | S45: ImportantBirdAreas | T45: na | U45: other | V45: other | W45: na | X45: National | Y45: km2 | Z45: 2500 | AA45: FALSE
A46: 25877 | B46: =K46 -> Observational | C46: ["Terrestrial"] | D46: ["Housing & urban area", "Livestock farming & ranching", "Annual & perennial non-timber crops", "Roads & railroads"] | E46: ["Residential & Commercial Development", "Agriculture & Aquaculture", "Transportation & Service Corridors"] | F46: database;modelled | G46: protected_area | H46: other | I46: africa | J46: Botswana | K46: Observational | L46: Terrestrial | M46: 1.1:DevResid;1.4:DevUnspec;2.3:AgLivestock;2.1:AgNTC;4.1:RoadRail | N46: cumulative | O46: Various | P46: 5 | Q46: Quantitative | R46: Qualitative | S46: NA | T46: na | U46: other | V46: other | W46: na | X46: Local | Y46: NA | Z46: NA | AA46: TRUE
A47: 24229 | B47: =K47 -> Observational | C47: ["Marine"] | D47: ["Housing & urban area", "Marine & freshwater aquaculture", "Fishing & harvesting aquatic resources", "Recreational activities", "Domestic & urban waste water", "Industrial & military effluents"] | E47: ["Residential & Commercial Development", "Agriculture & Aquaculture", "Biological Resource Use", "Human Intrusions & Disturbance", "Pollution"] | F47: literature;modelled | G47: database;literature | H47: plantae | I47: mediterranean | J47: France | K47: Observational | L47: Marine | M47: 1.1:DevResid;1.4:DevUnspec;2.4:Aqua;2.5:AgUncpec;5.4:UseAquatic;6.1:ActivRnR;9.1:PollDWW;9.2:PollIndMil | N47: level2 | O47: Holon et al 2015_other | P47: 8 | Q47: Qualitative | R47: qualitative | S47: medtrix.fr; Holon et al 2015 | T47: na | U47: species | V47: species | W47: liliopsida | X47: Multi-national | Y47: m | Z47: 50 | AA47: TRUE
A48: 24227 | B48: =K48 -> Observational | C48: ["Marine"] | D48: ["Housing & urban area", "Marine & freshwater aquaculture", "Fishing & harvesting aquatic resources", "Industrial & military effluents", "Recreational activities", "Domestic & urban waste water"] | E48: ["Residential & Commercial Development", "Agriculture & Aquaculture", "Biological Resource Use", "Pollution", "Human Intrusions & Disturbance"] | F48: modelled | G48: literature | H48: animalia;plantae | I48: mediterranean | J48: France | K48: Observational | L48: Marine | M48: 1.1:DevResid;1.4:DevUnspec;2.5:AgUncpec;2.4:Aqua;5.4:UseAquatic;9.2:PollIndMil;6.1:ActivRnR;9.1:PollDWW | N48: cumulative | O48: NA | P48: 8 | Q48: Quantitative | R48: Qualitative | S48: NA | T48: ecosystem | U48: domain | V48: domain | W48: habitat | X48: Sub-national | Y48: m | Z48: 20 | AA48: TRUE
A49: 25413 | B49: =K49 -> Observational | C49: ["Freshwater", "Terrestrial"] | D49: ["Housing & urban area", "Roads & railroads", "Excess energy"] | E49: ["Residential & Commercial Development", "Agriculture & Aquaculture", "Transportation & Service Corridors", "Pollution"] | F49: pcm | G49: database;literature | H49: animalia | I49: south america | J49: Colombia | K49: Observational | L49: Freshwater;Terrestrial | M49: 1.1:DevResid;1.4:DevUnspec;2.5:AgUncpec;4.1:RoadRail;9.6:PollEnergy | N49: cumulative | O49: GlobalHumanFootprint_WCS-CIESIN_2005 | P49: 5 | Q49: Quantitative | R49: quantitative | S49: NA | T49: amphibia | U49: class | V49: class | W49: na | X49: National | Y49: degrees | Z49: 0.5 | AA49: TRUE
A50: 23405 | B50: =K50 -> Observational | C50: ["Terrestrial"] | D50: ["Housing & urban area", "Roads & railroads"] | E50: ["Transportation & Service Corridors", "Residential & commercial development"] | F50: modelled | G50: survey | H50: animalia | I50: north america | J50: United States | K50: Observational | L50: Terrestrial | M50: 1.1:DevResid;1.4:DevUnspec;4.1:RoadRail | N50: level2 | O50: na | P50: 2 | Q50: Quantitative | R50: qualitative | S50: NA | T50: mammal | U50: species | V50: species | W50: na | X50: Sub-national | Y50: m | Z50: 100 | AA50: TRUE
A51: 25821 | B51: =K51 -> Observational | C51: ["Freshwater"] | D51: ["Housing & urban area", "Mining & quarrying", "Dams & water management/use", "Annual & perennial non-timber crops"] | E51: ["Residential & Commercial Development", "Pollution", "Energy Production & Mining", "Natural System Modifications", "Agriculture & Aquaculture"] | F51: pcm | G51: literature | H51: animalia | I51: north america | J51: United States | K51: Observational | L51: Freshwater | M51: 1.1:DevResid;1.4:DevUnspec;9.7:PollUnspec;3.2:MinQuar;7.2:WaterSystem;2.1:AgNTC | N51: cumulative | O51: NFHAP_Cumulative disturbance index | P51: 6 | Q51: Qualitative | R51: Quantitative | S51: NA | T51: fish | U51: phylum | V51: phylum | W51: na | X51: Sub-national | Y51: polygon | Z51: NA | AA51: TRUE
A52: 25846 | B52: =K52 -> Observational | C52: ["Terrestrial"] | D52: ["Housing & urban area", "Droughts", "Temperature extremes", "Mining & quarrying", "Roads & railroads", "Utility & service lines", "Recreational activities", "Dams & water management/use", "Invasive non-native/alien species/diseases", "Domestic & urban waste water", "Industrial & military effluents", "Agricultural & forestry effluents", "Garbage & solid waste", "Excess energy"] | E52: ["Climate Change & Severe Weather", "Energy Production & Mining", "Transportation & Service Corridors", "Human Intrusions & Disturbance", "Natural System Modifications", "Invasive & Other Problematic Species, Genes & Diseases", "Pollution"] | F52: database;expert;modelled | G52: expert;literature | H52: animalia | I52: north america | J52: United States | K52: Observational | L52: Terrestrial | M52: 1.1:DevResid;11.2:CC_Drought;11.3:CC_Temp;3.2:MinQuar;4.1:RoadRail;4.2:UtilityLine;6.1:ActivRnR;7.2:WaterSystem;8.1:SDAlienInv;9.1:PollDWW;9.2:PollIndMil;9.3:PollAgrFor;9.4:PollGarbSW;9.6:PollEnergy | N52: cumulative | O52: Myers2000 | P52: 14 | Q52: Quantitative | R52: qualitative | S52: NA | T52: bird;fish;invertebrates;mammal;invertebrates;reptile | U52: kingdom | V52: kingdom | W52: na | X52: Sub-national | Y52: m | Z52: m | AA52: FALSE
A53: 24500 | B53: =K53 -> Observational | C53: ["Freshwater", "Marine", "Terrestrial"] | D53: ["Housing & urban area", "Other impacts", "Invasive non-native/alien species/diseases"] | E53: ["Climate Change & Severe Weather", "Agriculture & Aquaculture", "Energy Production & Mining", "Transportation & Service Corridors", "Biological Resource Use", "Invasive & Other Problematic Species, Genes & Diseases", "Pollution"] | F53: database | G53: database | H53: animalia;plantae | I53: na | J53: na | K53: Observational | L53: Freshwater;Marine;Terrestrial | M53: 1.1:DevResid;11.5:CC_other;2.5:AgUncpec;3.4:EnergUnspec;4.5.UnspecLine;5.5:UseUnspec;8.1:SDAlienInv;9.7:PollUnspec | N53: level1 | O53: IUCNredlist | P53: 8 | Q53: Qualitative | R53: qualitative | S53: IUCN | T53: amphibia;invertebrates;bird;fish;invertebrates;mammal;reptile | U53: domain | V53: domain | W53: plant | X53: Global | Y53: polygon | Z53: na | AA53: TRUE
A54: 25230 | B54: =K54 -> Observational | C54: ["Freshwater", "Terrestrial"] | D54: ["Housing & urban area", "Annual & perennial non-timber crops"] | E54: ["Agriculture & Aquaculture"] | F54: rs | G54: pchba | H54: other | I54: africa | J54: Malawi | K54: Observational | L54: Freshwater;Terrestrial | M54: 1.1:DevResid;2.1:AgNTC | N54: level2 | O54: NA | P54: 2 | Q54: Qualitative | R54: Qualitative | S54: RAMSAR | T54: na | U54: other | V54: other | W54: na | X54: Local | Y54: polygon | Z54: NA | AA54: FALSE
A55: 25560 | B55: =K55 -> Observational | C55: ["Terrestrial"] | D55: ["Housing & urban area", "Annual & perennial non-timber crops"] | E55: ["Agriculture & Aquaculture"] | F55: rs | G55: modelled;survey | H55: animalia | I55: asia | J55: Nepal | K55: Observational | L55: Terrestrial | M55: 1.1:DevResid;2.1:AgNTC | N55: level2 | O55: NA | P55: 2 | Q55: Qualitative | R55: Qualitative | S55: NA | T55: mammal | U55: species | V55: species | W55: na | X55: National | Y55: polygon | Z55: NA | AA55: FALSE
A56: 25511 | B56: =K56 -> Observational | C56: ["Terrestrial"] | D56: ["Housing & urban area", "Annual & perennial non-timber crops", "Wood & pulp plantations"] | E56: ["Agriculture & Aquaculture"] | F56: rs | G56: rs | H56: plantae | I56: africa | J56: Kenya | K56: Observational | L56: Terrestrial | M56: 1.1:DevResid;2.1:AgNTC;2.2:AgWood | N56: level2 | O56: NA | P56: 3 | Q56: Qualitative | R56: Qualitative | S56: NA | T56: na | U56: kingdom | V56: kingdom | W56: forest;vegetation | X56: Local | Y56: NA | Z56: NA | AA56: FALSE
A57: 23714 | B57: =K57 -> Observational | C57: ["Freshwater", "Terrestrial"] | D57: ["Housing & urban area", "Annual & perennial non-timber crops", "Wood & pulp plantations", "Livestock farming & ranching"] | E57: ["Agriculture & Aquaculture"] | F57: rs | G57: rs | H57: plantae | I57: africa | J57: Ethiopia | K57: Observational | L57: Freshwater;Terrestrial | M57: 1.1:DevResid;2.1:AgNTC;2.2:AgWood;2.3:AgLivestock | N57: level2 | O57: na | P57: 4 | Q57: Qualitative | R57: qualitative | S57: NA | T57: na | U57: kingdom | V57: kingdom | W57: forest | X57: Local | Y57: m | Z57: 57 | AA57: FALSE
A58: 23845 | B58: =K58 -> Observational | C58: ["Terrestrial"] | D58: ["Housing & urban area", "Annual & perennial non-timber crops", "Wood & pulp plantations", "Livestock farming & ranching", "Mining & quarrying", "Roads & railroads"] | E58: ["Agriculture & Aquaculture", "Energy Production & Mining", "Transportation & Service Corridors"] | F58: database;literature;modelled | G58: database;modelled | H58: animalia | I58: south america | J58: Colombia | K58: Observational | L58: Terrestrial | M58: 1.1:DevResid;2.1:AgNTC;2.2:AgWood;2.3:AgLivestock;3.2:MinQuar;4.1:RoadRail | N58: cumulative | O58: IGAC; DANE | P58: 6 | Q58: Quantitative | R58: quantitative | S58: NatureServe_2009 | T58: amphibia;mammal | U58: phylum | V58: phylum | W58: na | X58: National | Y58: km2 | Z58: 1 | AA58: FALSE
A59: 23838 | B59: =K59 -> Observational | C59: ["Freshwater"] | D59: ["Housing & urban area", "Annual & perennial non-timber crops", "Wood & pulp plantations", "Livestock farming & ranching", "Roads & railroads"] | E59: ["Agriculture & Aquaculture", "Transportation & Service Corridors"] | F59: literature | G59: literature;modelled | H59: animalia | I59: north america | J59: Mexico;Belize;Honduras;Guatemala | K59: Observational | L59: Freshwater | M59: 1.1:DevResid;2.1:AgNTC;2.2:AgWood;2.3:AgLivestock;4.1:RoadRail | N59: cumulative | O59: NA | P59: 5 | Q59: Quantitative | R59: Qualitative | S59: NA | T59: fish | U59: phylum | V59: phylum | W59: na | X59: Multi-national | Y59: polygon | Z59: NA | AA59: FALSE
A60: 23982 | B60: =K60 -> Observational | C60: ["Terrestrial"] | D60: ["Housing & urban area", "Annual & perennial non-timber crops", "Wood & pulp plantations", "Livestock farming & ranching", "Hunting & collecting terrestrial animals"] | E60: ["Agriculture & Aquaculture", "Biological Resource Use"] | F60: database;modelled | G60: database | H60: animalia | I60: na | J60: na | K60: Observational | L60: Terrestrial | M60: 1.1:DevResid;2.1:AgNTC;2.2:AgWood;2.3:AgLivestock;5.1:UseAnimals | N60: level2 | O60: ESA_2017 | P60: 5 | Q60: Qualitative | R60: Qualitative | S60: IUCNredlist | T60: mammal | U60: species | V60: class | W60: na | X60: Global | Y60: arc_seconds | Z60: 30 | AA60: FALSE
A61: 24460 | B61: =K61 -> Observational | C61: ["Terrestrial"] | D61: ["Housing & urban area", "Annual & perennial non-timber crops", "Wood & pulp plantations", "Invasive non-native/alien species/diseases"] | E61: ["Agriculture & Aquaculture", "Invasive & Other Problematic Species, Genes & Diseases"] | F61: modelled | G61: modelled | H61: plantae | I61: africa | J61: Reunion | K61: Observational | L61: Terrestrial | M61: 1.1:DevResid;2.1:AgNTC;2.2:AgWood;8.1:SDAlienInv | N61: level2 | O61: NA | P61: 4 | Q61: Qualitative | R61: Qualitative | S61: NA | T61: na | U61: kingdom | V61: kingdom | W61: vegetation | X61: Local | Y61: m | Z61: 25 | AA61: FALSE
A62: 23117 | B62: =K62 -> Observational | C62: ["Terrestrial"] | D62: ["Housing & urban area", "Annual & perennial non-timber crops", "Livestock farming & ranching"] | E62: ["Agriculture & Aquaculture"] | F62: rs;survey | G62: survey | H62: animalia | I62: asia | J62: Iran | K62: Observational | L62: Terrestrial | M62: 1.1:DevResid;2.1:AgNTC;2.3:AgLivestock | N62: level1 | O62: NA | P62: 3 | Q62: Qualitative | R62: Qualitative | S62: NA | T62: mammal | U62: species | V62: species | W62: na | X62: Local | Y62: polygon | Z62: NA | AA62: FALSE
A63: 23190 | B63: =K63 -> Observational | C63: ["Terrestrial"] | D63: ["Housing & urban area", "Annual & perennial non-timber crops", "Livestock farming & ranching"] | E63: ["Agriculture & Aquaculture"] | F63: rs | G63: survey | H63: animalia | I63: north america | J63: United States | K63: Observational | L63: Terrestrial | M63: 1.1:DevResid;2.1:AgNTC;2.3:AgLivestock | N63: level1 | O63: na | P63: 2 | Q63: Qualitative | R63: qualitative | S63: NA | T63: mammal | U63: species | V63: species | W63: na | X63: Sub-national | Y63: km2 | Z63: 25 | AA63: FALSE
A64: 25642 | B64: =K64 -> Observational | C64: ["Terrestrial"] | D64: ["Housing & urban area", "Annual & perennial non-timber crops", "Livestock farming & ranching"] | E64: ["Agriculture & Aquaculture"] | F64: survey | G64: survey | H64: animalia | I64: africa | J64: Botswana | K64: Observational | L64: Terrestrial | M64: 1.1:DevResid;2.1:AgNTC;2.3:AgLivestock | N64: level2 | O64: Census | P64: 3 | Q64: Qualitative | R64: quantitative | S64: NA | T64: mammal | U64: species | V64: species | W64: na | X64: Local | Y64: polygon | Z64: na | AA64: FALSE
A65: 25671 | B65: =K65 -> Observational | C65: ["Freshwater"] | D65: ["Housing & urban area", "Annual & perennial non-timber crops", "Livestock farming & ranching"] | E65: ["Agriculture & Aquaculture"] | F65: modelled;rs | G65: modelled | H65: animalia | I65: south america | J65: Brazil;Uruguay | K65: Observational | L65: Freshwater | M65: 1.1:DevResid;2.1:AgNTC;2.3:AgLivestock | N65: level2 | O65: NA | P65: 3 | Q65: Qualitative | R65: Quantitative | S65: NA | T65: bird | U65: class | V65: class | W65: na | X65: Multi-national | Y65: NA | Z65: NA | AA65: FALSE
A66: 23509 | B66: =K66 -> Observational | C66: ["Terrestrial"] | D66: ["Housing & urban area", "Annual & perennial non-timber crops", "Livestock farming & ranching", "Wood & pulp plantations"] | E66: ["Agriculture & Aquaculture"] | F66: database | G66: database | H66: animalia | I66: na | J66: na | K66: Observational | L66: Terrestrial | M66: 1.1:DevResid;2.1:AgNTC;2.3:AgLivestock;2.2:AgWood | N66: cumulative | O66: IUCNredlist | P66: 4 | Q66: Qualitative | R66: Quantitative | S66: IUCNredlist | T66: mammal;bird;amphibia | U66: phylum | V66: phylum | W66: na | X66: Global | Y66: polygon | Z66: NA | AA66: FALSE
A67: 26104 | B67: =K67 -> Observational | C67: ["Terrestrial"] | D67: ["Housing & urban area", "Annual & perennial non-timber crops", "Livestock farming & ranching", "Roads & railroads", "Hunting & collecting terrestrial animals"] | E67: ["Agriculture & Aquaculture", "Transportation & Service Corridors", "Biological Resource Use"] | F67: literature | G67: database;literature | H67: animalia;plantae | I67: africa | J67: Equatorial Guinea (Bioko) | K67: Observational | L67: Terrestrial | M67: 1.1:DevResid;2.1:AgNTC;2.3:AgLivestock;4.1:RoadRail;5.1:UseAnimals | N67: level2 | O67: na | P67: 5 | Q67: Qualitative | R67: qualitative | S67: NA | T67: mammal;bird | U67: domain | V67: domain | W67: liliopsida;magnoliopsida;polypodiopsida | X67: Local | Y67: km2 | Z67: 1 | AA67: FALSE
A68: 23237 | B68: =K68 -> Observational | C68: ["Terrestrial"] | D68: ["Housing & urban area", "Annual & perennial non-timber crops", "Livestock farming & ranching", "Hunting & collecting terrestrial animals", "Gathering terrestrial plants", "Logging & wood harvesting", "Fire & fire suppression", "Invasive non-native/alien species/diseases"] | E68: ["Agriculture & Aquaculture", "Biological Resource Use", "Natural System Modifications", "Invasive & Other Problematic Species, Genes & Diseases"] | F68: literature;survey | G68: protected_area | H68: other | I68: asia | J68: India | K68: Observational | L68: Terrestrial | M68: 1.1:DevResid;2.1:AgNTC;2.3:AgLivestock;5.1:UseAnimals;5.2:UsePlant;5.3:UseWood;7.1:FireSystem;8.1:SDAlienInv | N68: level1 | O68: NA | P68: 8 | Q68: Quantitative | R68: Qualitative | S68: NA | T68: na | U68: other | V68: other | W68: na | X68: Local | Y68: ha | Z68: 30 | AA68: FALSE
A69: 25065 | B69: =K69 -> Observational | C69: ["Terrestrial"] | D69: ["Housing & urban area", "Annual & perennial non-timber crops", "Livestock farming & ranching", "Logging & wood harvesting"] | E69: ["Agriculture & Aquaculture", "Biological Resource Use"] | F69: rs | G69: protected_area;rs | H69: plantae | I69: north america | J69: United States | K69: Observational | L69: Terrestrial | M69: 1.1:DevResid;2.1:AgNTC;2.3:AgLivestock;5.3:UseWood | N69: level2 | O69: na | P69: 4 | Q69: Qualitative | R69: qualitative | S69: NA | T69: na | U69: phylum | V69: phylum | W69: habitat | X69: Sub-national | Y69: ha | Z69: 2.25 | AA69: FALSE
A70: 24122 | B70: =K70 -> Observational | C70: ["Terrestrial"] | D70: ["Housing & urban area", "Annual & perennial non-timber crops", "Livestock farming & ranching", "Logging & wood harvesting", "Roads & railroads", "Fire & fire suppression"] | E70: ["Agriculture & Aquaculture", "Biological Resource Use", "Transportation & Service Corridors", "Natural System Modifications"] | F70: database | G70: database | H70: animalia | I70: north america | J70: United States | K70: Observational | L70: Terrestrial | M70: 1.1:DevResid;2.1:AgNTC;2.3:AgLivestock;5.3:UseWood;4.1:RoadRail;7.1:FireSystem | N70: level1 | O70: BirdofNorthAmerica; IdahoCWCS | P70: 6 | Q70: Quantitative | R70: Quantitative | S70: IdahoVertebrateMonitoringDatabase | T70: bird | U70: class | V70: class | W70: na | X70: Sub-national | Y70: m | Z70: 90 | AA70: FALSE
A71: 24867 | B71: =K71 -> Observational | C71: ["Terrestrial"] | D71: ["Housing & urban area", "Annual & perennial non-timber crops", "Livestock farming & ranching", "Recreational activities", "Roads & railroads", "Invasive non-native/alien species/diseases"] | E71: ["Agriculture & Aquaculture", "Human Intrusions & Disturbance", "Transportation & Service Corridors", "Invasive & Other Problematic Species, Genes & Diseases"] | F71: database | G71: database | H71: plantae | I71: europe | J71: Portugal | K71: Observational | L71: Terrestrial | M71: 1.1:DevResid;2.1:AgNTC;2.3:AgLivestock;6.1:ActivRnR;4.1:RoadRail;8.1:SDAlienInv | N71: level2 | O71: AzoreanRegionalForestInventory_RFI2013 | P71: 6 | Q71: Qualitative | R71: Qualitative | S71: ATLANTIS | T71: na | U71: kingdom | V71: kingdom | W71: plant | X71: Local | Y71: m | Z71: 5 | AA71: FALSE
A72: 25355 | B72: =K72 -> Observational | C72: ["Marine", "Terrestrial"] | D72: ["Housing & urban area", "Annual & perennial non-timber crops", "Marine & freshwater aquaculture"] | E72: ["Agriculture & Aquaculture"] | F72: database;literature;rs | G72: database;literature | H72: plantae | I72: asia | J72: Indonesia;Malaysia;Myanmar (Burma);Philippines;Thailand;Vietnam | K72: Observational | L72: Marine;Terrestrial | M72: 1.1:DevResid;2.1:AgNTC;2.4:Aqua | N72: level2 | O72: na | P72: 3 | Q72: Quantitative | R72: quantitative | S72: GlobalForestChangeDataset_Hansen_etal; Giri_etal_Global distirubtionOfMangroveForests | T72: na | U72: phylum | V72: phylum | W72: mangrove | X72: Multi-national | Y72: degrees | Z72: 1 | AA72: FALSE
A73: 26050 | B73: =K73 -> Observational | C73: ["Terrestrial"] | D73: ["Housing & urban area", "Annual & perennial non-timber crops", "Oil & gas drilling", "Renewable energy", "Utility & service lines"] | E73: ["Agriculture & Aquaculture", "Energy Production & Mining", "Transportation & Service Corridors"] | F73: rs | G73: literature | H73: animalia | I73: north america | J73: United States | K73: Observational | L73: Terrestrial | M73: 1.1:DevResid;2.1:AgNTC;3.1:OilGas;3.3:Renew;4.2:UtilityLine | N73: level2 | O73: na | P73: 5 | Q73: Qualitative | R73: qualitative | S73: NA | T73: reptile | U73: species | V73: species | W73: na | X73: Sub-national | Y73: m | Z73: 1 | AA73: FALSE
A74: 25862 | B74: =K74 -> Observational | C74: ["Terrestrial"] | D74: ["Housing & urban area", "Annual & perennial non-timber crops", "Roads & railroads"] | E74: ["Agriculture & Aquaculture", "Transportation & Service Corridors"] | F74: database | G74: database;protected_area | H74: plantae | I74: africa | J74: Kenya;Malawi;Rwanda;Tanzania, United Republic of;Uganda;Zambia | K74: Observational | L74: Terrestrial | M74: 1.1:DevResid;2.1:AgNTC;4.1:RoadRail | N74: cumulative | O74: beta-hybrid;sage.wise;gis-lab.info | P74: 3 | Q74: Quantitative | R74: Qualitative | S74: VanBreugal2012 | T74: na | U74: kingdom | V74: kingdom | W74: vegetation | X74: Multi-national | Y74: m | Z74: 900 | AA74: FALSE
A75: 26081 | B75: =K75 -> Observational | C75: ["Terrestrial"] | D75: ["Housing & urban area", "Annual & perennial non-timber crops", "Roads & railroads"] | E75: ["Agriculture & Aquaculture", "Transportation & Service Corridors"] | F75: literature;rs | G75: literature | H75: animalia | I75: asia | J75: India | K75: Observational | L75: Terrestrial | M75: 1.1:DevResid;2.1:AgNTC;4.1:RoadRail | N75: level1 | O75: na | P75: 3 | Q75: Qualitative | R75: qualitative | S75: NA | T75: mammal | U75: species | V75: species | W75: na | X75: Local | Y75: polygon | Z75: m | AA75: FALSE
A76: 25229 | B76: =K76 -> Observational | C76: ["Freshwater", "Terrestrial"] | D76: ["Housing & urban area", "Annual & perennial non-timber crops", "Roads & railroads"] | E76: ["Agriculture & Aquaculture", "Transportation & Service Corridors"] | F76: rs | G76: pchba | H76: other | I76: africa | J76: Malawi | K76: Observational | L76: Freshwater;Terrestrial | M76: 1.1:DevResid;2.1:AgNTC;4.1:RoadRail | N76: level2 | O76: NA | P76: 3 | Q76: Qualitative | R76: Qualitative | S76: RAMSAR | T76: na | U76: other | V76: other | W76: na | X76: Local | Y76: polygon | Z76: NA | AA76: FALSE
A77: 25444 | B77: =K77 -> Observational | C77: ["Freshwater", "Terrestrial"] | D77: ["Housing & urban area", "Annual & perennial non-timber crops", "Roads & railroads"] | E77: ["Agriculture & Aquaculture", "Transportation & Service Corridors"] | F77: rs | G77: rs | H77: plantae | I77: asia | J77: India | K77: Observational | L77: Freshwater;Terrestrial | M77: 1.1:DevResid;2.1:AgNTC;4.1:RoadRail | N77: level2 | O77: NA | P77: 3 | Q77: Qualitative | R77: Qualitative | S77: NA | T77: na | U77: phylum | V77: phylum | W77: mangrove | X77: Local | Y77: NA | Z77: NA | AA77: FALSE
A78: 25745 | B78: =K78 -> Observational | C78: ["Terrestrial"] | D78: ["Housing & urban area", "Annual & perennial non-timber crops", "Roads & railroads", "Livestock farming & ranching"] | E78: ["Agriculture & Aquaculture", "Transportation & Service Corridors"] | F78: rs | G78: rs | H78: plantae | I78: europe | J78: Spain | K78: Observational | L78: Terrestrial | M78: 1.1:DevResid;2.1:AgNTC;4.1:RoadRail;2.3:AgLivestock | N78: level2 | O78: NA | P78: 4 | Q78: Qualitative | R78: Qualitative | S78: NA | T78: na | U78: kingdom | V78: kingdom | W78: forest | X78: Sub-national | Y78: km2 | Z78: 100 | AA78: FALSE
A79: 24736 | B79: =K79 -> Observational | C79: ["Terrestrial"] | D79: ["Housing & urban area", "Wood & pulp plantations", "Roads & railroads"] | E79: ["Agriculture & Aquaculture", "Transportation & Service Corridors"] | F79: rs | G79: rs | H79: plantae | I79: north america | J79: United States | K79: Observational | L79: Terrestrial | M79: 1.1:DevResid;2.2:AgWood;2.5:AgUncpec;4.1:RoadRail | N79: level2 | O79: NA | P79: 4 | Q79: Qualitative | R79: Qualitative | S79: NA | T79: na | U79: species | V79: species | W79: pinopsida | X79: Sub-national | Y79: polygon | Z79: NA | AA79: TRUE
A80: 24661 | B80: =K80 -> Observational | C80: ["Terrestrial"] | D80: ["Housing & urban area", "Wood & pulp plantations", "Mining & quarrying", "Logging & wood harvesting"] | E80: ["Agriculture & Aquaculture", "Energy Production & Mining", "Biological Resource Use"] | F80: rs | G80: database;pchba;protected_area;rs | H80: plantae | I80: africa | J80: Cameroon | K80: Observational | L80: Terrestrial | M80: 1.1:DevResid;2.2:AgWood;3.2:MinQuar;5.3:UseWood | N80: level2 | O80: na | P80: 4 | Q80: Qualitative | R80: qualitative | S80: BiodiversityHotspot;IntactForestLandscapes_20002014 | T80: na | U80: phylum | V80: phylum | W80: forest | X80: Sub-national | Y80: m | Z80: 60 | AA80: FALSE
A81: 23185 | B81: =K81 -> Observational | C81: ["Terrestrial"] | D81: ["Housing & urban area", "Wood & pulp plantations", "Hunting & collecting terrestrial animals", "Logging & wood harvesting"] | E81: ["Agriculture & Aquaculture", "Biological Resource Use"] | F81: survey | G81: survey | H81: animalia | I81: africa | J81: Gabon | K81: Observational | L81: Terrestrial | M81: 1.1:DevResid;2.2:AgWood;5.1:UseAnimals;5.3:UseWood | N81: cumulative | O81: NA | P81: 4 | Q81: Qualitative | R81: Qualitative | S81: NA | T81: mammal | U81: species | V81: species | W81: na | X81: Local | Y81: polygon | Z81: na | AA81: FALSE
A82: 25507 | B82: =K82 -> Observational | C82: ["Terrestrial"] | D82: ["Housing & urban area", "Livestock farming & ranching"] | E82: ["Agriculture & Aquaculture"] | F82: survey | G82: survey | H82: animalia | I82: africa | J82: Kenya | K82: Observational | L82: Terrestrial | M82: 1.1:DevResid;2.3:AgLivestock | N82: level2 | O82: NA | P82: 2 | Q82: Quantitative | R82: Quantitative | S82: NA | T82: mammal | U82: species | V82: class | W82: na | X82: Local | Y82: polygon | Z82: NA | AA82: FALSE
A83: 24139 | B83: =K83 -> Observational | C83: ["Terrestrial"] | D83: ["Housing & urban area", "Livestock farming & ranching", "Roads & railroads"] | E83: ["Agriculture & Aquaculture", "Transportation & Service Corridors"] | F83: literature | G83: database;survey | H83: plantae | I83: asia | J83: China | K83: Observational | L83: Terrestrial | M83: 1.1:DevResid;2.3:AgLivestock;4.1:RoadRail | N83: cumulative | O83: QinghaiStatisticalYearbook_2015 | P83: 3 | Q83: Qualitative | R83: quantitative | S83: ChineseVirtualHerbarium_cvh.ac.cn | T83: na | U83: kingdom | V83: kingdom | W83: plant | X83: Sub-national | Y83: km2 | Z83: km2 | AA83: FALSE
A84: 24574 | B84: =K84 -> Observational | C84: ["Terrestrial"] | D84: ["Housing & urban area", "Livestock farming & ranching", "Hunting & collecting terrestrial animals", "Logging & wood harvesting"] | E84: ["Agriculture & Aquaculture", "Biological Resource Use"] | F84: expert | G84: literature | H84: animalia | I84: africa | J84: Angola;Botswana;Benin;Burundi;Chad;Congo;Zaire;Cameroon;Central African Republic;Djibouti;Equatorial Guinea;Ethiopia;Gambia, The; Gabon;Ghana;Guinea;Ivory Coast;Kenya;Liberia;Lesotho;Malawi;Mali;Eritrea; Nigeria;Niger;Rwanda;South Africa;Sierra Leone;Sudan;Togo;Tanzania, United Republic of; Uganda;Burkina Faso;Namibia;Swaziland;Zambia;Zimbabwe | K84: Observational | L84: Terrestrial | M84: 1.1:DevResid;2.3:AgLivestock;5.1:UseAnimals;5.3:UseWood | N84: level2 | O84: na | P84: 4 | Q84: Qualitative | R84: qualitative | S84: NA | T84: mammal | U84: species | V84: species | W84: na | X84: Continental | Y84: polygon | Z84: na | AA84: FALSE
A85: 23013 | B85: =K85 -> Observational | C85: ["Terrestrial"] | D85: ["Housing & urban area", "Livestock farming & ranching", "Hunting & collecting terrestrial animals", "Work & other activities"] | E85: ["Agriculture & Aquaculture", "Biological Resource Use", "Human Intrusions & Disturbance"] | F85: literature | G85: survey | H85: animalia | I85: africa | J85: Tanzania, United Republic of | K85: Observational | L85: Terrestrial | M85: 1.1:DevResid;2.3:AgLivestock;5.1:UseAnimals;6.3:Other | N85: cumulative | O85: na | P85: 4 | Q85: Qualitative | R85: Quantitative | S85: na | T85: mammal | U85: species | V85: species | W85: na | X85: Local | Y85: polygon | Z85: na | AA85: FALSE
A86: 23091 | B86: =K86 -> Observational | C86: ["Terrestrial"] | D86: ["Housing & urban area", "Marine & freshwater aquaculture"] | E86: ["Agriculture & Aquaculture"] | F86: rs | G86: protected_area;rs | H86: plantae | I86: asia | J86: India | K86: Observational | L86: Terrestrial | M86: 1.1:DevResid;2.4:Aqua;2.5:AgUncpec | N86: level2 | O86: NA | P86: 3 | Q86: Qualitative | R86: Qualitative | S86: NA | T86: na | U86: family | V86: family | W86: liliopsida | X86: Local | Y86: m | Z86: 250 | AA86: TRUE
A87: 23082 | B87: =K87 -> Observational | C87: ["Marine"] | D87: ["Housing & urban area", "Marine & freshwater aquaculture", "Fishing & harvesting aquatic resources", "Recreational activities"] | E87: ["Agriculture & Aquaculture", "Biological Resource Use", "Human Intrusions & Disturbance"] | F87: expert;literature;survey | G87: expert;literature;survey | H87: animalia;plantae | I87: mediterranean | J87: Spain | K87: Observational | L87: Marine | M87: 1.1:DevResid;2.4:Aqua;5.4:UseAquatic;6.1:ActivRnR | N87: cumulative | O87: NA | P87: 4 | Q87: Quantitative | R87: Quantitative | S87: NA | T87: fish | U87: domain | V87: domain | W87: liliopsida | X87: Sub-national | Y87: m | Z87: 300 | AA87: FALSE
A88: 23684 | B88: =K88 -> Observational | C88: ["Terrestrial"] | D88: ["Housing & urban area"] | E88: ["Agriculture & aquaculture", "Residential & commercial development"] | F88: rs | G88: rs | H88: plantae | I88: europe | J88: Portugal | K88: Observational | L88: Terrestrial | M88: 1.1:DevResid;2.5:AgUncpec | N88: level1 | O88: NA | P88: 2 | Q88: Qualitative | R88: Qualitative | S88: NA | T88: na | U88: kingdom | V88: kingdom | W88: forest;habitat | X88: Local | Y88: polygon | Z88: NA | AA88: TRUE
A89: 24101 | B89: =K89 -> Observational | C89: ["Terrestrial"] | D89: ["Housing & urban area"] | E89: ["Residential & commercial development"] | F89: literature | G89: pchba;survey | H89: plantae | I89: south america | J89: Brazil | K89: Observational | L89: Terrestrial | M89: 1.1:DevResid;2.5:AgUncpec | N89: level1 | O89: NA | P89: 2 | Q89: Qualitative | R89: Qualitative | S89: BiodiversityHotspot | T89: na | U89: kingdom | V89: kingdom | W89: forest | X89: Local | Y89: polygon | Z89: NA | AA89: TRUE
A90: 24270 | B90: =K90 -> Observational | C90: ["Terrestrial"] | D90: ["Housing & urban area"] | E90: ["Residential & commercial development"] | F90: survey | G90: survey | H90: animalia | I90: africa | J90: Comoros | K90: Observational | L90: Terrestrial | M90: 1.1:DevResid;2.5:AgUncpec | N90: level1 | O90: NA | P90: 2 | Q90: Qualitative | R90: Quantitative | S90: NA | T90: bird | U90: species | V90: species | W90: na | X90: Local | Y90: NA | Z90: NA | AA90: TRUE
A91: 24527 | B91: =K91 -> Observational | C91: ["Terrestrial"] | D91: ["Housing & urban area"] | E91: ["Residential & commercial development"] | F91: database | G91: database | H91: plantae | I91: australasia | J91: Australia | K91: Observational | L91: Terrestrial | M91: 1.1:DevResid;2.5:AgUncpec | N91: level1 | O91: GLOBCOVER_v2.3 | P91: 2 | Q91: Qualitative | R91: Qualitative | S91: GLOBCOVER_v2.3 | T91: na | U91: kingdom | V91: kingdom | W91: forest | X91: Sub-national | Y91: km2 | Z91: 1 | AA91: TRUE
A92: 25276 | B92: =K92 -> Observational | C92: ["Terrestrial"] | D92: ["Housing & urban area"] | E92: ["Residential & commercial development"] | F92: rs | G92: modelled;rs | H92: plantae | I92: asia | J92: India | K92: Observational | L92: Terrestrial | M92: 1.1:DevResid;2.5:AgUncpec | N92: level1 | O92: NA | P92: 2 | Q92: Qualitative | R92: Qualitative | S92: NA | T92: na | U92: kingdom | V92: kingdom | W92: forest;vegetation;habitat | X92: Sub-national | Y92: NA | Z92: NA | AA92: TRUE
A93: 24411 | B93: =K93 -> Observational | C93: ["Freshwater"] | D93: ["Housing & urban area"] | E93: ["Residential & commercial development"] | F93: database | G93: survey | H93: animalia | I93: north america | J93: United States | K93: Observational | L93: Freshwater | M93: 1.1:DevResid;2.5:AgUncpec | N93: level2 | O93: MRLC_2012 | P93: 2 | Q93: Quantitative | R93: Quantitative | S93: NA | T93: fish | U93: phylum | V93: phylum | W93: na | X93: Local | Y93: m | Z93: 30 | AA93: TRUE
A94: 26089 | B94: =K94 -> Observational | C94: ["Terrestrial"] | D94: ["Housing & urban area", "Mining & quarrying"] | E94: ["Agriculture & Aquaculture", "Energy Production & Mining"] | F94: rs | G94: pchba;protected_area | H94: other | I94: asia | J94: China | K94: Observational | L94: Terrestrial | M94: 1.1:DevResid;2.5:AgUncpec;3.2:MinQuar;3.4:EnergUnspec | N94: cumulative | O94: NA | P94: 4 | Q94: Qualitative | R94: Qualitative | S94: Biodiversity Hotspot | T94: na | U94: other | V94: other | W94: na | X94: Sub-national | Y94: m | Z94: 30 | AA94: TRUE
A95: 24713 | B95: =K95 -> Observational | C95: ["Terrestrial"] | D95: ["Housing & urban area", "Mining & quarrying", "Roads & railroads"] | E95: ["Agriculture & Aquaculture", "Energy Production & Mining", "Transportation & Service Corridors"] | F95: database;modelled | G95: database;literature | H95: animalia;plantae | I95: south america | J95: Argentina | K95: Observational | L95: Terrestrial | M95: 1.1:DevResid;2.5:AgUncpec;3.2:MinQuar;4.1:RoadRail | N95: cumulative | O95: HFI | P95: 4 | Q95: Quantitative | R95: qualitative | S95: NA | T95: bird;mammal | U95: species | V95: domain | W95: forest;tracheophyta | X95: Sub-national | Y95: km2 | Z95: 1 | AA95: TRUE
A96: 24945 | B96: =K96 -> Observational | C96: ["Terrestrial"] | D96: ["Housing & urban area", "Mining & quarrying", "Roads & railroads"] | E96: ["Agriculture & Aquaculture", "Energy Production & Mining", "Transportation & Service Corridors"] | F96: database | G96: protected_area | H96: other | I96: asia | J96: Iran | K96: Observational | L96: Terrestrial | M96: 1.1:DevResid;2.5:AgUncpec;3.2:MinQuar;4.1:RoadRail | N96: level2 | O96: Various | P96: 4 | Q96: Qualitative | R96: Qualitative | S96: NA | T96: na | U96: other | V96: other | W96: na | X96: Sub-national | Y96: km2 | Z96: 1 | AA96: TRUE
A97: 25645 | B97: =K97 -> Observational | C97: ["Freshwater", "Terrestrial"] | D97: ["Housing & urban area", "Roads & railroads"] | E97: ["Transportation & Service Corridors", "Agriculture & aquaculture"] | F97: rs | G97: database;protected_area | H97: plantae | I97: asia | J97: Philippines | K97: Observational | L97: Freshwater;Terrestrial | M97: 1.1:DevResid;2.5:AgUncpec;4.1:RoadRail | N97: level1 | O97: na | P97: 3 | Q97: Qualitative | R97: qualitative | S97: NA | T97: na | U97: kingdom | V97: kingdom | W97: forest | X97: Local | Y97: m | Z97: 500 | AA97: TRUE
A98: 25559 | B98: =K98 -> Observational | C98: ["Terrestrial"] | D98: ["Housing & urban area", "Roads & railroads"] | E98: ["Transportation & Service Corridors", "Agriculture & aquaculture"] | F98: rs | G98: protected_area | H98: other | I98: asia | J98: Nepal | K98: Observational | L98: Terrestrial | M98: 1.1:DevResid;2.5:AgUncpec;4.1:RoadRail | N98: level2 | O98: NA | P98: 3 | Q98: Qualitative | R98: Qualitative | S98: NA | T98: na | U98: other | V98: other | W98: na | X98: Sub-national | Y98: NA | Z98: NA | AA98: TRUE
A99: 26063 | B99: =K99 -> Observational | C99: ["Terrestrial"] | D99: ["Housing & urban area", "Roads & railroads"] | E99: ["Transportation & Service Corridors", "Agriculture & aquaculture"] | F99: rs | G99: rs | H99: plantae | I99: asia | J99: China;Laos;Vietnam;Myanmar;Thailand;Cambodia | K99: Observational | L99: Terrestrial | M99: 1.1:DevResid;2.5:AgUncpec;4.1:RoadRail | N99: level2 | O99: NA | P99: 3 | Q99: Qualitative | R99: Qualitative | S99: NA | T99: na | U99: kingdom | V99: kingdom | W99: forest;habitat | X99: Multi-national | Y99: m | Z99: 30 | AA99: TRUE
A100: 25411 | B100: =K100 -> Observational | C100: ["Terrestrial"] | D100: ["Housing & urban area", "Roads & railroads", "Fire & fire suppression"] | E100: ["Agriculture & Aquaculture", "Transportation & Service Corridors", "Natural System Modifications"] | F100: modelled | G100: pchba | H100: other | I100: africa | J100: Madagascar | K100: Observational | L100: Terrestrial | M100: 1.1:DevResid;2.5:AgUncpec;4.1:RoadRail;7.1:FireSystem | N100: cumulative | O100: na | P100: 4 | Q100: Qualitative | R100: qualitative | S100: KBAs | T100: na | U100: other | V100: other | W100: na | X100: National | Y100: polygon | Z100: km | AA100: TRUE
...

Sheet Curated - Labels
A1: Publication Type | B1: Authors | C1: Book Authors | D1: Book Editors | E1: Book Group Authors | F1: Author Full Names | G1: Book Author Full Names | H1: Group Authors | I1: Article Title | J1: Source Title | K1: Book Series Title | L1: Book Series Subtitle | M1: Language | N1: Document Type | O1: Conference Title | P1: Conference Date | Q1: Conference Location | R1: Conference Sponsor | S1: Conference Host | T1: Author Keywords | U1: Keywords Plus | V1: Abstract | W1: Addresses | X1: Affiliations | Y1: Reprint Addresses | Z1: Email Addresses | AA1: Researcher Ids | AB1: ORCIDs | AC1: Funding Orgs | AD1: Funding Name Preferred | AE1: Funding Text | AF1: Cited References | AG1: Cited Reference Count | AH1: Times Cited, WoS Core | AI1: Times Cited, All Databases | AJ1: 180 Day Usage Count | AK1: Since 2013 Usage Count | AL1: Publisher | AM1: Publisher City | AN1: Publisher Address | AO1: ISSN | AP1: eISSN | AQ1: ISBN | AR1: Journal Abbreviation | AS1: Journal ISO Abbreviation | AT1: Publication Date | AU1: Publication Year | AV1: Volume | AW1: Issue | AX1: Part Number | AY1: Supplement | AZ1: Special Issue | BA1: Meeting Abstract | BB1: Start Page | BC1: End Page | BD1: Article Number | BE1: DOI | BF1: DOI Link | BG1: Book DOI | BH1: Early Access Date | BI1: Number of Pages | BJ1: WoS Categories | BK1: Web of Science Index | BL1: Research Areas | BM1: IDS Number | BN1: Pubmed Id | BO1: Open Access Designations | BP1: Highly Cited Status | BQ1: Hot Paper Status | BR1: Date of Export | BS1: UT (Unique WOS ID) | BT1: ArticleID | BU1: study_design | BV1: realm | BW1: threats_l0 | BX1: threats_l1 | BY1: unspec_other | BZ1: threat_precision | CA1: Web of Science Record
A2: J | B2: Heinemeyer, K; Squires, J; Hebblewhite, M; O'Keefe, JJ; Holbrook, JD; Copeland, J | F2: Heinemeyer, Kimberly; Squires, John; Hebblewhite, Mark; O'Keefe, Julia J.; Holbrook, Joseph D.; Copeland, Jeffrey | I2: Wolverines in winter: indirect habitat loss and functional responses to backcountry recreation | J2: ECOSPHERE | M2: English | N2: Article | T2: functional response; Gulo gulo; habitat model; indirect habitat loss; winter recreation; wolverine | U2: GULO-GULO; RESOURCE SELECTION; ENVIRONMENTAL CONCERN; MOUNTAIN CARIBOU; MULE DEER; CONSERVATION; CLIMATE; BEHAVIOR; INFRASTRUCTURE; REGULARIZATION | V2: Outdoor recreation is increasingly recognized to impact nature and wildlife, yet few studies have examined recreation within large natural landscapes that are critical habitat to some of our most rare and potentially disturbance-sensitive species. Over six winters (2010-2015) and four study areas (>1.1 million ha) in Idaho, Wyoming, and Montana, we studied the responses of wolverines (Gulo gulo) to backcountry winter recreation. We fit Global Positioning System (GPS) collars to 24 individual wolverines and acquired >54,000 GPS locations over 39 animal-years during winter (January-April). Simultaneously, we monitored winter recreation, collecting similar to 6000 GPS tracks (similar to 200,000 km) from backcountry recreationists. We combined the GPS tracks with trail use counts and aerial recreation surveys to map the extent and relative intensity of motorized and non-motorized recreation. We integrated our wolverine and backcountry recreation data to (1) assess patterns of wolverine habitat selection and (2) evaluate the effect of backcountry recreation on wolverine habitat relationships. We used resource selection functions to model habitat selection of male and female wolverines within their home ranges. We first modeled habitat selection for environmental covariates to understand male and female habitat use then incorporated winter recreation covariates. We assessed the potential for indirect habitat loss from winter recreation and tested for functional responses of wolverines to differing levels and types of recreation. Motorized recreation occurred at higher intensity across a larger footprint than non-motorized recreation in most wolverine home ranges. Wolverines avoided areas of both motorized and non-motorized winter recreation with off-road recreation eliciting a stronger response than road-based recreation. Female wolverines exhibited stronger avoidance of off-road motorized recreation and experienced higher indirect habitat loss than male wolverines. Wolverines showed negative functional responses to the level of recreation exposure within the home range, with female wolverines showing the strongest functional response to motorized winter recreation. We suggest indirect habitat loss, particularly to females, could be of concern in areas with higher recreation levels. We speculate that the potential for backcountry winter recreation to affect wolverines may increase under dimate change if reduced snow pack concentrates winter recreationists and wolverines in the remaining areas of persistent snow cover. | W2: [Heinemeyer, Kimberly; O'Keefe, Julia J.] Round River Conservat Studies, 104 East Main St, Bozeman, MT 59715 USA; [Squires, John; Copeland, Jeffrey] US Forest Serv, Rocky Mt Res Stn, Missoula, MT 59802 USA; [Hebblewhite, Mark] Univ Montana, WA Franke Coll Forestry & Conservat, Wildlife Biol Program, Dept Ecosyst & Conservat Sci, Missoula, MT 59812 USA; [Holbrook, Joseph D.] Univ Wyoming, Haub Sch Environm & Nat Resources, Laramie, WY 82072 USA; [Copeland, Jeffrey] Wolverine Fdn, 4444 Packsaddle Rd, Tetonia, ID 83452 USA | X2: United States Department of Agriculture (USDA); United States Forest Service; University of Montana System; University of Montana; University of Wyoming | Y2: Heinemeyer, K (corresponding author), Round River Conservat Studies, 104 East Main St, Bozeman, MT 59715 USA. | Z2: kim@roundriver.org | AA2: Hebblewhite, Mark/G-6164-2013 | AB2: Hebblewhite, Mark/0000-0001-5382-1361 | AC2: U.S. Forest Service; Liz Claiborne Art Ortenberg Foundation; Round River Conservation Studies; Idaho Department of Fish and Game; Wolverine Foundation; Idaho State Snowmobile Association; Idaho Falls Zoo; Sawtooth Society; Defenders of Wildlife; University of Montana | AD2: U.S. Forest Service(United States Department of Agriculture (USDA)United States Forest Service); Liz Claiborne Art Ortenberg Foundation; Round River Conservation Studies; Idaho Department of Fish and Game; Wolverine Foundation; Idaho State Snowmobile Association; Idaho Falls Zoo; Sawtooth Society; Defenders of Wildlife; University of Montana | AE2: We thank Ana Egnew, Diane Evans Mack, Lisa Nutt, Mark Drew, Rob Cavallaro, Robin Garwood, and the many additional agency personnel who assisted us from the Payette, Boise, Sawtooth, Bridger-Teton and Caribou-Targhee National Forests, Idaho Department of Fish and Game, Nez Perce Tribe and Wyoming Game and Fish. Funding, equipment, and logistical support for the project were provided by the U.S. Forest Service, Liz Claiborne Art Ortenberg Foundation, Round River Conservation Studies, Idaho Department of Fish and Game, The Wolverine Foundation, Idaho State Snowmobile Association, Idaho Falls Zoo, Sawtooth Society, Defenders of Wildlife, and the University of Montana. Businesses also provided logistic support including Brundage Mountain Resort, Jackson Hole Mountain Resort, Grand Targhee Resort, Sun Valley Heli Ski, Teton Backcountry Guides, and numerous local businesses in the towns of Cascade, Driggs, Fairfield, Island Park, McCall, Stanley, Sun Valley and Victor in Idaho and Jackson, Wyoming. We are indebted to our many hard-working field technicians and volunteers. We also thank the thousands of volunteer recreationists who carried and returned GPS units. We thank Lucretia Olson, Dennis Sizemore, and three anonymous reviewers for reviewing earlier versions of this paper. | AG2: 91 | AH2: 63 | AI2: 75 | AJ2: 2 | AK2: 135 | AL2: WILEY | AM2: HOBOKEN | AN2: 111 RIVER ST, HOBOKEN 07030-5774, NJ USA | AO2: 2150-8925 | AR2: ECOSPHERE | AS2: Ecosphere | AT2: FEB | AU2: 2019 | AV2: 10 | AW2: 2 | BD2: e02611 | BE2: 10.1002/ecs2.2611 | BF2: =HYPERLINK("http://dx.doi.org/10.1002/ecs2.2611","http://dx.doi.org/10.1002/ecs2.2611") -> http://dx.doi.org/10.1002/ecs2.2611 | BI2: 23 | BJ2: Ecology | BK2: Science Citation Index Expanded (SCI-EXPANDED); Social Science Citation Index (SSCI) | BL2: Environmental Sciences & Ecology | BM2: HP3LA | BO2: gold | BR2: 2025-12-28 | BS2: WOS:000461577000030 | BT2: 24186 | BU2: ["Observational"] | BV2: ["Terrestrial"] | BW2: =VLOOKUP($BT2,Enriched!$A$2:$E$1070,5,false) -> ["Residential & Commercial Development", "Human Intrusions & Disturbance"] | BX2: =VLOOKUP($BT2,Enriched!$A$2:$E$1070,4,false) -> ["Tourism & recreation areas", "Recreational activities"] | BY2: =VLOOKUP(BT2,Enriched!$A$1:$AA$1070,27,falsE) -> FALSE | BZ2: =VLOOKUP(BT2,Enriched!$A$1:$AA$1070,14,falsE) -> level2 | CA2: =HYPERLINK("https%3A%2F%2Fwww.webofscience.com%2Fwos%2Fwoscc%2Ffull-record%2FWOS:000461577000030","View Full Record in Web of Science") -> View Full Record in Web of Science
A3: J | B3: Hager, SB; Cosentino, BJ; Mckay, KJ; Monson, C; Zuurdeeg, W; Blevins, B | F3: Hager, Stephen B.; Cosentino, Bradley J.; McKay, Kelly J.; Monson, Cathleen; Zuurdeeg, Walt; Blevins, Brian | I3: Window Area and Development Drive Spatial Variation in Bird-Window Collisions in an Urban Landscape | J3: PLOS ONE | M3: English | N3: Article | U3: RELATIVE IMPORTANCE; HABITAT; MORTALITY; SCALE; URBANIZATION; COMPLEXITY; DIVERSITY; LANDBIRDS; COMMUNITY | V3: Collisions with windows are an important human-related threat to birds in urban landscapes. However, the proximate drivers of collisions are not well understood, and no study has examined spatial variation in mortality in an urban setting. We hypothesized that the number of fatalities at buildings varies with window area and habitat features that influence avian community structure. In 2010 we documented bird-window collisions (BWCs) and characterized avian community structure at 20 buildings in an urban landscape in northwestern Illinois, USA. For each building and season, we conducted 21 daily surveys for carcasses and nine point count surveys to estimate relative abundance, richness, and diversity. Our sampling design was informed by experimentally estimated carcass persistence times and detection probabilities. We used linear and generalized linear mixed models to evaluate how habitat features influenced community structure and how mortality was affected by window area and factors that correlated with community structure. The most-supported model was consistent for all community indices and included effects of season, development, and distance to vegetated lots. BWCs were related positively to window area and negatively to development. We documented mortalities for 16/72 (22%) species (34 total carcasses) recorded at buildings, and BWCs were greater for juveniles than adults. Based on the most-supported model of BWCs, the median number of annual predicted fatalities at study buildings was 3 (range = 0-52). These results suggest that patchily distributed environmental resources and levels of window area in buildings create spatial variation in BWCs within and among urban areas. Current mortality estimates place little emphasis on spatial variation, which precludes a fundamental understanding of the issue. To focus conservation efforts, we illustrate how knowledge of the structural and environmental factors that influence bird-window collisions can be used to predict fatalities in the broader landscape. | W3: [Hager, Stephen B.] Augustana Coll, Dept Biol, Rock Isl, IL 61201 USA; [Cosentino, Bradley J.] Hobart & William Smith Coll, Dept Biol, Geneva, NY 14456 USA; [McKay, Kelly J.] BioEco Res & Monitoring Ctr, Hampton, IL USA | X3: Hobart & William Smith Colleges | Y3: Hager, SB (corresponding author), Augustana Coll, Dept Biol, Rock Isl, IL 61201 USA. | Z3: stevehager@augustana.edu | AC3: Quad City Audubon Society; Augustana College | AD3: Quad City Audubon Society; Augustana College | AE3: The authors received $2,400 from the Quad City Audubon Society (www.quadcityaudubon.org/) for travel expenses for carcass surveys. There is no grant number. The lead author (SBH) was awarded $ 1,000 Presidential Scholarship from Augustana College (www.augustana.edu). The funders had no role in study design, data collection and analysis, decision to publish, or preparation of the manuscript. | AG3: 58 | AH3: 71 | AI3: 90 | AJ3: 5 | AK3: 130 | AL3: PUBLIC LIBRARY SCIENCE | AM3: SAN FRANCISCO | AN3: 1160 BATTERY STREET, STE 100, SAN FRANCISCO, CA 94111 USA | AO3: 1932-6203 | AR3: PLOS ONE | AS3: PLoS One | AT3: JAN 9 | AU3: 2013 | AV3: 8 | AW3: 1 | BD3: e53371 | BE3: 10.1371/journal.pone.0053371 | BF3: =HYPERLINK("http://dx.doi.org/10.1371/journal.pone.0053371","http://dx.doi.org/10.1371/journal.pone.0053371") -> http://dx.doi.org/10.1371/journal.pone.0053371 | BI3: 10 | BJ3: Multidisciplinary Sciences | BK3: Science Citation Index Expanded (SCI-EXPANDED) | BL3: Science & Technology - Other Topics | BM3: 070YR | BN3: 23326420 | BO3: Green Submitted, gold | BR3: 2025-12-28 | BS3: WOS:000313551500067 | BT3: 24120 | BU3: ["Observational"] | BV3: ["Terrestrial"] | BW3: =VLOOKUP($BT3,Enriched!$A$2:$E$1070,5,false) -> ["Residential & commercial development"] | BX3: =VLOOKUP($BT3,Enriched!$A$2:$E$1070,4,false) | BY3: =VLOOKUP(BT3,Enriched!$A$1:$AA$1070,27,falsE) -> TRUE | BZ3: =VLOOKUP(BT3,Enriched!$A$1:$AA$1070,14,falsE) -> level1 | CA3: =HYPERLINK("https%3A%2F%2Fwww.webofscience.com%2Fwos%2Fwoscc%2Ffull-record%2FWOS:000313551500067","View Full Record in Web of Science") -> View Full Record in Web of Science
A4: J | B4: Marques, AT; Santos, CD; Hanssen, F; Munoz, AR; Onrubia, A; Wikelski, M; Moreira, F; Palmeirim, JM; Silva, JP | F4: Marques, Ana T.; Santos, Carlos D.; Hanssen, Frank; Munoz, Antonio-Roman; Onrubia, Alejandro; Wikelski, Martin; Moreira, Francisco; Palmeirim, Jorge Manuel; Silva, Joao P. | I4: Wind turbines cause functional habitat loss for migratory soaring birds | J4: JOURNAL OF ANIMAL ECOLOGY | M4: English | N4: Article | T4: aerial habitat; avoidance behaviour; migration; orographic uplift; raptor; thermal uplift; wind farms | U4: SATELLITE TRACKING; AUTUMN MIGRATION; GOLDEN EAGLES; SPACE USE; MORTALITY; FARM; REGRESSION; MOVEMENT; RAPTORS; STRAIT | V4: Wind energy production has expanded to meet climate change mitigation goals, but negative impacts of wind turbines have been reported on wildlife. Soaring birds are among the most affected groups with alarming fatality rates by collision with wind turbines and an escalating occupation of their migratory corridors. These birds have been described as changing their flight trajectories to avoid wind turbines, but this behaviour may lead to functional habitat loss, as suitable soaring areas in the proximity of wind turbines will likely be underused. We modelled the displacement effect of wind turbines on black kites (Milvus migrans) tracked by GPS. We also evaluated the impact of this effect at the scale of the landscape by estimating how much suitable soaring area was lost to wind turbines. We used state-of-the-art tracking devices to monitor the movements of 130 black kites in an area populated by wind turbines, at the migratory bottleneck of the Strait of Gibraltar. Landscape use by birds was mapped from GPS data using dynamic Brownian bridge movement models, and generalized additive mixed modelling was used to estimate the effect of wind turbine proximity on bird use while accounting for orographic and thermal uplift availability. We found that areas up to approximately 674 m away from the turbines were less used than expected given their uplift potential. Within that distance threshold, bird use decreased with the proximity to wind turbines. We estimated that the footprint of wind turbines affected 3%-14% of the areas suitable for soaring in our study area. We present evidence that the impacts of wind energy industry on soaring birds are greater than previously acknowledged. In addition to the commonly reported fatalities, the avoidance of turbines by soaring birds causes habitat losses in their movement corridors. Authorities should recognize this further impact of wind energy production and establish new regulations that protect soaring habitat. We also showed that soaring habitat for birds can be modelled at a fine scale using publicly available data. Such an approach can be used to plan low-impact placement of turbines in new wind energy developments. | W4: [Marques, Ana T.; Palmeirim, Jorge Manuel; Silva, Joao P.] Univ Lisbon, Fac Ciencias, CE3c Ctr Ecol Evolucao & Alteracoes Ambientais, P-1749016 Lisbon, Portugal; [Marques, Ana T.] Univ Lisbon, Inst Super Agron, Ctr Ecol Aplicada Prof Baeta Neves CEABN, InBio, Lisbon, Portugal; [Marques, Ana T.; Moreira, Francisco; Silva, Joao P.] Univ Porto, Ctr Invest Biodiversidade & Recursos Genet, REN Biodivers Chair, CIBIO InBio,Lab Associado, Vairao, Portugal; [Santos, Carlos D.; Wikelski, Martin] Max Planck Inst Ornithol, Dept Migrat & Immunoecol, Radolfzell am Bodensee, Germany; [Santos, Carlos D.] Univ Fed Para, Nucleo Teoria & Pesquisa Comportamento, Belem, Para, Brazil; [Hanssen, Frank] Norwegian Inst Nat Res, Trondheim, Norway; [Munoz, Antonio-Roman] Univ Malaga, Fac Ciencias, Dept Biol Anim, Biogeog Divers & Conservat Res Team, Malaga, Spain; [Onrubia, Alejandro] Fdn Migres CIMA, Cadiz, Spain; [Wikelski, Martin] Univ Konstanz, Dept Biol, Constance, Germany; [Moreira, Francisco; Silva, Joao P.] Univ Lisbon, Inst Super Agron, Ctr Invest Biodiversidade & Recursos Genet, CIBIO InBio,Lab Associado, Lisbon, Portugal | X4: Universidade de Lisboa; Universidade de Lisboa; Universidade do Porto; Max Planck Society; Universidade Federal do Para; Norwegian Institute Nature Research; Universidad de Malaga; University of Konstanz; Universidade de Lisboa | Y4: Marques, AT (corresponding author), Univ Lisbon, Fac Ciencias, CE3c Ctr Ecol Evolucao & Alteracoes Ambientais, P-1749016 Lisbon, Portugal.;Marques, AT (corresponding author), Univ Lisbon, Inst Super Agron, Ctr Ecol Aplicada Prof Baeta Neves CEABN, InBio, Lisbon, Portugal.;Marques, AT (corresponding author), Univ Porto, Ctr Invest Biodiversidade & Recursos Genet, REN Biodivers Chair, CIBIO InBio,Lab Associado, Vairao, Portugal. | Z4: ateresamarques@gmail.com | AA4: Marques, Ana Teresa/J-2585-2014; Palmeirim, Jorge/A-1323-2014; Onrubia, Alejano/G-3314-2016; Moreira, Francisco/B-2873-2008; Santos, Carlos David/E-5881-2013; Silva, João Paulo/L-6745-2013; Muñoz, Antonio-Román/K-8259-2014; Hanssen, Frank/AAW-2037-2020; Wikelski, Martin/LZF-2734-2025 | AB4: Marques, Ana Teresa/0000-0003-3279-643X; Palmeirim, Jorge/0000-0003-4734-8162; Onrubia, Alejano/0000-0001-8860-3524; Moreira, Francisco/0000-0003-4393-8018; Santos, Carlos David/0000-0001-5693-9795; Silva, João Paulo/0000-0002-1956-5779; Muñoz, Antonio-Román/0000-0002-0253-7632; Hanssen, Frank/0000-0002-0775-6340; | AG4: 70 | AH4: 103 | AI4: 126 | AJ4: 10 | AK4: 217 | AL4: WILEY | AM4: HOBOKEN | AN4: 111 RIVER ST, HOBOKEN 07030-5774, NJ USA | AO4: 0021-8790 | AP4: 1365-2656 | AR4: J ANIM ECOL | AS4: J. Anim. Ecol. | AT4: JAN | AU4: 2020 | AV4: 89 | AW4: 1 | BB4: 93 | BC4: 103 | BE4: 10.1111/1365-2656.12961 | BF4: =HYPERLINK("http://dx.doi.org/10.1111/1365-2656.12961","http://dx.doi.org/10.1111/1365-2656.12961") -> http://dx.doi.org/10.1111/1365-2656.12961 | BI4: 11 | BJ4: Ecology; Zoology | BK4: Science Citation Index Expanded (SCI-EXPANDED) | BL4: Environmental Sciences & Ecology; Zoology | BM4: KB7YZ | BN4: 30762229 | BO4: Green Submitted, Bronze | BR4: 2025-12-28 | BS4: WOS:000506707800010 | BT4: 24698 | BU4: ["Observational"] | BV4: ["Terrestrial"] | BW4: =VLOOKUP($BT4,Enriched!$A$2:$E$1070,5,false) -> ["Energy Production & Mining"] | BX4: =VLOOKUP($BT4,Enriched!$A$2:$E$1070,4,false) -> ["Renewable energy"] | BY4: =VLOOKUP(BT4,Enriched!$A$1:$AA$1070,27,falsE) -> FALSE | BZ4: =VLOOKUP(BT4,Enriched!$A$1:$AA$1070,14,falsE) -> level2 | CA4: =HYPERLINK("https%3A%2F%2Fwww.webofscience.com%2Fwos%2Fwoscc%2Ffull-record%2FWOS:000506707800010","View Full Record in Web of Science") -> View Full Record in Web of Science
A5: J | B5: Lehnert, LS; Kramer-Schadt, S; Schönborn, S; Lindecke, O; Niermann, I; Voigt, CC | F5: Lehnert, Linn S.; Kramer-Schadt, Stephanie; Schoenborn, Sophia; Lindecke, Oliver; Niermann, Ivo; Voigt, Christian C. | I5: Wind Farm Facilities in Germany Kill Noctule Bats from Near and Far | J5: PLOS ONE | M5: English | N5: Article | U5: ENERGY DEVELOPMENT; STABLE HYDROGEN; ADULT SURVIVAL; MIGRATION; MORTALITY; LASIURUS; ISOTOPES | V5: Over recent years, it became widely accepted that alternative, renewable energy may come at some risk for wildlife, for example, when wind turbines cause large numbers of bat fatalities. To better assess likely populations effects of wind turbine related wildlife fatalities, we studied the geographical origin of the most common bat species found dead below German wind turbines, the noctule bat (Nyctalus noctula). We measured stable isotope ratios of non-exchangeable hydrogen in fur keratin to separate migrants from local individuals, used a linear mixed-effects model to identify temporal, spatial and biological factors explaining the variance in measured stable isotope ratios and determined the geographical breeding provenance of killed migrants using isoscape origin models. We found that 72% of noctule bat casualties (n = 136) were of local origin, while 28% were long-distance migrants. These findings highlight that bat fatalities at German wind turbines may affect both local and distant populations. Our results indicated a sex and age-specific vulnerability of bats towards lethal accidents at turbines, i.e. a relatively high proportion of killed females were recorded among migratory individuals, whereas more juveniles than adults were recorded among killed bats of local origin. Migratory noctule bats were found to originate from distant populations in the Northeastern parts of Europe. The large catchment areas of German wind turbines and high vulnerability of female and juvenile noctule bats call for immediate action to reduce the negative cross-boundary effects of bat fatalities at wind turbines on local and distant populations. Further, our study highlights the importance of implementing effective mitigation measures and developing species and scale-specific conservation approaches on both national and international levels to protect source populations of bats. The efficacy of local compensatory measures appears doubtful, at least for migrant noctule bats, considering the large geographical catchment areas of German wind turbines for this species. | W5: [Lehnert, Linn S.; Kramer-Schadt, Stephanie; Schoenborn, Sophia; Lindecke, Oliver; Voigt, Christian C.] Leibniz Inst Zoo & Wildlife Res, Dept Evolutionary Ecol, Berlin, Germany; [Lindecke, Oliver] Univ Halle Wittenberg, Cent Repository Nat Sci Collect, D-06108 Halle, Saale, Germany; [Niermann, Ivo] Leibniz Univ Hannover, Inst Environm Planning, D-30167 Hannover, Germany | X5: Leibniz Institut fur Zoo und Wildtierforschung; Martin Luther University Halle Wittenberg; Leibniz University Hannover | Y5: Lehnert, LS (corresponding author), Leibniz Inst Zoo & Wildlife Res, Dept Evolutionary Ecol, Berlin, Germany. | Z5: lehnert@izw-berlin.de | AA5: Lindecke, Oliver/Z-4304-2019; Kramer-Schadt, Stephanie/A-8778-2013; Lehnert, Linn/E-2941-2016 | AB5: Lindecke, Oliver/0000-0002-2545-9999; Kramer-Schadt, Stephanie/0000-0002-9269-4446; | AC5: Federal State of Berlin (Elsa-Neumann-Stipendium) | AD5: Federal State of Berlin (Elsa-Neumann-Stipendium) | AE5: We would like to thank Anja Luckner and Karin Sorgel from the IZW stable isotope laboratory for isotope analyses. We are indebted to Tobias Durr (Staatliche Vogelschutzwarte Buckow) for making fur samples available and thank Burkhard Lehmann and colleagues from MYOTIS - Buro fur Landschaftsokologie for support during fieldwork. Linn Sophia Lehnert was supported by the PhD student grant of the Federal State of Berlin (Elsa-Neumann-Stipendium). | AG5: 42 | AH5: 86 | AI5: 97 | AJ5: 1 | AK5: 104 | AL5: PUBLIC LIBRARY SCIENCE | AM5: SAN FRANCISCO | AN5: 1160 BATTERY STREET, STE 100, SAN FRANCISCO, CA 94111 USA | AO5: 1932-6203 | AR5: PLOS ONE | AS5: PLoS One | AT5: AUG 13 | AU5: 2014 | AV5: 9 | AW5: 8 | BD5: e103106 | BE5: 10.1371/journal.pone.0103106 | BF5: =HYPERLINK("http://dx.doi.org/10.1371/journal.pone.0103106","http://dx.doi.org/10.1371/journal.pone.0103106") -> http://dx.doi.org/10.1371/journal.pone.0103106 | BI5: 8 | BJ5: Multidisciplinary Sciences | BK5: Science Citation Index Expanded (SCI-EXPANDED) | BL5: Science & Technology - Other Topics | BM5: AN9BM | BN5: 25118805 | BO5: Green Submitted, gold | BR5: 2025-12-28 | BS5: WOS:000340900600017 | BT5: 24511 | BU5: ["Observational"] | BV5: ["Terrestrial"] | BW5: =VLOOKUP($BT5,Enriched!$A$2:$E$1070,5,false) -> ["Energy Production & Mining"] | BX5: =VLOOKUP($BT5,Enriched!$A$2:$E$1070,4,false) -> ["Renewable energy"] | BY5: =VLOOKUP(BT5,Enriched!$A$1:$AA$1070,27,falsE) -> FALSE | BZ5: =VLOOKUP(BT5,Enriched!$A$1:$AA$1070,14,falsE) -> level2 | CA5: =HYPERLINK("https%3A%2F%2Fwww.webofscience.com%2Fwos%2Fwoscc%2Ffull-record%2FWOS:000340900600017","View Full Record in Web of Science") -> View Full Record in Web of Science
A6: J | B6: Fargione, J; Kiesecker, J; Slaats, MJ; Olimb, S | F6: Fargione, Joseph; Kiesecker, Joseph; Slaats, M. Jan; Olimb, Sarah | I6: Wind and Wildlife in the Northern Great Plains: Identifying Low-Impact Areas for Wind Development | J6: PLOS ONE | M6: English | N6: Article | U6: ENERGY FACILITIES; MORTALITY; BAT; FATALITIES | V6: Wind energy offers the potential to reduce carbon emissions while increasing energy independence and bolstering economic development. However, wind energy has a larger land footprint per Gigawatt (GW) than most other forms of energy production and has known and predicted adverse effects on wildlife. The Northern Great Plains (NGP) is home both to some of the world's best wind resources and to remaining temperate grasslands, the most converted and least protected ecological system on the planet. Thus, appropriate siting and mitigation of wind development is particularly important in this region. Steering energy development to disturbed lands with low wildlife value rather than placing new developments within large and intact habitats would reduce impacts to wildlife. Goals for wind energy development in the NGP are roughly 30 GW of nameplate capacity by 2030. Our analyses demonstrate that there are large areas where wind development would likely have few additional impacts on wildlife. We estimate there are similar to 1,056 GW of potential wind energy available across the NGP on areas likely to have low-impact for biodiversity, over 35 times development goals. New policies and approaches will be required to guide wind energy development to low-impact areas. | W6: [Fargione, Joseph; Slaats, M. Jan] Nature Conservancy, Minneapolis, MN USA; [Kiesecker, Joseph] Nature Conservancy, Ft Collins, CO USA; [Olimb, Sarah] World Wildlife Fund, Bozeman, MT USA | X6: Nature Conservancy; Nature Conservancy; World Wildlife Fund | Y6: Fargione, J (corresponding author), Nature Conservancy, Minneapolis, MN USA. | Z6: jfargione@TNC.ORG | AA6: Olimb, Sarah/IAN-0014-2023 | AB6: Olimb, Sarah/0000-0001-5714-6586; Fargione, Joseph/0000-0002-0636-5380 | AG6: 60 | AH6: 51 | AI6: 57 | AJ6: 0 | AK6: 79 | AL6: PUBLIC LIBRARY SCIENCE | AM6: SAN FRANCISCO | AN6: 1160 BATTERY STREET, STE 100, SAN FRANCISCO, CA 94111 USA | AO6: 1932-6203 | AR6: PLOS ONE | AS6: PLoS One | AT6: JUL 25 | AU6: 2012 | AV6: 7 | AW6: 7 | BD6: e41468 | BE6: 10.1371/journal.pone.0041468 | BF6: =HYPERLINK("http://dx.doi.org/10.1371/journal.pone.0041468","http://dx.doi.org/10.1371/journal.pone.0041468") -> http://dx.doi.org/10.1371/journal.pone.0041468 | BI6: 14 | BJ6: Multidisciplinary Sciences | BK6: Science Citation Index Expanded (SCI-EXPANDED) | BL6: Science & Technology - Other Topics | BM6: 979GX | BN6: 22848505 | BO6: Green Submitted, gold | BR6: 2025-12-28 | BS6: WOS:000306806600070 | BT6: 23866 | BU6: ["Observational"] | BV6: ["Terrestrial"] | BW6: =VLOOKUP($BT6,Enriched!$A$2:$E$1070,5,false) -> ["Agriculture & Aquaculture", "Energy Production & Mining", "Residential & Commercial Development"] | BX6: =VLOOKUP($BT6,Enriched!$A$2:$E$1070,4,false) -> ["Annual & perennial non-timber crops", "Oil & gas drilling", "Mining & quarrying"] | BY6: =VLOOKUP(BT6,Enriched!$A$1:$AA$1070,27,falsE) -> TRUE | BZ6: =VLOOKUP(BT6,Enriched!$A$1:$AA$1070,14,falsE) -> cumulative | CA6: =HYPERLINK("https%3A%2F%2Fwww.webofscience.com%2Fwos%2Fwoscc%2Ffull-record%2FWOS:000306806600070","View Full Record in Web of Science") -> View Full Record in Web of Science
A7: J | B7: Shilling, FM; Waetjen, DP | F7: Shilling, Fraser M.; Waetjen, David P. | I7: Wildlife-vehicle collision hotspots at US highway extents: scale and data source effects | J7: NATURE CONSERVATION-BULGARIA | M7: English | N7: Article; Proceedings Paper | O7: IENE International Conference on Ecology and Transportation | P7: SEP 16-19, 2014 | Q7: Malmo Univ, Malmo, SWEDEN | R7: IENE,Swedish Transport Adm,Swedish Univ Agr Sci,Danish Road Directorate,Calluna AB | S7: Malmo Univ | T7: Transportation; Wildlife-Vehicle Collisions; Roadkill; Informatics; Citizen Science; Wildlife Observation; Wildlife Movement | U7: CITIZEN-SCIENCE; ROAD-MORTALITY; SPATIAL-ANALYSIS; IDENTIFICATION; CONSERVATION; ACCIDENTS; ABUNDANCE; ACCURACY; RISK; TOOL | V7: Highways provide commuter traffic and goods movement among regions and cities through wild, protected areas. Wildlife-vehicle collisions (WVC) can occur frequently when wildlife are present, impacting drivers and animals. Because collisions are often avoidable with constructed mitigation and reduced speeds, transportation agencies often want to know where they can act most effectively and what kinds of mitigation are cost-effective. For this study, WVC occurrences were obtained from two sources: 1) highway agencies that monitor carcass retrieval and disposal by agency maintenance staff and 2) opportunistic observations of carcasses by participants in two statewide systems, the California Roadkill Observation System (CROS; http://wildlifecrossing.net/california) and the Maine Audubon Wildlife Road Watch (MAWRW; http://wildlifecrossing.net/maine). Between September, 2009 and December 31, 2014, >33,700 independent observations of >450 vertebrate species had been recorded in these online, form-based informatics systems by >1,300 observers. We asked whether or not WVC observations collected by these extensive, volunteer-science networks could be used to inform transportation-mitigation planning. Cluster analyses of volunteer-observed WVC were performed using spatial autocorrelation tests for parts or all of 34 state highways and interstates. Statistically-significant WVC hotspots were modeled using the Getis-Ord Gi* statistic. High density locations of WVC, that were not necessarily hotspots, were also visualized. Statistically-significant hotspots were identified along similar to 7,900 km of highways. These hotspots are shown to vary in position from year to year. For highways with frequent deer-vehicle collisions, annual costs from collisions ranged from US$0 to >US$30,000/km. Carcass clusters from volunteer data had very little or no overlap with similar findings from agency-collected WVC data, during a different time-range. We show that both state agency-collected and volunteer-collection of WVC observations could be useful in prioritizing mitigation action at US state-scales by state transportation agencies to protect biodiversity and driver safety Because of the spatial extent and taxonomic accuracy at which volunteer observations can be collected, these may be the most important source of data for transportation agencies to protect drivers and wildlife. | W7: [Shilling, Fraser M.; Waetjen, David P.] Univ Calif Davis, Dept Environm Sci & Policy, Davis, CA 95616 USA | X7: University of California System; University of California Davis | Y7: Shilling, FM (corresponding author), Univ Calif Davis, Dept Environm Sci & Policy, One Shields Ave, Davis, CA 95616 USA. | Z7: fmshilling@ucdavis.edu | AG7: 52 | AH7: 44 | AI7: 57 | AJ7: 2 | AK7: 38 | AL7: PENSOFT PUBLISHERS | AM7: SOFIA | AN7: 12 PROF GEORGI ZLATARSKI ST, SOFIA, 1700, BULGARIA | AO7: 1314-6947 | AP7: 1314-3301 | AR7: NAT CONSERV-BULGARIA | AS7: Nat. Conserv.-Bulgaria | AU7: 2015 | AW7: 11 | AZ7: SI | BB7: 41 | BC7: 60 | BE7: 10.3897/natureconservation.11.4438 | BF7: =HYPERLINK("http://dx.doi.org/10.3897/natureconservation.11.4438","http://dx.doi.org/10.3897/natureconservation.11.4438") -> http://dx.doi.org/10.3897/natureconservation.11.4438 | BI7: 20 | BJ7: Biodiversity Conservation | BK7: Science Citation Index Expanded (SCI-EXPANDED); Conference Proceedings Citation Index - Science (CPCI-S) | BL7: Biodiversity & Conservation | BM7: CO8VB | BO7: Green Submitted, gold | BR7: 2025-12-28 | BS7: WOS:000359449200005 | BT7: 25567 | BU7: ["Observational"] | BV7: ["Terrestrial"] | BW7: =VLOOKUP($BT7,Enriched!$A$2:$E$1070,5,false) -> ["Transportation & Service Corridors"] | BX7: =VLOOKUP($BT7,Enriched!$A$2:$E$1070,4,false) -> ["Roads & railroads"] | BY7: =VLOOKUP(BT7,Enriched!$A$1:$AA$1070,27,falsE) -> FALSE | BZ7: =VLOOKUP(BT7,Enriched!$A$1:$AA$1070,14,falsE) -> level2 | CA7: =HYPERLINK("https%3A%2F%2Fwww.webofscience.com%2Fwos%2Fwoscc%2Ffull-record%2FWOS:000359449200005","View Full Record in Web of Science") -> View Full Record in Web of Science
A8: J | B8: Filius, J; van der Hoek, Y; Jarrín-V, P; van Hooft, P | F8: Filius, Jonathan; van der Hoek, Yntze; Jarrin-V, Pablo; van Hooft, Pim | I8: Wildlife roadkill patterns in a fragmented landscape of the Western Amazon | J8: ECOLOGY AND EVOLUTION | M8: English | N8: Article | T8: Amazon; herpetofauna; hotspots; road ecology; roadkill; spatial patterns | U8: VEHICLE COLLISIONS; ECUADORIAN AMAZON; MODEL SELECTION; MORTALITY RISK; HOT-SPOTS; ECOLOGY; HIGHWAYS; FOREST; DEFORESTATION; BIODIVERSITY | V8: One of the most evident and direct effects of roads on wildlife is the death of animals by vehicle collision. Understanding the spatial patterns behind roadkill helps to plan mitigation measures to reduce the impacts of roads on animal populations. However, although roadkill patterns have been extensively studied in temperate zones, the potential impacts of roads on wildlife in the Neotropics have received less attention and are particularly poorly understood in the Western Amazon. Here, we present the results of a study on roadkill in the Amazon region of Ecuador; a region that is affected by a rapidly increasing development of road infrastructure. Over the course of 50 days, in the wet season between September and November 2017, we searched for road-killed vertebrates on 15.9 km of roads near the city of Tena, Napo province, for a total of 1,590 surveyed kilometers. We recorded 593 dead specimens, predominantly reptiles (237 specimens, 40%) and amphibians (190, 32%), with birds (102, 17%) and mammals (64, 11%) being less common. Recorded species were assigned to three functional groups, based on their movement behavior and habitat use (slow, intermediate, and fast). Using Ripley's K statistical analyses and 2D HotSpot Identification Analysis, we found multiple distinct spatial clusters or hotspots, where roadkill was particularly frequent. Factors that potentially determined these clusters, and the prevalence of roadkill along road segments in general, differed between functional groups, but often included land cover variables such as native forest and waterbodies, and road characteristics such as speed limit (i.e., positive effect on roadkill frequency). Our study, which provides a first summary of species that are commonly found as roadkill in this part of the Amazon region, contributes to a better understanding of the negative impacts of roads on wildlife and is an important first step toward conservation efforts to mitigate these impacts. | W8: [Filius, Jonathan; van Hooft, Pim] Wageningen Univ & Res, Wildlife Ecol & Conservat Grp, Wageningen, Netherlands; [van der Hoek, Yntze] Univ Reg Amazonica Ikiam, Tena, Ecuador; [van der Hoek, Yntze] Dian Fossey Gorilla Fund Int, Musanze, Rwanda; [Jarrin-V, Pablo] Univ Reg Amazonica Ikiam, Grp Poblac & Ambiente, Tena, Ecuador | X8: Wageningen University & Research | Y8: Filius, J (corresponding author), Wageningen Univ & Res, Wildlife Ecol & Conservat Grp, Wageningen, Netherlands. | Z8: filiusjonathan@gmail.com | AB8: Jarrín-V, Pablo/0000-0002-7431-0381; Filius, Jonathan/0000-0002-1292-955X | AG8: 84 | AH8: 44 | AI8: 51 | AJ8: 3 | AK8: 46 | AL8: WILEY | AM8: HOBOKEN | AN8: 111 RIVER ST, HOBOKEN 07030-5774, NJ USA | AO8: 2045-7758 | AR8: ECOL EVOL | AS8: Ecol. Evol. | AT8: JUL | AU8: 2020 | AV8: 10 | AW8: 13 | BB8: 6623 | BC8: 6635 | BE8: 10.1002/ece3.6394 | BF8: =HYPERLINK("http://dx.doi.org/10.1002/ece3.6394","http://dx.doi.org/10.1002/ece3.6394") -> http://dx.doi.org/10.1002/ece3.6394 | BH8: JUN 2020 | BI8: 13 | BJ8: Ecology; Evolutionary Biology | BK8: Science Citation Index Expanded (SCI-EXPANDED) | BL8: Environmental Sciences & Ecology; Evolutionary Biology | BM8: NG3SX | BN8: 32724537 | BO8: Green Submitted, gold | BR8: 2025-12-28 | BS8: WOS:000541248700001 | BT8: 23903 | BU8: ["Observational"] | BV8: ["Terrestrial"] | BW8: =VLOOKUP($BT8,Enriched!$A$2:$E$1070,5,false) -> ["Transportation & Service Corridors"] | BX8: =VLOOKUP($BT8,Enriched!$A$2:$E$1070,4,false) -> ["Roads & railroads"] | BY8: =VLOOKUP(BT8,Enriched!$A$1:$AA$1070,27,falsE) -> FALSE | BZ8: =VLOOKUP(BT8,Enriched!$A$1:$AA$1070,14,falsE) -> level2 | CA8: =HYPERLINK("https%3A%2F%2Fwww.webofscience.com%2Fwos%2Fwoscc%2Ffull-record%2FWOS:000541248700001","View Full Record in Web of Science") -> View Full Record in Web of Science
A9: J | B9: Ghorbani, A; Gravendeel, B; Naghibi, F; de Boer, H | F9: Ghorbani, Abdolbaset; Gravendeel, Barbara; Naghibi, Farzaneh; de Boer, Hugo | I9: Wild orchid tuber collection in Iran: a wake-up call for conservation | J9: BIODIVERSITY AND CONSERVATION | M9: English | N9: Article | T9: Salep; Orchidaceae; Anacamptis; Orchis; Dactylorhiza; Sustainability; CITES | U9: TRADE; SALEP | V9: Wild orchids are traditionally harvested as Salep and used in traditional medicine and ice-cream production in Iran. Recently however, illegal harvest of wild orchids for export appears to have grown. This study aimed to: (1) determine the diversity of harvested wild orchid species and their collection sites in Iran; and (2) study the current harvest status and trade chain and volume to estimate the total orchid plant extraction from natural populations. Field surveys of collectors and market surveys of traders were conducted to establish the diversity of collected species, to identify harvest hotspots, and to document harvesting and trade volumes. Sixteen species and subspecies from 7 genera of Orchidaceae are collected for their tubers. Based on estimates from the 2013 April to June harvest season more than 24.5 tons of fresh tubers were collected from three districts in Golestan province alone. It is estimated that this amount of tuber requires the lethal destructive harvesting of 5.5 -6.1 million orchids, with a market value of 320,000 USD. In the Tehran Bazar Salep trade during May-July 2013 was 1.9 tons of dried tubers, with estimated retail value of 310,000 USD. Current orchid collection practices in Iran, which have soared in recent years due to international demand, do not seem sustainable as all tubers are collected destructively. To preserve orchid populations, in the longterm, establishment of specific Orchid Conservation Areas and introduction of sustainable production practices, could alleviate harvesting pressure. In the midterm, development of a DNA barcoding-based molecular identification system could help to monitor and control illegal trade. In the near term, effective implementation of collection bans in excessively harvested areas and strengthening of current regulations are necessary to avoid the catastrophic effects of harvesting on orchid populations, as has been observed in Turkey. | W9: [Ghorbani, Abdolbaset; de Boer, Hugo] Uppsala Univ, Dept Organismal Biol, Evolutionary Biol Ctr, Uppsala, Sweden; [Gravendeel, Barbara; de Boer, Hugo] Nat Biodivers Ctr, Leiden, Netherlands; [Gravendeel, Barbara] Univ Appl Sci, Leiden, Netherlands; [Ghorbani, Abdolbaset; Naghibi, Farzaneh] Shaheed Beheshti Univ Med Sci, Tradit Med & Mat Med Res Ctr, Tehran, Iran; [de Boer, Hugo] Univ Oslo, Nat Hist Museum, Oslo, Norway | X9: Uppsala University; Naturalis Biodiversity Center; Shahid Beheshti University Medical Sciences; University of Oslo | Y9: de Boer, H (corresponding author), Uppsala Univ, Dept Organismal Biol, Evolutionary Biol Ctr, Uppsala, Sweden. | Z9: hugo.deboer@ebc.uu.se | AA9: Naghibi, Fereydoun/AFS-3715-2022; de Boer, Hugo/AAS-7585-2020; de Boer, Hugo/B-5640-2015 | AB9: Gravendeel, Barbara/0000-0002-6508-0895; de Boer, Hugo/0000-0003-1985-7859 | AC9: Carl Tryggers Foundation for Scientific Research; Netherlands Organisation for Scientific Research (NWO) | AD9: Carl Tryggers Foundation for Scientific Research; Netherlands Organisation for Scientific Research (NWO)(Netherlands Organization for Scientific Research (NWO)) | AE9: The authors are indebted to local plant collectors and traders for their cordiality and cooperation. We also gratefully acknowledge the Carl Tryggers Foundation for Scientific Research for providing a postdoctoral research stipend to AG (through HdB). HdB is a research fellow at Naturalis financed by the Netherlands Organisation for Scientific Research (NWO). Further support for fieldwork was gratefully received from an Anne S. Chatham fellowship of the Garden Club of America (AG), Sven och Dagmar Salens stiftelse (HdB), Lars Hiertas Minne (HdB) and the Swedish Science Council Swedish Research Links program (HdB). In Memoriam: Farzaneh Naghibi passed away in early 2014. She was an inspiration to all of us, as well as to a generation of Iranian researchers in ethnobotany and pharmacognosy. She will be remembered for her focus on quality and innovative research and her openhearted hospitality. She was an active coach for young researchers both male and female, providing opportunities for aspiring students to fulfill their ambitions, show their dedication, and develop their independence. | AG9: 18 | AH9: 62 | AI9: 70 | AJ9: 0 | AK9: 64 | AL9: SPRINGER | AM9: DORDRECHT | AN9: VAN GODEWIJCKSTRAAT 30, 3311 GZ DORDRECHT, NETHERLANDS | AO9: 0960-3115 | AP9: 1572-9710 | AR9: BIODIVERS CONSERV | AS9: Biodivers. Conserv. | AT9: OCT | AU9: 2014 | AV9: 23 | AW9: 11 | BB9: 2749 | BC9: 2760 | BE9: 10.1007/s10531-014-0746-y | BF9: =HYPERLINK("http://dx.doi.org/10.1007/s10531-014-0746-y","http://dx.doi.org/10.1007/s10531-014-0746-y") -> http://dx.doi.org/10.1007/s10531-014-0746-y | BI9: 12 | BJ9: Biodiversity Conservation; Ecology; Environmental Sciences | BK9: Science Citation Index Expanded (SCI-EXPANDED) | BL9: Biodiversity & Conservation; Environmental Sciences & Ecology | BM9: AO1OB | BR9: 2025-12-28 | BS9: WOS:000341081400005 | BT9: 24024 | BU9: ["Observational"] | BV9: ["Terrestrial"] | BW9: =VLOOKUP($BT9,Enriched!$A$2:$E$1070,5,false) -> ["Biological resource use"] | BX9: =VLOOKUP($BT9,Enriched!$A$2:$E$1070,4,false) -> ["Gathering terrestrial plants"] | BY9: =VLOOKUP(BT9,Enriched!$A$1:$AA$1070,27,falsE) -> FALSE | BZ9: =VLOOKUP(BT9,Enriched!$A$1:$AA$1070,14,falsE) -> level2 | CA9: =HYPERLINK("https%3A%2F%2Fwww.webofscience.com%2Fwos%2Fwoscc%2Ffull-record%2FWOS:000341081400005","View Full Record in Web of Science") -> View Full Record in Web of Science
